Workbook

Sheet FK Map
A1: S.No. | B1: Table | C1: Column | D1: Reference Table | E1: Reference Column | F1: Cardinality
A2: 1 | B2: Sales_SKU | C2: SKU Code | D2: Material Master | E2: SKU Code | F2: One to one
A3: 2 | B3: Sales_SKU | C3: plant | D3: Plants | E3: plant_code | F3: Many to one
A4: 3 | B4: Sales_SKU | C4: market_eligibility | D4: Regions | E4: region_id | F4: Many to one
A5: 4 | B5: Purchase_SKU | C5: SKU code | D5: Material Master | E5: SKU Code | F5: One to one
A6: 5 | B6: Countries | C6: region_id | D6: Regions | E6: region_id | F6: Many to one
A7: 6 | B7: Customers | C7: country_iso | D7: Countries | E7: iso_code | F7: Many to one
A8: 7 | B8: Customers | C8: customer_region_id | D8: Regions | E8: region_id | F8: Many to one
A9: 8 | B9: SLA Profiles | C9: scope_region_id | D9: Regions | E9: region_id | F9: Many to one
A10: 9 | B10: Lines | C10: plant_id | D10: Plants | E10: plant_code | F10: Many to one
A11: 10 | B11: Bins | C11: node_id | D11: Storage Nodes | E11: node_id | F11: Many to one
A12: 11 | B12: LSP Master List | C12: base_node_id | D12: Storage Nodes | E12: node_id | F12: Many to one
A13: 12 | B13: LSP Master List | C13: coverage_nodes | D13: Storage Nodes | E13: node_id | F13: Many to one
... A55: 54 | B55: Lessons | C55: Review ID | D55: Review Events | E55: Review Event ID | F55: Many to one

Sheet Material Master
A1: SKU Code (Primary Key) | B1: cas_number | C1: hazard_class | D1: shelf_life_months
A2: ESS-ACETYL-ETHACE-LM-98.5-NEAT-BULK-DST | B2: 141-78-6 | C2: Flam. Liq. 2 | D2: 24
A3: ESS-ACETYL-ETHACE-LM-98.5-NEAT-BULK-DST | B3: 141-78-6 | C3: Flam. Liq. 2 | D3: 24
A4: ESS-ACETYL-ETHACE-LM-98.5-NEAT-BULK-DST | B4: 141-78-6 | C4: Flam. Liq. 2 | D4: 24
A5: SPI-ACETYL-ACEANH-PH-98.6-NEAT-DR200_UN-MHD | B5: 108-24-7 | C5: Skin Corr. 1B | D5: 24
A6: SPI-ACETYL-ACEANH-PH-98.6-NEAT-DR200_UN-MHD | B6: 108-24-7 | C6: Skin Corr. 1B | D6: 24
A7: SPI-ACETYL-ACEANH-PH-98.6-NEAT-DR200_UN-MHD | B7: 108-24-7 | C7: Skin Corr. 1B | D7: 24
A8: SPI-ACETYL-ACE-IND-98.4-NEAT-ISO20-LTE | B8: 75-07-0 | C8: Flam. Liq. 2; Acute Tox. 3 | D8: 12
A9: SPI-ACETYL-ACE-IND-98.4-NEAT-ISO20-LTE | B9: 75-07-0 | C9: Flam. Liq. 2; Acute Tox. 3 | D9: 12
A10: SPI-ACETYL-ACE-IND-98.4-NEAT-ISO20-LTE | B10: 75-07-0 | C10: Flam. Liq. 2; Acute Tox. 3 | D10: 12
A11: ESS-ACETYL-BUTACE-TECH-98.3-NEAT-DR200-DHJ | B11: 123-86-4 | C11: Flam. Liq. 3 | D11: 24
A12: ESS-ACETYL-BUTACE-TECH-98.3-NEAT-DR200-DHJ | B12: 123-86-4 | C12: Flam. Liq. 3 | D12: 24
A13: ESS-ACETYL-BUTACE-TECH-98.3-NEAT-DR200-DHJ | B13: 123-86-4 | C13: Flam. Liq. 3 | D13: 24
... A130: RM-DIK-ET-88412 | B130: 674-82-8 | C130: Flam. Liq. 2 | D130: 12
A131: INT-KET-INS-145120 | B131: 463-51-4 | C131: Flam. Gas 1; Acute Tox. 2
A132: INT-DKD-INT-342781 | C132: Flam. Liq. 3 | D132: 12
A133: INT-ARY-INT-558903 | C133: Skin Irrit. 2 | D133: 12
A134: INT-FLR-BLK-903117 | C134: DG (Fluoro) | D134: 12
A135: RM-SUL-AC-10477 | B135: 7664-93-9 | C135: Skin Corr. 1A | D135: 36
A136: RM-HCL-32-65019 | B136: 7647-01-0 | C136: Skin Corr. 1B | D136: 24
A137: RM-NAO-CP-77811 | B137: 1310-73-2 | C137: Skin Corr. 1A | D137: 36
A138: RM-ACN-SV-33120 | B138: 75-05-8 | C138: Flam. Liq. 2 | D138: 36
A139: RM-TOL-SV-90412 | B139: 108-88-3 | C139: Flam. Liq. 2 | D139: 36
A140: RM-MEO-SV-11024 | B140: 67-56-1 | C140: Flam. Liq. 2; Acute Tox. 3 | D140: 36
A141: RM-PDH-CB-61302 | B141: 7440-05-3 | D141: 36
A142: RM-PTC-CAT-27190 | B142: 1643-19-2 | C142: Acute Tox. 4 | D142: 36
A143: PACK-DRM-HD-20001
A144: PACK-IBC-IB-10002
A145: PACK-BAG-PP-25003
A146: PACK-LIN-FX-12004
A147: PACK-SEA-DR-33005
A148: INT-ACE-ANH-772001 | B148: 108-24-7 | C148: Skin Corr. 1B | D148: 12
A149: INT-AAA-EMM-990812 | D149: 12

Sheet Sales_SKU
A1: FG_Primary Key | B1: SKU Code (FK) | C1: business_unit | D1: Product family | E1: Product Sub-group (molecule_name) | F1: Variant (grade) | G1: Spec 1 (key_specs_assay_pct) | H1: Spec 2 (key_specs_moisture_ppm) | I1: Spec 3 (key_specs_color_apha) | J1: form | K1: packaging | L1: plant (plant FK) | M1: market_eligibility (regions FK) | N1: regulatory_set_id
A2: FG01 | B2: ESS-ACETYL-ETHACE-LM-98.5-NEAT-BULK-DST | C2: Essentials | D2: ACETYL | E2: Ethyl Acetate | F2: LM | G2: 98.3 | H2: 233 | I2: 17 | J2: =IF(ISNUMBER(SEARCH("-NEAT-",Sales_SKU!$B2)),"Neat",IF(ISNUMBER(SEARCH("-PWD-",Sales_SKU!$B2)),"powder","")) -> Neat | K2: BULK | L2: DST | M2: IN | N2: REG-IN-ACETYL-LM
A3: FG02 | B3: ESS-ACETYL-ETHACE-LM-98.5-NEAT-BULK-DST | C3: Essentials | D3: ACETYL | E3: Ethyl Acetate | F3: LM | G3: 98.3 | H3: 246 | I3: 19 | J3: =IF(ISNUMBER(SEARCH("-NEAT-",Sales_SKU!$B3)),"Neat",IF(ISNUMBER(SEARCH("-PWD-",Sales_SKU!$B3)),"powder","")) -> Neat | K3: BULK | L3: DST | M3: EU | N3: REG-EU-ACETYL-LM
A4: FG03 | B4: ESS-ACETYL-ETHACE-LM-98.5-NEAT-BULK-DST | C4: Essentials | D4: ACETYL | E4: Ethyl Acetate | F4: LM | G4: 98.3 | H4: 259 | I4: 23 | J4: =IF(ISNUMBER(SEARCH("-NEAT-",Sales_SKU!$B4)),"Neat",IF(ISNUMBER(SEARCH("-PWD-",Sales_SKU!$B4)),"powder","")) -> Neat | K4: BULK | L4: DST | M4: APAC | N4: REG-APAC-ACETYL-LM
A5: FG04 | B5: SPI-ACETYL-ACEANH-PH-98.6-NEAT-DR200_UN-MHD | C5: Specialties | D5: ACETYL | E5: Acetic Anhydride | F5: PH | G5: 98.8 | H5: 139 | I5: 8 | J5: =IF(ISNUMBER(SEARCH("-NEAT-",Sales_SKU!$B5)),"Neat",IF(ISNUMBER(SEARCH("-PWD-",Sales_SKU!$B5)),"powder","")) -> Neat | K5: DR200_UN | L5: MHD | M5: IN | N5: REG-IN-ACETYL-PH
A6: FG05 | B6: SPI-ACETYL-ACEANH-PH-98.6-NEAT-DR200_UN-MHD | C6: Specialties | D6: ACETYL | E6: Acetic Anhydride | F6: PH | G6: 98.8 | H6: 51 | I6: 8 | J6: =IF(ISNUMBER(SEARCH("-NEAT-",Sales_SKU!$B6)),"Neat",IF(ISNUMBER(SEARCH("-PWD-",Sales_SKU!$B6)),"powder","")) -> Neat | K6: DR200_UN | L6: MHD | M6: EU | N6: REG-EU-ACETYL-PH
A7: FG06 | B7: SPI-ACETYL-ACEANH-PH-98.6-NEAT-DR200_UN-MHD | C7: Specialties | D7: ACETYL | E7: Acetic Anhydride | F7: PH | G7: 98.8 | H7: 64 | I7: 9 | J7: =IF(ISNUMBER(SEARCH("-NEAT-",Sales_SKU!$B7)),"Neat",IF(ISNUMBER(SEARCH("-PWD-",Sales_SKU!$B7)),"powder","")) -> Neat | K7: DR200_UN | L7: MHD | M7: APAC | N7: REG-APAC-ACETYL-PH
A8: FG07 | B8: SPI-ACETYL-ACE-IND-98.4-NEAT-ISO20-LTE | C8: Specialties | D8: ACETYL | E8: Acetaldehyde | F8: IND | G8: 98.4 | H8: 345 | I8: 22 | J8: =IF(ISNUMBER(SEARCH("-NEAT-",Sales_SKU!$B8)),"Neat",IF(ISNUMBER(SEARCH("-PWD-",Sales_SKU!$B8)),"powder","")) -> Neat | K8: ISO20 | L8: LTE | M8: IN | N8: REG-IN-ACETYL-IND
A9: FG08 | B9: SPI-ACETYL-ACE-IND-98.4-NEAT-ISO20-LTE | C9: Specialties | D9: ACETYL | E9: Acetaldehyde | F9: IND | G9: 98.4 | H9: 358 | I9: 21 | J9: =IF(ISNUMBER(SEARCH("-NEAT-",Sales_SKU!$B9)),"Neat",IF(ISNUMBER(SEARCH("-PWD-",Sales_SKU!$B9)),"powder","")) -> Neat | K9: ISO20 | L9: LTE | M9: EU | N9: REG-EU-ACETYL-IND
A10: FG09 | B10: SPI-ACETYL-ACE-IND-98.4-NEAT-ISO20-LTE | C10: Specialties | D10: ACETYL | E10: Acetaldehyde | F10: IND | G10: 98.4 | H10: 371 | I10: 17 | J10: =IF(ISNUMBER(SEARCH("-NEAT-",Sales_SKU!$B10)),"Neat",IF(ISNUMBER(SEARCH("-PWD-",Sales_SKU!$B10)),"powder","")) -> Neat | K10: ISO20 | L10: LTE | M10: APAC | N10: REG-APAC-ACETYL-IND
A11: FG10 | B11: ESS-ACETYL-BUTACE-TECH-98.3-NEAT-DR200-DHJ | C11: Essentials | D11: ACETYL | E11: Butyl Acetate | F11: TECH | G11: 98.2 | H11: 200 | I11: 14 | J11: =IF(ISNUMBER(SEARCH("-NEAT-",Sales_SKU!$B11)),"Neat",IF(ISNUMBER(SEARCH("-PWD-",Sales_SKU!$B11)),"powder","")) -> Neat | K11: DR200 | L11: DHJ | M11: IN | N11: REG-IN-ACETYL-TECH
A12: FG11 | B12: ESS-ACETYL-BUTACE-TECH-98.3-NEAT-DR200-DHJ | C12: Essentials | D12: ACETYL | E12: Butyl Acetate | F12: TECH | G12: 98.2 | H12: 213 | I12: 14 | J12: =IF(ISNUMBER(SEARCH("-NEAT-",Sales_SKU!$B12)),"Neat",IF(ISNUMBER(SEARCH("-PWD-",Sales_SKU!$B12)),"powder","")) -> Neat | K12: DR200 | L12: DHJ | M12: EU | N12: REG-EU-ACETYL-TECH
A13: FG12 | B13: ESS-ACETYL-BUTACE-TECH-98.3-NEAT-DR200-DHJ | C13: Essentials | D13: ACETYL | E13: Butyl Acetate | F13: TECH | G13: 98.2 | H13: 226 | I13: 9 | J13: =IF(ISNUMBER(SEARCH("-NEAT-",Sales_SKU!$B13)),"Neat",IF(ISNUMBER(SEARCH("-PWD-",Sales_SKU!$B13)),"powder","")) -> Neat | K13: DR200 | L13: DHJ | M13: APAC | N13: REG-APAC-ACETYL-TECH
... A121: FG120 | B121: ESS-FLUORO-FLRBLK-LM-98.9-PWD-BAG25-DHJ | C121: Essentials | D121: FLUORO | E121: Fluoro Building Block | F121: LM | G121: 98.7 | H121: 236 | I121: 20 | J121: =IF(ISNUMBER(SEARCH("-NEAT-",Sales_SKU!$B121)),"Neat",IF(ISNUMBER(SEARCH("-PWD-",Sales_SKU!$B121)),"powder","")) -> powder | K121: BAG25 | L121: DHJ | M121: APAC | N121: REG-APAC-FLUORO-LM

Sheet Purchase_SKU
A1: rm_id (Primary Key) | B1: SKU code (FK) | C1: rm_name | D1: rm_type | E1: uom | F1: storage_type | G1: storage_temp_c | H1: lead_time_days | I1: criticality | J1: approved_for_families | K1: primary_source_region_id | L1: notes
A2: RM0001 | B2: RM-ETH-AL-64175 | C2: Ethyl Alcohol (Ethanol) | D2: RAW_MATERIAL | E2: MT | F2: Tank | G2: Ambient | H2: 7 | I2: A | J2: ACETYL,DKD | K2: DOM | L2: Bulk solvent/feed; excise-controlled; illustrative
A3: RM0002 | B3: RM-AAC-GL-23011 | C3: Acetic Acid (Glacial) | D3: RAW_MATERIAL | E3: MT | F3: Tank | G3: Ambient | H3: 10 | I3: A | J3: ACETYL,DKD | K3: DOM | L3: Corrosive; dedicated SS tank; illustrative
A4: RM0003 | B4: RM-BUT-NB-51720 | C4: n-Butanol | D4: RAW_MATERIAL | E4: MT | F4: Tank | G4: Ambient | H4: 14 | I4: B | J4: ACETYL | K4: APAC | L4: Flammable; used for butyl acetate; illustrative
A5: RM0004 | B5: RM-ETL-AC-11804 | C5: Ethyl Acetate (Solvent grade) | D5: RAW_MATERIAL | E5: MT | F5: Tank | G5: Ambient | H5: 12 | I5: B | J5: ACETYL | K5: DOM | L5: Purchased solvent for blends/cleaning; illustrative
A6: RM0005 | B6: RM-MTH-AA-40218 | C6: Methacrylic Acid | D6: RAW_MATERIAL | E6: KG | F6: Drum/IBC | G6: Ambient | H6: 28 | I6: A | J6: ACETYL | K6: EU | L6: Inhibitor present; check MEHQ ppm; illustrative
A7: RM0006 | B7: RM-ANI-LN-90355 | C7: Aniline | D7: RAW_MATERIAL | E7: KG | F7: Drum/IBC | G7: Ambient | H7: 30 | I7: A | J7: ARYLIDE | K7: DOM | L7: Toxic; COA required per batch; illustrative
A8: RM0007 | B8: RM-PCA-AN-77210 | C8: p-Chloroaniline | D8: RAW_MATERIAL | E8: KG | F8: Bag | G8: Ambient | H8: 35 | I8: A | J8: ARYLIDE | K8: APAC | L8: Solid; store dry; sieve before charge; illustrative
A9: RM0008 | B9: RM-OAN-AS-55102 | C9: o-Anisidine | D9: RAW_MATERIAL | E9: KG | F9: Drum/IBC | G9: Ambient | H9: 32 | I9: B | J9: ARYLIDE | K9: EU | L9: Light sensitive; nitrogen blanket preferred; illustrative
A10: RM0009 | B10: RM-DIK-ET-88412 | C10: Diketene | D10: RAW_MATERIAL | E10: KG | F10: Drum/IBC | G10: 2-8 | H10: 21 | I10: A | J10: DKD,ACETYL | K10: DOM | L10: Refrigerated storage; moisture sensitive; illustrative
A11: RM0010 | B11: INT-KET-INS-145120 | C11: Ketene (in-situ) | D11: INTERMEDIATE | E11: KG | F11: On-site Generation | G11: N/A | H11: 0 | I11: A | J11: DKD,ACETYL | K11: DOM | L11: Generated on demand; no inventory; illustrative
A12: RM0011 | B12: INT-DKD-INT-342781 | C12: DKD Intermediate (Crude) | D12: INTERMEDIATE | E12: KG | F12: Drum/IBC | G12: Ambient | H12: 3 | I12: B | J12: DKD | K12: DOM | L12: Internal transfer; QC release required; illustrative
A13: RM0012 | B13: INT-ARY-INT-558903 | C13: Arylide Intermediate (Wet cake) | D13: INTERMEDIATE | E13: KG | F13: Bag | G13: Ambient | H13: 2 | I13: B | J13: ARYLIDE | K13: DOM | L13: Moist solid; process within 48h; illustrative
... A29: RM0028 | B29: INT-AAA-EMM-990812 | C29: AAEM Precursor (Stabilized) | D29: INTERMEDIATE | E29: KG | F29: Drum/IBC | G29: Ambient | H29: 4 | I29: B | J29: ACETYL | K29: DOM | L29: Stabilized intermediate; check inhibitor; illustrative

Sheet Regions
A1: region_id (Primary Key) | B1: region_name | C1: type | D1: active | E1: notes
A2: DOM | B2: India (Domestic) | C2: COUNTRY | D2: TRUE | E2: Domestic sales; GST invoicing; standard road lanes.
A3: EU | B3: European Union | C3: BLOC | D3: TRUE | E3: REACH/CLP compliance; SDS in local languages; DG-capable sea lanes.
A4: AMER | B4: Americas | C4: REGION | D4: TRUE | E4: US/LatAm exports; TSCA alignment; longer lead times via ocean freight.
A5: APAC | B5: Asia Pacific | C5: REGION | D5: TRUE | E5: APAC export hub; varied local registrations; mixed sea/road lanes.
A6: MEA | B6: Middle East & Africa | C6: REGION | D6: TRUE | E6: Often DG documentation required; bank LC common; temperature exposure risk.
A7: ROW | B7: Rest of World | C7: REGION | D7: TRUE | E7: Catch-all region for ad-hoc exports; validate local regulatory needs per shipment.

Sheet Countries
A1: country_id (Primary Key) | B1: country_name | C1: type | D1: iso_code | E1: region_id (FK) | F1: active | G1: notes
A2: IND | B2: India | C2: COUNTRY | D2: IN | E2: DOM | F2: TRUE | G2: Home market; GST/road lanes.
A3: DEU | B3: Germany | C3: COUNTRY | D3: DE | E3: EU | F3: TRUE | G3: EU; REACH/CLP aligned.
A4: FRA | B4: France | C4: COUNTRY | D4: FR | E4: EU | F4: TRUE | G4: EU; DG documentation common.
A5: ITA | B5: Italy | C5: COUNTRY | D5: IT | E5: EU | F5: TRUE | G5: EU; port lead times vary.
A6: ESP | B6: Spain | C6: COUNTRY | D6: ES | E6: EU | F6: TRUE | G6: EU; distributor network.
A7: NLD | B7: Netherlands | C7: COUNTRY | D7: NL | E7: EU | F7: TRUE | G7: EU hub; Rotterdam.
A8: BEL | B8: Belgium | C8: COUNTRY | D8: BE | E8: EU | F8: TRUE | G8: EU chemicals; strict SDS.
A9: POL | B9: Poland | C9: COUNTRY | D9: PL | E9: EU | F9: TRUE | G9: EU; growing demand.
A10: SWE | B10: Sweden | C10: COUNTRY | D10: SE | E10: EU | F10: TRUE | G10: EU; DG sea lanes.
A11: DNK | B11: Denmark | C11: COUNTRY | D11: DK | E11: EU | F11: TRUE | G11: EU; DG sea lanes.
A12: AUT | B12: Austria | C12: COUNTRY | D12: AT | E12: EU | F12: TRUE | G12: EU; inland trucking.
A13: CZE | B13: Czech Republic | C13: COUNTRY | D13: CZ | E13: EU | F13: TRUE | G13: EU; labeling compliance.
... A53: IRN | B53: Iran | C53: COUNTRY | D53: IR | E53: MEA | F53: FALSE | G53: Restricted market; illustrative inactive.

Sheet Customers
A1: customer_id (Primary Key) | B1: customer_name | C1: customer_type | D1: industry | E1: industry_code | F1: customer_region_id (FK-style) | G1: country_iso (FK) | H1: city | I1: currency | J1: channel | K1: risk_rating | L1: status | M1: gst_vat_id | N1: key_account_manager | O1: created_date
A2: CUS0001 | B2: GreenField Pharma GmbH | C2: B2B | D2: Pharmaceuticals | E2: PHARMA | F2: DOM | G2: IN | H2: Ahmedabad | I2: INR | J2: Direct | K2: C | L2: Active | M2: TAX-IN-499676 | N2: Team-Strategic | O2: 45994
A3: CUS0002 | B3: Keystone Pigments Co. Ltd | C3: B2B | D3: Adhesives | E3: ADH | F3: CN | G3: CN | H3: Shanghai | I3: CNY | J3: Distributor | K3: A | L3: Active | M3: TAX-CN-943121 | N3: Team-Intl | O3: 46191
A4: CUS0003 | B4: Aurum Agro S.A. | C4: B2B | D4: Industrial Solvents | E4: SOLV | F4: DOM | G4: IN | H4: Mumbai | I4: INR | J4: Distributor | K4: C | L4: Active | M4: TAX-IN-696397 | N4: Team-South | O4: 46070
A5: CUS0004 | B5: BluePeak Agro Ltd | C5: B2B | D5: Pigments | E5: PIGM | F5: US | G5: US | H5: Newark | I5: USD | J5: Distributor | K5: B | L5: Active | M5: TAX-US-215769 | N5: Team-Intl | O5: 45589
A6: CUS0005 | B6: Keystone Coatings S.A. | C6: B2B | D6: Inks & Coatings | E6: INKS | F6: DOM | G6: IN | H6: Gurgaon | I6: INR | J6: Distributor | K6: B | L6: Active | M6: TAX-IN-979970 | N6: Team-West | O6: 45404
A7: CUS0006 | B7: Sapphire Pharma NV | C7: B2B | D7: Industrial Solvents | E7: SOLV | F7: CN | G7: CN | H7: Shenzhen | I7: CNY | J7: Direct | K7: A | L7: Active | M7: TAX-CN-490679 | N7: Team-Strategic | O7: 45521
A8: CUS0007 | B8: Sterling Solvents GmbH | C8: B2B | D8: Adhesives | E8: ADH | F8: DOM | G8: IN | H8: Gurgaon | I8: INR | J8: Direct | K8: A | L8: Active | M8: TAX-IN-987820 | N8: Team-South | O8: 45758
A9: CUS0008 | B9: Nimbus Pigments S.A. | C9: B2B | D9: Agrochemicals | E9: AGRO | F9: US | G9: US | H9: Newark | I9: USD | J9: Direct | K9: B | L9: Active | M9: TAX-US-840961 | N9: Team-Intl | O9: 46292
A10: CUS0009 | B10: Silverline Pharma Inc. | C10: B2B | D10: Packaging | E10: PKG | F10: DOM | G10: IN | H10: Ahmedabad | I10: INR | J10: Direct | K10: B | L10: Active | M10: TAX-IN-700729 | N10: Team-South | O10: 45897
A11: CUS0010 | B11: Keystone Coatings Co. Ltd | C11: B2B | D11: Inks & Coatings | E11: INKS | F11: EU | G11: FR | H11: Lyon | I11: EUR | J11: Distributor | K11: B | L11: Active | M11: TAX-FR-255209 | N11: Team-Intl | O11: 45884
A12: CUS0011 | B12: Nimbus Packaging NV | C12: B2B | D12: Pigments | E12: PIGM | F12: EU | G12: SE | H12: Barcelona | I12: EUR | J12: Distributor | K12: A | L12: Active | M12: TAX-SE-766346 | N12: Team-Intl | O12: 46356
A13: CUS0012 | B13: Sterling Agro LLP | C13: B2B | D13: Adhesives | E13: ADH | F13: DOM | G13: IN | H13: Chennai | I13: INR | J13: Distributor | K13: B | L13: Prospect | M13: TAX-IN-731425 | N13: Team-Strategic | O13: 46281
... A101: CUS0100 | B101: Atlas Pigments LLP | C101: B2B | D101: Pigments | E101: PIGM | F101: EU | G101: DE | H101: Warsaw | I101: EUR | J101: Direct | K101: C | L101: Active | M101: TAX-DE-234001 | N101: Team-Intl | O101: 46341

Sheet SLA Profiles
A1: sla_id (Primary Key) | B1: sla_name | C1: scope_region_id (FK) | D1: applicable_channels | E1: applicable_families | F1: incoterms_scope | G1: service_window_cutoff_local | H1: service_days | I1: dispatch_lead_time_days (min) | J1: dispatch_lead_time_days (max) | K1: Handover at | L1: delivery_window_days (min) | M1: delivery_window_days (max) | N1: otif_target_pct | O1: ot_time_tolerance | P1: in_full_target_pct | Q1: fill_rate_target_pct | R1: backorder_resolution_days | S1: quote_tat_hours | T1: order_ack_tat_hours | U1: documentation_requirements | V1: documentation_accuracy_pct | W1: pod_submission_hours | X1: claims_response_business_days | Y1: claims_closure_business_days | Z1: temperature_control | AA1: dg_class_handling | AB1: min_order_quantity | AC1: packaging_constraints | AD1: penalty_credit_logic | AE1: review_frequency | AF1: effective_from | AG1: effective_to | AH1: status
A2: SLA_STD_DOM_T1 | B2: Domestic Standard T1 (Bulk Liquids) | C2: DOM | D2: Direct,Distributor | E2: ACETYL,DKD | F2: EXW/FCA | G2: 14:00 | H2: Mon-Sat | I2: 1 | J2: 2 | K2: Plant gate | L2: 1 | M2: 3 | N2: 94 | O2: +/-1 day | P2: 97 | Q2: 96 | R2: 5 | S2: 8 | T2: 4 | U2: COA,Invoice,Ewaybill | V2: 99.5 | W2: 48 | X2: 3 | Y2: 10 | Z2: Ambient | AA2: DG allowed (where applicable) | AB2: 2000 KG | AC2: BULK,ISO20,IBC1KL | AD2: 1% credit if OTIF < target (monthly) on eligible orders | AE2: Quarterly | AF2: 2026-01-01 | AH2: Active
A3: SLA_STD_DOM_T2 | B3: Domestic Priority T2 (Drums/IBCs) | C3: DOM | D3: Direct,Distributor | E3: ACETYL,DKD,ARYLIDE | F3: EXW/FCA | G3: 16:00 | H3: Mon-Sat | I3: 0 | J3: 1 | K3: Plant gate | L3: 1 | M3: 2 | N3: 96 | O3: +/-0 day | P3: 98 | Q3: 97 | R3: 3 | S3: 6 | T3: 2 | U3: COA,Invoice,Ewaybill,UN Pack Cert (if DG) | V3: 99.7 | W3: 36 | X3: 2 | Y3: 7 | Z3: Ambient | AA3: DG allowed | AB3: 500 KG | AC3: DR200,DR200_UN,IBC1KL | AD3: 2% credit on freight line if OTIF < target (monthly) | AE3: Monthly | AF3: 2026-01-01 | AH3: Active
A4: SLA_STD_DOM_T3 | B4: Domestic Economy T3 (Powders) | C4: DOM | D4: Distributor | E4: ARYLIDE,FLUORO | F4: EXW | G4: 12:00 | H4: Mon-Fri | I4: 2 | J4: 4 | K4: Plant gate | L4: 2 | M4: 5 | N4: 92 | O4: +/-1 day | P4: 96 | Q4: 95 | R4: 7 | S4: 12 | T4: 6 | U4: COA,Invoice | V4: 99 | W4: 72 | X4: 4 | Y4: 15 | Z4: Ambient | AA4: DG by exception | AB4: 1000 KG | AC4: BAG25 only | AD4: No penalties; service credits only for documented failures above 3% of orders | AE4: Semi-Annual | AF4: 2026-01-01 | AH4: Active
A5: SLA_EXPORT_EU_T1 | B5: Export EU T1 (REACH-ready) | C5: EU | D5: Export-Direct,Distributor | E5: ACETYL,DKD,ARYLIDE | F5: FOB/CIF/CIP | G5: 13:00 | H5: Mon-Fri | I5: 3 | J5: 5 | K5: Port (Nhava Sheva/Mundra) | L5: 14 | M5: 21 | N5: 94 | O5: +/-2 days | P5: 97 | Q5: 96 | R5: 10 | S5: 24 | T5: 12 | U5: COA,Invoice,Packing List,SDS,REACH docs,BL | V5: 99.5 | W5: 120 | X5: 5 | Y5: 20 | Z5: Ambient | AA5: DG allowed (IMO) | AB5: 10 MT | AC5: ISO20,Flexitank,DR200_UN | AD5: 1% credit on invoice value if OTIF < target (quarterly) for contract orders | AE5: Quarterly | AF5: 2026-01-01 | AH5: Active
A6: SLA_EXPORT_US_T1_D | B6: Export US T1 (DG capable - Direct) | C6: AMER | D6: Export-Direct | E6: ACETYL,DKD | F6: FOB/CIF | G6: 13:00 | H6: Mon-Fri | I6: 3 | J6: 6 | K6: Port (Nhava Sheva) | L6: 18 | M6: 28 | N6: 93 | O6: +/-3 days | P6: 96 | Q6: 95 | R6: 12 | S6: 24 | T6: 12 | U6: COA,Invoice,Packing List,SDS,TSCA statement,BL | V6: 99.3 | W6: 168 | X6: 5 | Y6: 25 | Z6: Ambient | AA6: DG allowed (IMO) | AB6: 10 MT | AC6: ISO20,DR200_UN | AD6: 2% credit on ocean freight component if OTIF < target (quarterly) | AE6: Quarterly | AF6: 2026-01-01 | AH6: Active
A7: SLA_EXPORT_US_T1_P | B7: Export US T1 (Pharma/High Purity) | C7: AMER | D7: Export-Direct | E7: ACETYL | F7: CIP/DDP (case by case) | G7: 12:00 | H7: Mon-Fri | I7: 2 | J7: 4 | K7: Port + Forwarder handoff | L7: 14 | M7: 24 | N7: 95 | O7: +/-2 days | P7: 98 | Q7: 97 | R7: 8 | S7: 16 | T7: 8 | U7: COA,Invoice,Packing List,SDS,TSCA,Allergen/Pharma statement,BL | V7: 99.7 | W7: 120 | X7: 4 | Y7: 18 | Z7: 46061 | AA7: Non-DG preferred | AB7: 5 MT | AC7: DR200_UN,IBC1KL | AD7: Service credit 1% if documentation accuracy < target; OTIF credits per contract | AE7: Monthly | AF7: 2026-01-01 | AH7: Active
A8: SLA_EXPORT_APAC_T1_D | B8: Export APAC T1 (SEA lanes) | C8: APAC | D8: Export-Direct,Distributor | E8: ACETYL,DKD,FLUORO | F8: FOB/CIF | G8: 14:00 | H8: Mon-Fri | I8: 2 | J8: 5 | K8: Port (Nhava Sheva/Mundra) | L8: 10 | M8: 18 | N8: 94 | O8: +/-2 days | P8: 97 | Q8: 96 | R8: 8 | S8: 18 | T8: 8 | U8: COA,Invoice,Packing List,SDS,BL | V8: 99.2 | W8: 96 | X8: 4 | Y8: 15 | Z8: Ambient | AA8: DG allowed (IMO) | AB8: 5 MT | AC8: ISO20,DR200_UN,IBC1KL | AD8: 0.5% credit if OTIF < target (quarterly) for annual contracts | AE8: Quarterly | AF8: 2026-01-01 | AH8: Active
A9: SLA_EXPORT_APAC_T1_P | B9: Export APAC T1 (Powders) | C9: APAC | D9: Export-Direct,Distributor | E9: ARYLIDE,FLUORO | F9: FOB/CIF | G9: 12:00 | H9: Mon-Fri | I9: 3 | J9: 6 | K9: Port (Nhava Sheva/Mundra) | L9: 12 | M9: 20 | N9: 92 | O9: +/-3 days | P9: 96 | Q9: 95 | R9: 10 | S9: 24 | T9: 12 | U9: COA,Invoice,Packing List,SDS,BL | V9: 99 | W9: 120 | X9: 5 | Y9: 20 | Z9: Ambient | AA9: DG where required | AB9: 3 MT | AC9: BAG25,IBC1KL | AD9: No penalties for port delays; credit applies only for documentation failures | AE9: Semi-Annual | AF9: 2026-01-01 | AH9: Active
A10: SLA_EXPORT_ROW_T2_D | B10: Export ROW T2 (DG/Remote - Direct) | C10: MEA | D10: Export-Direct | E10: ACETYL,DKD,FLUORO | F10: FOB/CFR/CIF | G10: 11:00 | H10: Mon-Fri | I10: 4 | J10: 8 | K10: Port (Nhava Sheva) | L10: 20 | M10: 35 | N10: 90 | O10: +/-4 days | P10: 95 | Q10: 94 | R10: 15 | S10: 30 | T10: 12 | U10: COA,Invoice,Packing List,SDS,BL,Legalization (if required) | V10: 98.8 | W10: 240 | X10: 7 | Y10: 30 | Z10: Ambient | AA10: DG allowed (IMO) | AB10: 10 MT | AC10: ISO20,DR200_UN | AD10: Credits capped at 0.5% of invoice; exclusions for force majeure/port congestion | AE10: Annual | AF10: 2026-01-01 | AH10: Active
A11: SLA_EXPORT_ROW_T2_P | B11: Export ROW T2 (Project/Small lots) | C11: MEA | D11: Distributor | E11: ARYLIDE,FLUORO | F11: EXW/FCA/FOB | G11: 10:00 | H11: Mon-Fri | I11: 5 | J11: 10 | K11: Plant gate / Port | L11: 25 | M11: 45 | N11: 90 | O11: +/-5 days | P11: 95 | Q11: 94 | R11: 20 | S11: 36 | T11: 24 | U11: COA,Invoice,Packing List,SDS | V11: 98.5 | W11: 240 | X11: 8 | Y11: 35 | Z11: Ambient | AA11: DG by exception | AB11: 1000 KG | AC11: BAG25,DR200_UN | AD11: No penalties; review service gaps in QBR and agree corrective actions | AE11: Annual | AF11: 2026-01-01 | AG11: 2026-12-31 | AH11: Planned

Sheet Orders
A1: Mean
A2: St Deviation (%)
A3: Total per month / No. of entries | B3: 180
A4: Order ID (Primary Key) | B4: Order Type | C4: Order Date | D4: Customer ID (FK) | E4: To WH ID | F4: Payment Terms | G4: Order Status
A5: ORD202602-0001 | B5: Sales Order | C5: 2026-02-01 | D5: CUS0001 | F5: Advance | G5: Delivered
A6: ORD202602-0002 | B6: Sales Order | C6: 2026-02-02 | D6: CUS0002 | F6: Net 15 | G6: Delivered
A7: ORD202602-0003 | B7: Sales Order | C7: 2026-02-03 | D7: CUS0003 | F7: Advance | G7: Delivered
A8: ORD202602-0004 | B8: Sales Order | C8: 2026-02-04 | D8: CUS0004 | F8: Net 30 | G8: Delivered
A9: ORD202602-0005 | B9: Sales Order | C9: 2026-02-05 | D9: CUS0005 | F9: Net 15 | G9: Shipped
A10: ORD202602-0006 | B10: Sales Order | C10: 2026-02-06 | D10: CUS0006 | F10: Net 30 | G10: Shipped
A11: ORD202602-0007 | B11: Transfer Order | C11: 2026-02-07 | E11: TNK_EUR_RTM | F11: Net 30 | G11: Confirmed
A12: ORD202602-0008 | B12: Sales Order | C12: 2026-02-08 | D12: CUS0008 | F12: Net 15 | G12: Delivered
A13: ORD202602-0009 | B13: Sales Order | C13: 2026-02-09 | D13: CUS0009 | F13: Net 30 | G13: Delivered
A14: ORD202602-0010 | B14: Sales Order | C14: 2026-02-10 | D14: CUS0010 | F14: Net 15 | G14: Delivered
A15: ORD202602-0011 | B15: Sales Order | C15: 2026-02-11 | D15: CUS0011 | F15: Advance | G15: Shipped
A16: ORD202602-0012 | B16: Sales Order | C16: 2026-02-12 | D16: CUS0012 | F16: Net 30 | G16: Shipped
A17: ORD202602-0013 | B17: Sales Order | C17: 2026-02-13 | D17: CUS0013 | F17: Net 15 | G17: Shipped
A18: ORD202602-0014 | B18: Transfer Order | C18: 2026-02-14 | E18: TNK_EUR_ANT | F18: Net 30 | G18: Confirmed
A19: ORD202602-0015 | B19: Sales Order | C19: 2026-02-15 | D19: CUS0015 | F19: Advance | G19: Confirmed
A20: ORD202602-0016 | B20: Sales Order | C20: 2026-02-16 | D20: CUS0016 | F20: Net 30 | G20: Delivered
A21: ORD202602-0017 | B21: Sales Order | C21: 2026-02-17 | D21: CUS0017 | F21: Advance | G21: Delivered
A22: ORD202602-0018 | B22: Sales Order | C22: 2026-02-18 | D22: CUS0018 | F22: Net 15 | G22: Shipped
A23: ORD202602-0019 | B23: Sales Order | C23: 2026-02-19 | D23: CUS0019 | F23: Advance | G23: Shipped
A24: ORD202602-0020 | B24: Sales Order | C24: 2026-02-20 | D24: CUS0020 | F24: Net 30 | G24: Shipped
A25: ORD202602-0021 | B25: Transfer Order | C25: 2026-02-21 | E25: TNK_EUR_GEN | F25: Net 30 | G25: Confirmed
A26: ORD202602-0022 | B26: Sales Order | C26: 2026-02-22 | D26: CUS0022 | F26: Advance | G26: Confirmed
A27: ORD202602-0023 | B27: Sales Order | C27: 2026-02-23 | D27: CUS0023 | F27: Advance | G27: Confirmed
A28: ORD202602-0024 | B28: Sales Order | C28: 2026-02-24 | D28: CUS0024 | F28: Net 30 | G28: Shipped
A29: ORD202602-0025 | B29: Sales Order | C29: 2026-02-25 | D29: CUS0025 | F29: Net 30 | G29: Shipped
A30: ORD202602-0026 | B30: Sales Order | C30: 2026-02-26 | D30: CUS0026 | F30: Net 30 | G30: Shipped
A31: ORD202602-0027 | B31: Sales Order | C31: 2026-02-27 | D31: CUS0027 | F31: Net 15 | G31: Confirmed
A32: ORD202602-0028 | B32: Transfer Order | C32: 2026-02-28 | E32: WH_IN_WEST_BHI | F32: Net 30 | G32: Confirmed
A33: ORD202602-0029 | B33: Sales Order | C33: 2026-02-01 | D33: CUS0029 | F33: Net 15 | G33: Shipped
A34: ORD202602-0030 | B34: Sales Order | C34: 2026-02-02 | D34: CUS0030 | F34: Advance | G34: Confirmed
A35: ORD202602-0031 | B35: Sales Order | C35: 2026-02-03 | D35: CUS0031 | F35: Advance | G35: Delivered
A36: ORD202602-0032 | B36: Sales Order | C36: 2026-02-04 | D36: CUS0032 | F36: Net 30 | G36: Delivered
A37: ORD202602-0033 | B37: Sales Order | C37: 2026-02-05 | D37: CUS0033 | F37: Net 30 | G37: Delivered
A38: ORD202602-0034 | B38: Sales Order | C38: 2026-02-06 | D38: CUS0034 | F38: Net 30 | G38: Delivered
A39: ORD202602-0035 | B39: Transfer Order | C39: 2026-02-07 | E39: WH_IN_GUJ_AHD | F39: Net 30 | G39: Delivered
A40: ORD202602-0036 | B40: Sales Order | C40: 2026-02-08 | D40: CUS0036 | F40: Advance | G40: Shipped
A41: ORD202602-0037 | B41: Sales Order | C41: 2026-02-09 | D41: CUS0037 | F41: Net 15 | G41: Shipped
A42: ORD202602-0038 | B42: Sales Order | C42: 2026-02-10 | D42: CUS0038 | F42: Advance | G42: Confirmed
A43: ORD202602-0039 | B43: Sales Order | C43: 2026-02-11 | D43: CUS0039 | F43: Advance | G43: Delivered
A44: ORD202602-0040 | B44: Sales Order | C44: 2026-02-12 | D44: CUS0040 | F44: Net 30 | G44: Delivered
A45: ORD202602-0041 | B45: Sales Order | C45: 2026-02-13 | D45: CUS0041 | F45: Advance | G45: Shipped
A46: ORD202602-0042 | B46: Transfer Order | C46: 2026-02-14 | E46: WH_IN_SOUTH_HYD | F46: Net 30 | G46: Shipped
A47: ORD202602-0043 | B47: Sales Order | C47: 2026-02-15 | D47: CUS0043 | F47: Net 15 | G47: Shipped
A48: ORD202602-0044 | B48: Sales Order | C48: 2026-02-16 | D48: CUS0044 | F48: Advance | G48: Shipped
A49: ORD202602-0045 | B49: Sales Order | C49: 2026-02-17 | D49: CUS0045 | F49: Net 15 | G49: Confirmed
A50: ORD202602-0046 | B50: Sales Order | C50: 2026-02-18 | D50: CUS0046 | F50: Advance | G50: Confirmed
A51: ORD202602-0047 | B51: Sales Order | C51: 2026-02-19 | D51: CUS0047 | F51: Net 30 | G51: Delivered
A52: ORD202602-0048 | B52: Sales Order | C52: 2026-02-20 | D52: CUS0048 | F52: Net 15 | G52: Delivered
A53: ORD202602-0049 | B53: Transfer Order | C53: 2026-02-21 | E53: WH_IN_NORTH_BAW | F53: Net 30 | G53: Shipped
A54: ORD202602-0050 | B54: Sales Order | C54: 2026-02-22 | D54: CUS0050 | F54: Net 30 | G54: Confirmed
A55: ORD202602-0051 | B55: Sales Order | C55: 2026-02-23 | D55: CUS0051 | F55: Net 15 | G55: Confirmed
A56: ORD202602-0052 | B56: Sales Order | C56: 2026-02-24 | D56: CUS0052 | F56: Net 30 | G56: Confirmed
A57: ORD202602-0053 | B57: Sales Order | C57: 2026-02-25 | D57: CUS0053 | F57: Net 15 | G57: Confirmed
A58: ORD202602-0054 | B58: Sales Order | C58: 2026-02-26 | D58: CUS0054 | F58: Net 30 | G58: Delivered
A59: ORD202602-0055 | B59: Sales Order | C59: 2026-02-27 | D59: CUS0055 | F59: Advance | G59: Shipped
A60: ORD202602-0056 | B60: Transfer Order | C60: 2026-02-28 | E60: CFS_IN_NHAV | F60: Net 30 | G60: Shipped
A61: ORD202602-0057 | B61: Sales Order | C61: 2026-02-01 | D61: CUS0057 | F61: Advance | G61: Delivered
A62: ORD202602-0058 | B62: Sales Order | C62: 2026-02-02 | D62: CUS0058 | F62: Net 30 | G62: Delivered
A63: ORD202602-0059 | B63: Sales Order | C63: 2026-02-03 | D63: CUS0059 | F63: Net 15 | G63: Shipped
A64: ORD202602-0060 | B64: Sales Order | C64: 2026-02-04 | D64: CUS0060 | F64: Net 30 | G64: Shipped
A65: ORD202602-0061 | B65: Sales Order | C65: 2026-02-05 | D65: CUS0061 | F65: Net 30 | G65: Confirmed
A66: ORD202602-0062 | B66: Sales Order | C66: 2026-02-06 | D66: CUS0062 | F66: Net 30 | G66: Delivered
A67: ORD202602-0063 | B67: Transfer Order | C67: 2026-02-07 | E67: WH_UAE_SHJ | F67: Net 30 | G67: Delivered
A68: ORD202602-0064 | B68: Sales Order | C68: 2026-02-08 | D68: CUS0064 | F68: Net 15 | G68: Delivered
A69: ORD202602-0065 | B69: Sales Order | C69: 2026-02-09 | D69: CUS0065 | F69: Advance | G69: Delivered
A70: ORD202602-0066 | B70: Sales Order | C70: 2026-02-10 | D70: CUS0066 | F70: Net 30 | G70: Delivered
A71: ORD202602-0067 | B71: Sales Order | C71: 2026-02-11 | D71: CUS0067 | F71: Net 15 | G71: Shipped
A72: ORD202602-0068 | B72: Sales Order | C72: 2026-02-12 | D72: CUS0068 | F72: Advance | G72: Confirmed
A73: ORD202602-0069 | B73: Sales Order | C73: 2026-02-13 | D73: CUS0069 | F73: Net 30 | G73: Confirmed
A74: ORD202602-0070 | B74: Transfer Order | C74: 2026-02-14 | E74: WH_US_EAST_NJ | F74: Net 30 | G74: Delivered
A75: ORD202602-0071 | B75: Sales Order | C75: 2026-02-15 | D75: CUS0071 | F75: Net 30 | G75: Delivered
A76: ORD202602-0072 | B76: Sales Order | C76: 2026-02-16 | D76: CUS0072 | F76: Net 15 | G76: Shipped
A77: ORD202602-0073 | B77: Sales Order | C77: 2026-02-17 | D77: CUS0073 | F77: Advance | G77: Shipped
A78: ORD202602-0074 | B78: Sales Order | C78: 2026-02-18 | D78: CUS0074 | F78: Advance | G78: Shipped
A79: ORD202602-0075 | B79: Sales Order | C79: 2026-02-19 | D79: CUS0075 | F79: Net 15 | G79: Shipped
A80: ORD202602-0076 | B80: Sales Order | C80: 2026-02-20 | D80: CUS0076 | F80: Advance | G80: Confirmed
A81: ORD202602-0077 | B81: Transfer Order | C81: 2026-02-21 | E81: WH_US_MID_CHI | F81: Net 30 | G81: Delivered
A82: ORD202602-0078 | B82: Sales Order | C82: 2026-02-22 | D82: CUS0078 | F82: Net 15 | G82: Shipped
A83: ORD202602-0079 | B83: Sales Order | C83: 2026-02-23 | D83: CUS0079 | F83: Net 30 | G83: Shipped
A84: ORD202602-0080 | B84: Sales Order | C84: 2026-02-24 | D84: CUS0080 | F84: Net 15 | G84: Shipped
A85: ORD202602-0081 | B85: Sales Order | C85: 2026-02-25 | D85: CUS0081 | F85: Net 15 | G85: Confirmed
A86: ORD202602-0082 | B86: Sales Order | C86: 2026-02-26 | D86: CUS0082 | F86: Net 30 | G86: Confirmed
A87: ORD202602-0083 | B87: Sales Order | C87: 2026-02-27 | D87: CUS0083 | F87: Net 15 | G87: Confirmed
A88: ORD202602-0084 | B88: Transfer Order | C88: 2026-02-28 | E88: TNK_EUR_RTM | F88: Net 30 | G88: Confirmed
A89: ORD202602-0085 | B89: Sales Order | C89: 2026-02-01 | D89: CUS0085 | F89: Advance | G89: Delivered
A90: ORD202602-0086 | B90: Sales Order | C90: 2026-02-02 | D90: CUS0086 | F90: Net 15 | G90: Delivered
A91: ORD202602-0087 | B91: Sales Order | C91: 2026-02-03 | D91: CUS0087 | F91: Advance | G91: Delivered
A92: ORD202602-0088 | B92: Sales Order | C92: 2026-02-04 | D92: CUS0088 | F92: Net 30 | G92: Delivered
A93: ORD202602-0089 | B93: Sales Order | C93: 2026-02-05 | D93: CUS0089 | F93: Net 30 | G93: Delivered
A94: ORD202602-0090 | B94: Sales Order | C94: 2026-02-06 | D94: CUS0090 | F94: Net 30 | G94: Shipped
A95: ORD202602-0091 | B95: Transfer Order | C95: 2026-02-07 | E95: TNK_EUR_ANT | F95: Net 30 | G95: Shipped
A96: ORD202602-0092 | B96: Sales Order | C96: 2026-02-08 | D96: CUS0092 | F96: Advance | G96: Confirmed
A97: ORD202602-0093 | B97: Sales Order | C97: 2026-02-09 | D97: CUS0093 | F97: Net 30 | G97: Delivered
A98: ORD202602-0094 | B98: Sales Order | C98: 2026-02-10 | D98: CUS0094 | F98: Net 15 | G98: Delivered
A99: ORD202602-0095 | B99: Sales Order | C99: 2026-02-11 | D99: CUS0095 | F99: Advance | G99: Shipped
A100: ORD202602-0096 | B100: Sales Order | C100: 2026-02-12 | D100: CUS0096 | F100: Net 30 | G100: Shipped
...

Sheet Order_Line Items
A1: Mean
A2: St Deviation (%)
A3: Total per month / No. of entries | B3: 216
A4: Order Line Item (Primary Key) | B4: Order_id (FK) | C4: SLA Profile ID (FK) | D4: Delivery_by_date | E4: Requirement Status | F4: Fulfilled by WH ID (WH ID FK) | G4: SKU ID (FK) | H4: Quantity (MT) | I4: Unit Price (USD) | J4: Value (USD) | K4: Forecast ID (FK)
A5: OLI202602-0001 | B5: ORD202602-0001 | C5: SLA_STD_DOM_T1 | D5: 2026-02-09 | E5: Fulfilled | F5: WH_IN_NORTH_BAW | G5: ESS-ACETYL-ACEANH-IND-98.8-NEAT-BULK-MHD | H5: 101.01 | I5: 1076.43 | J5: 108731.54 | K5: FC202602-DOM-ACETYL
A6: OLI202602-0002 | B6: ORD202602-0002 | C6: SLA_EXPORT_ROW_T2_D | D6: 2026-02-26 | E6: Fulfilled | F6: WH_UAE_SHJ | G6: ESS-ACETYL-ACEANH-PH-99.7-NEAT-ISO20-DHJ | H6: 106.95 | I6: 1082.43 | J6: 115763.95 | K6: FC202602-APAC-ACETYL
A7: OLI202602-0003 | B7: ORD202602-0003 | C7: SLA_STD_DOM_T1 | D7: 2026-02-10 | E7: Fulfilled | F7: WH_IN_WEST_BHI | G7: ESS-ACETYL-BUTACE-PH-98.5-NEAT-ISO20-MHD | H7: 92.21 | I7: 1282.15 | J7: 118222.68 | K7: FC202602-DOM-ACETYL
A8: OLI202602-0004 | B8: ORD202602-0004 | C8: SLA_EXPORT_US_T1_D | D8: 2026-03-01 | E8: Fulfilled | F8: CFS_IN_NHAV | G8: ESS-ACETYL-AAEM-INK-99.7-NEAT-IBC1KL-LTE | H8: 95.46 | I8: 1237.57 | J8: 118134.89 | K8: FC202602-AMER-ACETYL
A9: OLI202602-0005 | B9: ORD202602-0005 | C9: SLA_STD_DOM_T2 | D9: 2026-02-15 | E9: In Transit | F9: WH_IN_GUJ_AHD | G9: SPI-ACETYL-MAA-TECH-98.7-NEAT-DR200-LTE | H9: 79.9 | I9: 1130.54 | J9: 90333.06 | K9: FC202602-DOM-ACETYL
A10: OLI202602-0006 | B10: ORD202602-0006 | C10: SLA_EXPORT_ROW_T2_P | D10: 2026-02-28 | E10: In Transit | F10: WH_UAE_SHJ | G10: SPI-ARYLIDE-ARYINT-TECH-98.4-PWD-BAG25-DST | H10: 107.28 | I10: 1848.85 | J10: 198347.1 | K10: FC202602-APAC-ARYLIDE
A11: OLI202602-0007 | B11: ORD202602-0007 | C11: SLA_STD_DOM_T2 | D11: 2026-02-17 | E11: Planned | F11: TNK_EUR_RTM | G11: ESS-ACETYL-EAA-IND-98.3-NEAT-IBC1KL-MHD | H11: 90.14 | I11: 1146.69 | J11: 103361.82 | K11: FC202602-DOM-ACETYL
A12: OLI202602-0008 | B12: ORD202602-0008 | C12: SLA_EXPORT_US_T1_D | D12: 2026-03-03 | E12: Fulfilled | F12: WH_US_EAST_NJ | G12: ESS-ACETYL-MAA-LM-98.4-NEAT-IBC1KL-DST | H12: 97.7 | I12: 999.77 | J12: 97674.11 | K12: FC202602-AMER-ACETYL
A13: OLI202602-0009 | B13: ORD202602-0009 | C13: SLA_STD_DOM_T3 | D13: 2026-02-18 | E13: Fulfilled | F13: WH_IN_WEST_BHI | G13: SPI-FLUORO-FLRBLK-LM-99.0-PWD-BAG25-DHJ | H13: 88.24 | I13: 2119.56 | J13: 187029.67 | K13: FC202602-DOM-FLUORO
A14: OLI202602-0010 | B14: ORD202602-0010 | C14: SLA_EXPORT_EU_T1 | D14: 2026-03-01 | E14: Fulfilled | F14: TNK_EUR_RTM | G14: ESS-ACETYL-ACEANH-IND-98.8-NEAT-BULK-MHD | H14: 87.14 | I14: 1018.86 | J14: 88787.15 | K14: FC202602-EU-ACETYL
A15: OLI202602-0011 | B15: ORD202602-0011 | C15: SLA_EXPORT_EU_T1 | D15: 2026-03-08 | E15: In Transit | F15: TNK_EUR_RTM | G15: ESS-DKD-DKDINT-LM-98.0-NEAT-DR200-MHD | H15: 92.41 | I15: 1240.89 | J15: 114674.38 | K15: FC202602-EU-DKD
A16: OLI202602-0012 | B16: ORD202602-0012 | C16: SLA_STD_DOM_T2 | D16: 2026-02-21 | E16: In Transit | F16: WH_IN_SOUTH_HYD | G16: SPI-ACETYL-EAA-IND-99.2-NEAT-DR200-MHD | H16: 95.89 | I16: 1296.85 | J16: 124349.92 | K16: FC202602-DOM-ACETYL
... A220: OLI202602-0216 | B220: ORD202602-0055 | C220: SLA_EXPORT_US_T1_D | D220: 2026-03-23 | E220: In Transit | F220: WH_US_EAST_NJ | G220: ESS-ACETYL-ETHACE-LM-98.5-NEAT-BULK-DST | H220: 106.28 | I220: 1217.12 | J220: 129355.51 | K220: FC202602-AMER-ACETYL

Sheet Signals
A1: No restriction on number of signals
A2: Signal ID (Primary Key) | B2: Source | C2: Topic headline | D2: Description | E2: Sentiment Score | F2: Confidence | G2: Detected On_Date | H2: Signal Type | I2: Forecast ID (FK) | J2: Exception ID (FK)
A3: SIG202602-0001 | B3: News (ICIS) | C3: European ethanol tightness lifts solvent feedstock costs | D3: ICIS highlights tighter EU ethanol availability; monitor import parity and consider advancing March purchases for ACETYL chain. Review TNK_EUR_RTM replenishment plan. | E3: 0.18 | F3: 0.78 | G3: 2026-02-01T06:45:00.000Z | H3: forecast input | I3: FC202602-EU-ACETYL
A4: SIG202602-0002 | B4: Finance note (FX/credit) | C4: INR volatility may impact import cost for methacrylic acid | D4: FX desk flags INR weakness vs EUR; update landed cost assumptions for AAEM-related inputs and validate customer price pass-through. | E4: -0.12 | F4: 0.74 | G4: 2026-02-01T11:20:00.000Z | H4: forecast input | I4: FC202602-DOM-ACETYL
A5: SIG202602-0003 | B5: Internal memo (Plant Ops) | C5: Mahad esterification train running stable at higher throughputs | D5: Ops note indicates Train 2 sustained rates; opportunity to pull forward domestic dispatches if WH_IN_WEST_BHI capacity allows. | E5: 0.22 | F5: 0.83 | G5: 2026-02-02T03:10:00.000Z | H5: forecast input | I5: FC202602-DOM-ACETYL
A6: SIG202602-0004 | B6: LSP bulletin | C6: JNPT congestion warning for DG containers this week | D6: Carrier bulletin warns of gate-in delays at CFS_IN_NHAV; prioritize documentation readiness and consider earlier cut-offs for export lots. | E6: -0.35 | F6: 0.86 | G6: 2026-02-02T09:55:00.000Z | H6: exception | J6: EXC202602-0001
A7: SIG202602-0005 | B7: Customer call note | C7: US coatings customer requests additional DR200_UN availability | D7: Customer indicates preference for UN drums for Q2; validate drum supply and align allocation from WH_US_EAST_NJ for smoother deliveries. | E7: 0.09 | F7: 0.69 | G7: 2026-02-03T15:05:00.000Z | H7: forecast input | I7: FC202602-AMER-ACETYL
A8: SIG202602-0006 | B8: News (S&P Global Platts) | C8: Freight rates soften on Asia-Europe lane in February | D8: Platts notes modest decline in spot container rates; reassess CIF offers for APAC customers and update forecast margin assumptions. | E8: 0.11 | F8: 0.77 | G8: 2026-02-03T04:30:00.000Z | H8: forecast input | I8: FC202602-APAC-ACETYL
A9: SIG202602-0007 | B9: Internal email (Sales) | C9: Distributor asking for extended credit on acetyl solvents | D9: Sales email suggests higher credit exposure; recommend Advance terms for risk-rated C accounts until payments normalize. | E9: -0.28 | F9: 0.71 | G9: 2026-02-04T08:40:00.000Z | H9: exception | J9: EXC202602-0002
A10: SIG202602-0008 | B10: News (ICIS) | C10: Acetic acid spot prices firm on planned maintenance | D10: ICIS reports planned turnarounds; consider locking domestic contracts and updating FC202602-DOM-ACETYL assumptions for March-April. | E10: 0.26 | F10: 0.84 | G10: 2026-02-04T12:15:00.000Z | H10: forecast input | I10: FC202602-DOM-ACETYL
A11: SIG202602-0009 | B11: Internal memo (Plant Ops) | C11: Lote fluoro suite scheduling constraint for DG packaging | D11: Ops flags limited DG packing slots; stagger FLUORO dispatches and reserve bagging windows for BAG25 lots. | E11: -0.14 | F11: 0.8 | G11: 2026-02-05T05:05:00.000Z | H11: exception | J11: EXC202602-0003
A12: SIG202602-0010 | B12: Customer call note | C12: EU pigment customer expects stronger demand for arylide intermediates | D12: Customer indicates higher pulls; propose increasing TNK_EUR_ANT safety stock and adjust FC202602-EU-ARYLIDE upward. | E12: 0.31 | F12: 0.76 | G12: 2026-02-05T13:35:00.000Z | H12: forecast input | I12: FC202602-EU-ARYLIDE
A13: SIG202602-0011 | B13: LSP bulletin | C13: Rotterdam terminal slot availability reduced for ISO tanks | D13: Terminal operator signals fewer ISO20 slots; pre-book arrivals and avoid bunching shipments into TNK_EUR_RTM. | E13: -0.21 | F13: 0.82 | G13: 2026-02-06T07:20:00.000Z | H13: exception | J13: EXC202602-0004
A14: SIG202602-0012 | B14: Internal email (Sales) | C14: Domestic inks customer requests higher assay EAA for reformulation | D14: Customer needs tighter assay; align allocations to PH/INK grades and update forecast mix for ACETYL-EAA in DOM. | E14: 0.12 | F14: 0.67 | G14: 2026-02-06T10:50:00.000Z | H14: forecast input | I14: FC202602-DOM-ACETYL
A15: SIG202602-0013 | B15: News (S&P Global Platts) | C15: US Gulf petrochemical rail delays may extend inland deliveries | D15: Platts mentions rail congestion; increase delivery buffers for Midwest and consider stocking WH_US_MID_CHI earlier. | E15: -0.19 | F15: 0.73 | G15: 2026-02-07T02:25:00.000Z | H15: exception | J15: EXC202602-0005
A16: SIG202602-0014 | B16: Finance note (FX/credit) | C16: Customer credit downgrade flagged for one EU distributor | D16: Credit team recommends tightening terms for the account; shift to Net 15 or Advance for EU orders until review completes. | E16: -0.33 | F16: 0.79 | G16: 2026-02-07T14:10:00.000Z | H16: exception | J16: EXC202602-0006
A17: SIG202602-0015 | B17: News (ICIS) | C17: Butanol availability steady; no near-term supply disruption | D17: Market commentary suggests stable n-butanol; keep BUTACE forecast assumptions unchanged for February. | E17: 0.05 | F17: 0.7 | G17: 2026-02-08T06:05:00.000Z | H17: forecast input | I17: FC202602-DOM-ACETYL
A18: SIG202602-0016 | B18: Internal memo (Plant Ops) | C18: DKD ester line yields improved after catalyst optimization | D18: Ops reports better yields; potential to lift DKD availability for export without increasing feed. Update FC202602-EU-DKD accordingly. | E18: 0.27 | F18: 0.88 | G18: 2026-02-08T11:55:00.000Z | H18: forecast input | I18: FC202602-EU-DKD
A19: SIG202602-0017 | B19: LSP bulletin | C19: Sharjah bonded warehouse adding DG segregation inspections | D19: New inspection step may add 1–2 days dwell; build buffer for MEA shipments routed via WH_UAE_SHJ. | E19: -0.16 | F19: 0.81 | G19: 2026-02-09T09:15:00.000Z | H19: exception | J19: EXC202602-0007
A20: SIG202602-0018 | B20: Internal email (Sales) | C20: Inquiry surge from APAC for bulk ethyl acetate ISO tanks | D20: Sales sees more ISO20 RFQs; pre-allocate ISO tanks and update FC202602-APAC-ACETYL volume expectations. | E20: 0.24 | F20: 0.72 | G20: 2026-02-09T13:45:00.000Z | H20: forecast input | I20: FC202602-APAC-ACETYL
A21: SIG202602-0019 | B21: Customer call note | C21: Domestic pharma customer requests expedited delivery for acetic anhydride | D21: Customer needs earlier delivery; check WH_IN_GUJ_AHD availability and prioritize dispatch under SLA_STD_DOM_T2. | E21: 0.08 | F21: 0.66 | G21: 2026-02-10T05:40:00.000Z | H21: exception | J21: EXC202602-0008
A22: SIG202602-0020 | B22: News (ICIS) | C22: EU REACH enforcement focus on SDS accuracy for solvents | D22: ICIS compliance note; run SDS/documentation audit for EU lots staged at TNK_EUR_GEN and TNK_EUR_RTM. | E22: -0.08 | F22: 0.75 | G22: 2026-02-10T12:30:00.000Z | H22: exception | J22: EXC202602-0009
A23: SIG202602-0021 | B23: Internal memo (Plant Ops) | C23: Planned maintenance window proposed for Mahad AA unit mid-March | D23: Ops proposes maintenance; consider building buffer inventory in February and updating March forecast for ACETYL-ACEANH. | E23: -0.1 | F23: 0.9 | G23: 2026-02-11T04:05:00.000Z | H23: forecast input | I23: FC202602-DOM-ACETYL
A24: SIG202602-0022 | B24: Finance note (FX/credit) | C24: Ocean insurance premiums inch up for DG cargo to EU | D24: Insurers signal surcharge for DG; incorporate into EU landed cost model for FLUORO and selected solvents. | E24: -0.06 | F24: 0.68 | G24: 2026-02-11T16:15:00.000Z | H24: forecast input | I24: FC202602-EU-FLUORO
A25: SIG202602-0023 | B25: LSP bulletin | C25: Antwerp terminal weekend cut-off changes for DG documentation | D25: Updated cut-offs may affect documentation sequencing; align export paperwork earlier for TNK_EUR_ANT receipts. | E25: -0.15 | F25: 0.77 | G25: 2026-02-12T07:35:00.000Z | H25: exception | J25: EXC202602-0010
A26: SIG202602-0024 | B26: Internal email (Sales) | C26: Distributor reports slower payments in North India coatings cluster | D26: Collections risk increasing; recommend Advance for new orders routed via WH_IN_NORTH_BAW until stabilization. | E26: -0.22 | F26: 0.73 | G26: 2026-02-12T10:05:00.000Z | H26: exception | J26: EXC202602-0011
A27: SIG202602-0025 | B27: News (S&P Global Platts) | C27: China demand uptick for specialty blocks amid inventory restocking | D27: Platts indicates restocking; consider incremental FLUORO volumes routed via APAC lanes and update FC202602-APAC-FLUORO. | E27: 0.29 | F27: 0.78 | G27: 2026-02-13T02:50:00.000Z | H27: forecast input | I27: FC202602-APAC-FLUORO
A28: SIG202602-0026 | B28: Customer call note | C28: US customer asks for COA turnaround within 24 hours | D28: Customer expects faster COA dispatch; ensure lab release timing aligns with SLA_EXPORT_US_T1_P and staging at CFS_IN_NHAV. | E28: 0.07 | F28: 0.62 | G28: 2026-02-13T17:20:00.000Z | H28: exception | J28: EXC202602-0012
A29: SIG202602-0027 | B29: Internal memo (Plant Ops) | C29: VOC abatement audit passed; no restrictions for bulk solvent loading | D29: Audit outcome positive; supports higher bulk load plan for Feb at MHD and export staging via CFS_IN_NHAV. | E29: 0.2 | F29: 0.85 | G29: 2026-02-14T06:30:00.000Z | H29: forecast input | I29: FC202602-DOM-ACETYL
A30: SIG202602-0028 | B30: News (ICIS) | C30: Diketene logistics constrained; cold-chain slots limited | D30: ICIS notes chilled storage scarcity; confirm 2-8°C capacity at LTE and plan receipts earlier to avoid stockouts. | E30: -0.18 | F30: 0.81 | G30: 2026-02-14T12:05:00.000Z | H30: forecast input | I30: FC202602-DOM-DKD
A31: SIG202602-0029 | B31: LSP bulletin | C31: US East warehouse labor shortages may slow unloading | D31: 3PL warns of slower receiving at WH_US_EAST_NJ; route some replenishments to WH_US_MID_CHI if feasible. | E31: -0.17 | F31: 0.76 | G31: 2026-02-15T09:40:00.000Z | H31: exception | J31: EXC202602-0013
A32: SIG202602-0030 | B32: Internal email (Sales) | C32: EU customer requests smaller lots; more DR200_UN shipments | D32: Shift toward drums increases handling; reserve DG pallet slots at TNK_EUR_RTM and adjust packaging mix forecast. | E32: 0.04 | F32: 0.7 | G32: 2026-02-15T14:25:00.000Z | H32: forecast input | I32: FC202602-EU-ACETYL
A33: SIG202602-0031 | B33: News (S&P Global Platts) | C33: Middle East buyers negotiating lower solvent prices | D33: Platts reports softer MEA pricing; protect margins via freight optimization and monitor WH_UAE_SHJ throughput. | E33: -0.11 | F33: 0.69 | G33: 2026-02-16T03:55:00.000Z | H33: forecast input | I33: FC202602-MEA-ACETYL
A34: SIG202602-0032 | B34: Customer call note | C34: Domestic adhesive customer requests weekly deliveries to reduce storage | D34: Customer wants more frequent drops; validate route capacity from WH_IN_WEST_BHI and consolidate with nearby accounts. | E34: 0.06 | F34: 0.61 | G34: 2026-02-16T11:10:00.000Z | H34: forecast input | I34: FC202602-DOM-ACETYL
A35: SIG202602-0033 | B35: Internal memo (Plant Ops) | C35: Powder bagging line dust collection maintenance scheduled | D35: Bagging downtime expected; pre-pack ARYLIDE lots and avoid late-Feb BAG25 commitments. | E35: -0.2 | F35: 0.87 | G35: 2026-02-17T05:15:00.000Z | H35: exception | J35: EXC202602-0014
A36: SIG202602-0034 | B36: Finance note (FX/credit) | C36: Customer payment improved; consider restoring Net 30 selectively | D36: Credit team notes improvement for select accounts; allow Net 30 for A-rated customers while keeping C on Advance. | E36: 0.1 | F36: 0.65 | G36: 2026-02-18T09:05:00.000Z | H36: forecast input | I36: FC202602-DOM-ACETYL
A37: SIG202602-0035 | B37: LSP bulletin | C37: Genoa terminal revises hazardous cargo documentation checklist | D37: New checklist may cause document rework; ensure SDS/IMO declarations are complete before TNK_EUR_GEN receipt. | E37: -0.13 | F37: 0.8 | G37: 2026-02-19T07:00:00.000Z | H37: exception | J37: EXC202602-0015
A38: SIG202602-0036 | B38: News (ICIS) | C38: Acetaldehyde handling advisory following regional incident | D38: ICIS safety note; re-verify handling SOPs and UN drum integrity for ACE shipments through WH_IN_GUJ_AHD. | E38: -0.09 | F38: 0.73 | G38: 2026-02-20T04:45:00.000Z | H38: exception | J38: EXC202602-0016
A39: SIG202602-0037 | B39: Internal email (Sales) | C39: APAC distributor proposes annual contract for DKD intermediates | D39: Opportunity to lock volumes; align with LTE DKD capacity and update FC202602-APAC-DKD baseline assumptions. | E39: 0.23 | F39: 0.72 | G39: 2026-02-21T13:25:00.000Z | H39: forecast input | I39: FC202602-APAC-DKD
A40: SIG202602-0038 | B40: Customer call note | C40: EU customer asks for REACH dossier reference in shipping docs | D40: Ensure documentation packet includes REACH references; stage compliant packs at TNK_EUR_ANT to avoid clearance delays. | E40: 0.02 | F40: 0.6 | G40: 2026-02-23T08:10:00.000Z | H40: exception | J40: EXC202602-0017
A41: SIG202602-0039 | B41: Internal memo (Plant Ops) | C41: Dahej project timeline update; utilities commissioning risk flagged | D41: Project memo highlights utility commissioning risk; do not rely on DHJ in near-term capacity planning and keep buffers at MHD/LTE. | E41: -0.07 | F41: 0.84 | G41: 2026-02-24T06:20:00.000Z | H41: forecast input | I41: FC202602-DOM-ACETYL
A42: SIG202602-0040 | B42: News (S&P Global Platts) | C42: US customer inventory build for spring season supports solvent uptick | D42: Platts indicates seasonal build; increase AMER acetyl volume outlook and pre-position inventory at WH_US_EAST_NJ. | E42: 0.25 | F42: 0.79 | G42: 2026-02-26T03:35:00.000Z | H42: forecast input | I42: FC202602-AMER-ACETYL

Sheet Forecasts
A1: Mean | B1: =AVERAGE(F5:F28) -> 3201.875
A2: St Deviation (%) | B2: 0.05
A3: Total per month / No. of entries | B3: 24
A4: Forecast ID (Primary Key) | B4: Demand Region ID (FK) | C4: Forecast Date | D4: Forecast Horizon | E4: Product Family | F4: Quantity | G4: S&OP Event ID (FK)
A5: FC-DOM-ACETYL | B5: DOM | C5: 46112 | D5: Monthly | E5: ACETYL | F5: 5700 | G5: SOP202603-DOM
A6: FC-EU-ACETYL | B6: EU | C6: 46112 | D6: Monthly | E6: ACETYL | F6: 5415 | G6: SOP202603-EU
A7: FC-AMER-ACETYL | B7: AMER | C7: 46112 | D7: Monthly | E7: ACETYL | F7: 5130 | G7: SOP202603-AMER
A8: FC-APAC-ACETYL | B8: APAC | C8: 46112 | D8: Monthly | E8: ACETYL | F8: 4845 | G8: SOP202603-APAC
A9: FC-MEA-ACETYL | B9: MEA | C9: 46112 | D9: Monthly | E9: ACETYL | F9: 3420 | G9: SOP202603-MEA
A10: FC-ROW-ACETYL | B10: ROW | C10: 46112 | D10: Monthly | E10: ACETYL | F10: 2280 | G10: SOP202603-ROW
A11: FC-DOM-DKD | B11: DOM | C11: 46112 | D11: Monthly | E11: DKD | F11: 5650 | G11: SOP202603-DOM
A12: FC-EU-DKD | B12: EU | C12: 46112 | D12: Monthly | E12: DKD | F12: 5367.5 | G12: SOP202603-EU
A13: FC-AMER-DKD | B13: AMER | C13: 46112 | D13: Monthly | E13: DKD | F13: 5085 | G13: SOP202603-AMER
A14: FC-APAC-DKD | B14: APAC | C14: 46112 | D14: Monthly | E14: DKD | F14: 4802.5 | G14: SOP202603-APAC
A15: FC-MEA-DKD | B15: MEA | C15: 46112 | D15: Monthly | E15: DKD | F15: 3390 | G15: SOP202603-MEA
A16: FC-ROW-DKD | B16: ROW | C16: 46112 | D16: Monthly | E16: DKD | F16: 2260 | G16: SOP202603-ROW
... A28: FC-ROW-FLUORO | B28: ROW | C28: 46112 | D28: Monthly | E28: FLUORO | F28: 720 | G28: SOP202603-ROW

Sheet SOP Events
A1: S&OP Event ID (Primary Key) | B1: Frequency | C1: Horizon | D1: Region Scope (Region ID FK) | E1: Date | F1: Minutes
A2: SOP202601-DOM | B2: Monthly | C2: 1M | D2: DOM | E2: 2026-01-15T18:30:00.000Z | F2: Illustrative monthly S&OP (DOM)
A3: SOP202601-EU | B3: Monthly | C3: 1M | D3: EU | E3: 2026-01-16T18:30:00.000Z | F3: Illustrative monthly S&OP (EU)
A4: SOP202601-AMER | B4: Monthly | C4: 1M | D4: AMER | E4: 2026-01-17T18:30:00.000Z | F4: Illustrative monthly S&OP (AMER)
A5: SOP202601-APAC | B5: Monthly | C5: 1M | D5: APAC | E5: 2026-01-14T18:30:00.000Z | F5: Illustrative monthly S&OP (APAC)
A6: SOP202602-DOM | B6: Monthly | C6: 1M | D6: DOM | E6: 2026-02-15T18:30:00.000Z | F6: Illustrative monthly S&OP (DOM)
A7: SOP202602-EU | B7: Monthly | C7: 1M | D7: EU | E7: 2026-02-16T18:30:00.000Z | F7: Illustrative monthly S&OP (EU)
A8: SOP202602-AMER | B8: Monthly | C8: 1M | D8: AMER | E8: 2026-02-17T18:30:00.000Z | F8: Illustrative monthly S&OP (AMER)
A9: SOP202602-APAC | B9: Monthly | C9: 1M | D9: APAC | E9: 2026-02-14T18:30:00.000Z | F9: Illustrative monthly S&OP (APAC)
A10: SOP202603-DOM | B10: Monthly | C10: 1M | D10: DOM | E10: 2026-03-15T18:30:00.000Z | F10: Illustrative monthly S&OP (DOM)
A11: SOP202603-EU | B11: Monthly | C11: 1M | D11: EU | E11: 2026-03-16T18:30:00.000Z | F11: Illustrative monthly S&OP (EU)
A12: SOP202603-AMER | B12: Monthly | C12: 1M | D12: AMER | E12: 2026-03-17T18:30:00.000Z | F12: Illustrative monthly S&OP (AMER)
A13: SOP202603-APAC | B13: Monthly | C13: 1M | D13: APAC | E13: 2026-03-14T18:30:00.000Z | F13: Illustrative monthly S&OP (APAC)

Sheet Capacity Reservations
A1: Mean | B1: 378.87
A2: St Deviation (%) | B2: 0.05
A3: Total per month / No. of entries | B3: 60
A4: Capacity Reservation ID (Primary Key) | B4: S&OP Event ID (FK) | C4: Product Family | D4: Line ID (FK) | E4: Reserved Quantity (MT) | F4: Planned Start Date | G4: Planned End Date | H4: Status
A5: CR202603-0001 | B5: SOP202603-DOM | C5: ACETYL | D5: LINE_MHD_EA_TRAIN1 | E5: 397.12 | F5: 46082 | G5: 46085 | H5: Draft
A6: CR202603-0002 | B6: SOP202603-EU | C6: ACETYL | D6: LINE_MHD_AA_ANHY | E6: 388.64 | F6: 46084 | G6: 46088 | H6: Draft
A7: CR202603-0003 | B7: SOP202603-AMER | C7: ACETYL | D7: LINE_MHD_SOL_BLEND | E7: 365.84 | F7: 46086 | G7: 46091 | H7: Draft
A8: CR202603-0004 | B8: SOP202602-DOM | C8: ACETYL | D8: LINE_MHD_EA_TRAIN1 | E8: 362.13 | F8: 46088 | G8: 46094 | H8: Draft
A9: CR202603-0005 | B9: SOP202602-EU | C9: ACETYL | D9: LINE_MHD_AA_ANHY | E9: 382.95 | F9: 46090 | G9: 46097 | H9: Draft
A10: CR202603-0006 | B10: SOP202602-AMER | C10: ACETYL | D10: LINE_MHD_SOL_BLEND | E10: 397.79 | F10: 46092 | G10: 46095 | H10: Draft
A11: CR202603-0007 | B11: SOP202603-DOM | C11: ACETYL | D11: LINE_MHD_EA_TRAIN1 | E11: 384.91 | F11: 46094 | G11: 46098 | H11: Draft
A12: CR202603-0008 | B12: SOP202603-EU | C12: ACETYL | D12: LINE_MHD_AA_ANHY | E12: 363.19 | F12: 46096 | G12: 46101 | H12: Draft
A13: CR202603-0009 | B13: SOP202603-AMER | C13: ACETYL | D13: LINE_MHD_SOL_BLEND | E13: 364.44 | F13: 46098 | G13: 46104 | H13: Draft
A14: CR202603-0010 | B14: SOP202602-DOM | C14: ACETYL | D14: LINE_MHD_EA_TRAIN1 | E14: 386.83 | F14: 46100 | G14: 46107 | H14: Draft
A15: CR202603-0011 | B15: SOP202602-EU | C15: ACETYL | D15: LINE_MHD_AA_ANHY | E15: 397.56 | F15: 46102 | G15: 46105 | H15: Draft
A16: CR202603-0012 | B16: SOP202602-AMER | C16: ACETYL | D16: LINE_MHD_SOL_BLEND | E16: 380.91 | F16: 46104 | G16: 46108 | H16: Draft
... A64: CR202603-0060 | B64: SOP202602-APAC | C64: DKD | D64: LINE_LTE_FLR_BLOCK200 | E64: 360.45 | F64: 46088 | G64: 46095 | H64: Approved

Sheet Material Requirements Plan
A1: Mean | B1: 159.12
A2: St Deviation (%) | B2: 0.1
A3: Total per month / No. of entries | B3: 150
A4: MRP ID (Primary Key) | B4: Capacity Reservation ID (FK) | C4: product_family | D4: SKU Code (FK) | E4: gross_requirement_qty | F4: onhand_qty | G4: scheduled_receipts_qty | H4: net_requirement_qty | I4: uom | J4: std_lead_time_days | K4: recommended_order_release_date | L4: priority | M4: notes
A5: MRP202603-0001 | B5: CR202603-0001 | C5: ACETYL | D5: RM-ETH-AL-64197 | E5: 213.18 | F5: 38.18 | G5: 7.91 | H5: =MAX(0,E5-F5-G5) -> 167.09 | I5: MT | J5: 8 | K5: 46074 | L5: Medium | M5: ACETYL input RM-ETH-AL-64197; align procurement to March runs; illustrative.
A6: MRP202603-0002 | B6: CR202603-0002 | C6: ACETYL | D6: RM-ETH-AL-64219 | E6: 241.01 | F6: 38.74 | G6: 46.34 | H6: =MAX(0,E6-F6-G6) -> 155.93 | I6: MT | J6: 9 | K6: 46074 | L6: Medium | M6: ACETYL input RM-ETH-AL-64219; align procurement to March runs; illustrative.
A7: MRP202603-0003 | B7: CR202603-0003 | C7: ACETYL | D7: RM-SUL-AC-10477 | E7: 242.45 | F7: 18.47 | G7: 47.59 | H7: =MAX(0,E7-F7-G7) -> 176.39 | I7: MT | J7: 5 | K7: 46079 | L7: Medium | M7: ACETYL input RM-SUL-AC-10477; align procurement to March runs; illustrative.
A8: MRP202603-0004 | B8: CR202603-0004 | C8: ACETYL | D8: RM-ETH-AL-64175 | E8: 185.4 | F8: 7.56 | G8: 6.47 | H8: =MAX(0,E8-F8-G8) -> 171.37 | I8: MT | J8: 7 | K8: 46078 | L8: Medium | M8: ACETYL input RM-ETH-AL-64175; align procurement to March runs; illustrative.
A9: MRP202603-0005 | B9: CR202603-0005 | C9: ACETYL | D9: RM-ETH-AL-64197 | E9: 235.34 | F9: 63.83 | G9: 6.98 | H9: =MAX(0,E9-F9-G9) -> 164.53 | I9: MT | J9: 8 | K9: 46078 | L9: Medium | M9: ACETYL input RM-ETH-AL-64197; align procurement to March runs; illustrative.
A10: MRP202603-0006 | B10: CR202603-0006 | C10: ACETYL | D10: RM-ETH-AL-64197 | E10: 183.23 | F10: 10.03 | G10: 14.36 | H10: =MAX(0,E10-F10-G10) -> 158.84 | I10: MT | J10: 8 | K10: 46079 | L10: Medium | M10: ACETYL input RM-ETH-AL-64197; align procurement to March runs; illustrative.
A11: MRP202603-0007 | B11: CR202603-0007 | C11: ACETYL | D11: RM-AAC-GL-23011 | E11: 226.02 | F11: 40.36 | G11: 11.3 | H11: =MAX(0,E11-F11-G11) -> 174.36 | I11: MT | J11: 10 | K11: 46078 | L11: Medium | M11: ACETYL input RM-AAC-GL-23011; align procurement to March runs; illustrative.
A12: MRP202603-0008 | B12: CR202603-0008 | C12: DKD | D12: INT-KET-674828 | E12: 252.93 | F12: 52.28 | G12: 36.73 | H12: =MAX(0,E12-F12-G12) -> 163.92 | I12: MT | J12: 0 | K12: 46089 | L12: Medium | M12: DKD input INT-KET-674828; align procurement to March runs; illustrative.
A13: MRP202603-0009 | B13: CR202603-0009 | C13: ACETYL | D13: RM-BUT-NB-51720 | E13: 245.79 | F13: 60.01 | G13: 0.52 | H13: =MAX(0,E13-F13-G13) -> 185.26 | I13: MT | J13: 14 | K13: 46076 | L13: Medium | M13: ACETYL input RM-BUT-NB-51720; align procurement to March runs; illustrative.
A14: MRP202603-0010 | B14: CR202603-0010 | C14: ACETYL | D14: RM-ETH-AL-64197 | E14: 245.63 | F14: 65.97 | G14: 2.73 | H14: =MAX(0,E14-F14-G14) -> 176.93 | I14: MT | J14: 8 | K14: 46083 | L14: Medium | M14: ACETYL input RM-ETH-AL-64197; align procurement to March runs; illustrative.
A15: MRP202603-0011 | B15: CR202603-0011 | C15: DKD | D15: INT-KET-674828 | E15: 220.07 | F15: 26.28 | G15: 40.67 | H15: =MAX(0,E15-F15-G15) -> 153.12 | I15: MT | J15: 0 | K15: 46092 | L15: Medium | M15: DKD input INT-KET-674828; align procurement to March runs; illustrative.
A16: MRP202603-0012 | B16: CR202603-0012 | C16: ACETYL | D16: RM-NAO-CP-77811 | E16: 212.33 | F16: 6.66 | G16: 42.23 | H16: =MAX(0,E16-F16-G16) -> 163.44 | I16: MT | J16: 8 | K16: 46085 | L16: Medium | M16: ACETYL input RM-NAO-CP-77811; align procurement to March runs; illustrative.
... A154: MRP202603-0150 | B154: CR202603-0030 | C154: ACETYL | D154: RM-ETH-AL-64241 | E154: 125.22 | F154: 32.01 | G154: 35.08 | H154: =MAX(0,E154-F154-G154) -> 58.13 | I154: MT | J154: 10 | K154: 46081 | L154: Low | M154: ACETYL input RM-ETH-AL-64241; align procurement to March runs; illustrative.

Sheet Production Plan
A1: Mean
A2: St Deviation (%)
A3: Total per month / No. of entries | B3: 100
A4: Production Plan ID (PK) | B4: Capacity Reservations (FK) | C4: SKU ID (FK) | D4: Line ID (FK) | E4: Planned Start | F4: Planned End | G4: Required Quantity | H4: Estimated Scrappage (%) | I4: Quality Defect Rate (%) | J4: Planned Quantity | K4: Status
A5: PP202603-0001 | B5: CR202603-0001 | C5: ESS-ACETYL-ETHACE-LM-98.5-NEAT-BULK-DST | D5: LINE_MHD_EA_TRAIN2 | E5: 46082 | F5: 46082 | G5: 322.54 | H5: 0.029427372 | I5: 0.012078417 | J5: 330 | K5: Completed
A6: PP202603-0002 | B6: CR202603-0002 | C6: SPI-ACETYL-ACEANH-PH-98.6-NEAT-DR200_UN-MHD | D6: LINE_MHD_AA_ANHY | E6: 46083 | F6: 46085 | G6: 315.09 | H6: 0.024456604 | I6: 0.0065603031 | J6: 330 | K6: Completed
A7: PP202603-0003 | B7: CR202603-0003 | C7: SPI-DKD-DKDINT-IND-98.4-NEAT-ISO20-DHJ | D7: LINE_LTE_DKD_ESTER2 | E7: 46084 | F7: 46084 | G7: 41.73 | H7: 0.028126867 | I7: 0.024144046 | J7: 43.56 | K7: Completed
A8: PP202603-0004 | B8: CR202603-0004 | C8: ESS-ACETYL-BUTACE-TECH-98.3-NEAT-DR200-DHJ | D8: LINE_MHD_BA_BATCH1 | E8: 46085 | F8: 46088 | G8: 323.46 | H8: 0.023440115 | I8: 0.010597471 | J8: 330 | K8: Completed
A9: PP202603-0005 | B9: CR202603-0005 | C9: ESS-ACETYL-MAA-LM-98.4-NEAT-IBC1KL-DST | D9: LINE_MHD_EA_TRAIN1 | E9: 46085 | F9: 46085 | G9: 317.9 | H9: 0.012010283 | I9: 0.015989966 | J9: 330 | K9: Completed
A10: PP202603-0006 | B10: CR202603-0006 | C10: SPI-ACETYL-EAA-IND-99.2-NEAT-DR200-MHD | D10: LINE_MHD_EA_TRAIN1 | E10: 46087 | F10: 46090 | G10: 229.34 | H10: 0.025018376 | I10: 0.012875562 | J10: 232.39 | K10: Completed
A11: PP202603-0007 | B11: CR202603-0007 | C11: ESS-ACETYL-AAEM-TECH-98.8-NEAT-BULK-LTE | D11: LINE_MHD_AAEM_REACT1 | E11: 46088 | F11: 46090 | G11: 205.17 | H11: 0.02003091 | I11: 0.023945339 | J11: 215.21 | K11: Completed
A12: PP202603-0008 | B12: CR202603-0008 | C12: SPI-ACETYL-ETHACE-TECH-99.9-NEAT-BULK-LTE | D12: LINE_MHD_EA_TRAIN2 | E12: 46088 | F12: 46088 | G12: 275.34 | H12: 0.0029222421 | I12: 0.01513302 | J12: 282.47 | K12: Completed
A13: PP202603-0009 | B13: CR202603-0009 | C13: ESS-ACETYL-ACEANH-TECH-98.1-NEAT-ISO20-DHJ | D13: LINE_MHD_AA_ANHY | E13: 46090 | F13: 46091 | G13: 213.42 | H13: 0.0059754162 | I13: 0.02383883 | J13: 220.46 | K13: Completed
A14: PP202603-0010 | B14: CR202603-0010 | C14: ESS-ACETYL-ACE-TECH-98.8-NEAT-DR200_UN-DST | D14: LINE_MHD_EA_TRAIN1 | E14: 46090 | F14: 46091 | G14: 268.25 | H14: 0.015674906 | I14: 0.013564058 | J14: 277.93 | K14: Completed
A15: PP202603-0011 | B15: CR202603-0011 | C15: ESS-ACETYL-BUTACE-IND-98.3-NEAT-ISO20-MHD | D15: LINE_MHD_BA_BATCH1 | E15: 46090 | F15: 46093 | G15: 251 | H15: 0.012155138 | I15: 0.026021618 | J15: 255.03 | K15: Released
A16: PP202603-0012 | B16: CR202603-0012 | C16: SPI-ACETYL-MAA-TECH-98.7-NEAT-DR200-LTE | D16: LINE_MHD_EA_TRAIN1 | E16: 46091 | F16: 46091 | G16: 264.48 | H16: 0.011472411 | I16: 0.0026256883 | J16: 271.77 | K16: Completed
... A104: PP202603-0100 | B104: CR202603-0040 | C104: ESS-ACETYL-ACEANH-IND-98.8-NEAT-BULK-MHD | D104: LINE_MHD_AA_ANHY | E104: 46088 | F104: 46090 | G104: 231.3 | H104: 0.0029671446 | I104: 0.023461791 | J104: 238.83 | K104: Completed
J105: =SUM(J5:J104) -> 22277.42

Sheet Purchase Requisitions
A1: Mean | B1: 64.98
A2: Std Dev | B2: 5%
A3: Total per month / No. of entries | B3: 360
A4: PR Line ID (PK) | B4: Production Plan ID (FK) | C4: Requisition Date | D4: SKU_id (FK) | E4: Quantity | F4: Need by Date | G4: Status
A5: PR202603-0001 | B5: PP202603-0001 | C5: 2026-03-07 | D5: RM-OAN-AS-55102 | E5: 65.63 | F5: 2026-03-14 | G5: Rfx released
A6: PR202603-0002 | B6: PP202603-0001 | C6: 2026-03-13 | D6: RM-PDH-CB-61302 | E6: 62.38 | F6: 2026-03-22 | G6: Rfx released
A7: PR202603-0003 | B7: PP202603-0001 | C7: 2026-03-19 | D7: INT-ACE-ANH-772001 | E7: 66.28 | F7: 2026-03-30 | G7: Rfx released
A8: PR202603-0004 | B8: PP202603-0001 | C8: 2026-03-25 | D8: RM-ETL-AC-11804 | E8: 63.03 | F8: 2026-04-07 | G8: Rfx released
A9: PR202603-0005 | B9: PP202603-0002 | C9: 2026-03-31 | D9: RM-HCL-32-65019 | E9: 66.93 | F9: 2026-04-15 | G9: Rfx released
A10: PR202603-0006 | B10: PP202603-0002 | C10: 2026-03-06 | D10: INT-KET-674828 | E10: 63.68 | F10: 2026-03-12 | G10: PO Issued
A11: PR202603-0007 | B11: PP202603-0002 | C11: 2026-03-12 | D11: RM-ETH-AL-64197 | E11: 67.58 | F11: 2026-03-20 | G11: PO Issued
A12: PR202603-0008 | B12: PP202603-0002 | C12: 2026-03-18 | D12: RM-PCA-AN-77210 | E12: 64.33 | F12: 2026-03-28 | G12: PO Issued
A13: PR202603-0009 | B13: PP202603-0003 | C13: 2026-03-24 | D13: RM-TOL-SV-90412 | E13: 68.23 | F13: 2026-04-05 | G13: PO Issued
A14: PR202603-0010 | B14: PP202603-0003 | C14: 2026-03-30 | D14: INT-ARY-INT-558903 | E14: 64.98 | F14: 2026-04-13 | G14: PO Issued
A15: PR202603-0011 | B15: PP202603-0003 | C15: 2026-03-05 | D15: RM-AAC-GL-23011 | E15: 61.73 | F15: 2026-03-10 | G15: PO Issued
A16: PR202603-0012 | B16: PP202603-0003 | C16: 2026-03-11 | D16: RM-SUL-AC-10477 | E16: 65.63 | F16: 2026-03-18 | G16: GRN Issued
... A364: PR202603-0360 | B364: PP202603-0100 | C364: 2026-03-22 | D364: INT-KET-INS-145120 | E364: 64.33 | F364: 2026-04-01 | G364: Rfx released

Sheet Plants
A1: plant_code (Primary Key) | B1: plant_name | C1: city | D1: district | E1: state | F1: country | G1: latitude | H1: longitude | I1: business_unit | J1: operating_status | K1: iso_certifications | L1: responsible_care | M1: port_proximity_km | N1: storage_tankage_kl | O1: hazardous_waste_facility | P1: ehs_notes | Q1: effective_from | R1: status | S1: notes
A2: MHD | B2: Mahad Manufacturing Complex | C2: Mahad | D2: Raigad | E2: Maharashtra | F2: India | G2: 18.083 | H2: 73.416 | I2: Essentials | J2: Active | K2: ISO 9001:2015, ISO 14001:2015, ISO 45001:2018 | L2: Yes | M2: 110 | N2: 8500 | O2: Yes | P2: Solvent handling with VOC controls; DG drum yard; firewater ring main. | Q2: 2020-04-01 | R2: Active | S2: Illustrative site master; aligned to annual report commentary on capacity debottlenecking.
A3: LTE | B3: Lote Parshuram Specialty Site | C3: Lote Parshuram | D3: Ratnagiri | E3: Maharashtra | F3: India | G3: 17.85 | H3: 73.225 | I3: Specialties | J3: Active | K3: ISO 9001:2015, ISO 14001:2015, ISO 45001:2018 | L3: Yes | M3: 45 | N3: 2500 | O3: Yes | P3: Fluoro/DG segregation; nitrogen blanketing; low-temp storage (2-8°C) for sensitive inputs. | Q3: 2021-07-01 | R3: Active | S3: Illustrative; aligned to annual report commentary on specialty expansions and compliance.
A4: DHJ | B4: Dahej Greenfield Project | C4: Dahej | D4: Bharuch | E4: Gujarat | F4: India | G4: 21.705 | H4: 72.624 | I4: Mixed | J4: Planned | K4: Planned: ISO 9001:2015, ISO 14001:2015, ISO 45001:2018 | L4: No | M4: 15 | N4: 6000 | O4: Planned | P4: Planned VOC abatement; hazardous area classification; port-linked bulk logistics. | Q4: 2026-01-01 | R4: Planned | S4: Illustrative greenfield entry; aligned to commentary on future multi-product flexibility.
A5: DST | B5: External Distillery Cluster (Partner) | C5: N/A | D5: N/A | E5: Maharashtra | F5: India | G5: 0 | H5: 0 | I5: External | J5: External | K5: N/A | L5: N/A | M5: 0 | N5: 0 | O5: N/A | P5: Partner feedstock sourcing; QA sampling at receipt; limited EHS control beyond supplier audits. | Q5: 2020-01-01 | R5: External | S5: Illustrative partner location for ethanol/feedstock; aligned to commentary on backward integration sourcing.
A6: TPL | B6: Tarapur Tolling / Third-Party Site | C6: Tarapur | D6: Palghar | E6: Maharashtra | F6: India | G6: 19.862 | H6: 72.742 | I6: External | J6: External | K6: ISO 9001:2015 | L6: No | M6: 70 | N6: 1200 | O6: No | P6: Tolling operations under contract; DG packing per SOP; batch traceability via COA. | Q6: 2022-04-01 | R6: External | S6: Illustrative tolling site to manage peak demand; aligned to annual report commentary on flexible manufacturing.

Sheet Lines
A1: line_id (Primary Key) | B1: line_name | C1: plant_id (FK) | D1: area | E1: family | F1: process | G1: design_capacity_tpd | H1: pack_out | I1: hazard_zone | J1: commissioned_on | K1: status | L1: notes
A2: LINE_MHD_EA_TRAIN1 | B2: Ethyl Acetate Train 1 | C2: MHD | D2: Solvents Block A | E2: ACETYL | F2: Continuous Esterification | G2: 220 | H2: ISO20,IBC1KL,BULK | I2: Flammable (Zone 2) | J2: 42156 | K2: Active | L2: High-volume ester line; VOC abatement; illustrative
A3: LINE_MHD_EA_TRAIN2 | B3: Ethyl Acetate Train 2 | C3: MHD | D3: Solvents Block A | E3: ACETYL | F3: Continuous Esterification | G3: 260 | H3: ISO20,IBC1KL,BULK | I3: Flammable (Zone 2) | J3: 43388 | K3: Active | L3: Debottlenecked for export grades; illustrative
A4: LINE_MHD_AA_ANHY | B4: Acetic Anhydride Unit | C4: MHD | D4: Acid Anhydrides | E4: ACETYL | F4: Continuous Dehydration/Distillation | G4: 180 | H4: ISO20,DR200_UN,BULK | I4: Corrosive/Flammable | J4: 42449 | K4: Active | L4: Corrosive service metallurgy; UN packing; illustrative
A5: LINE_MHD_BA_BATCH1 | B5: Butyl Acetate Batch 1 | C5: MHD | D5: Solvents Block B | E5: ACETYL | F5: Batch Esterification | G5: 120 | H5: ISO20,DR200,IBC1KL | I5: Flammable (Zone 2) | J5: 41948 | K5: Active | L5: Flexible campaign scheduling; illustrative
A6: LINE_MHD_AAEM_REACT1 | B6: AAEM Reactor Line 1 | C6: MHD | D6: Acrylates Area | E6: ACETYL | F6: Batch Esterification/Polymerizable | G6: 85 | H6: IBC1KL,DR200 | I6: Corrosive/Flammable | J6: 44440 | K6: Active | L6: Inhibitor dosing & low-temp controls; illustrative
A7: LINE_LTE_DKD_ESTER1 | B7: DKD Ester Line 1 | C7: LTE | D7: DKD Block | E7: DKD | F7: Condensation/Isolation | G7: 22 | H7: DR200,DR200_UN,IBC1KL | I7: Flammable (Zone 2) | J7: 43506 | K7: Active | L7: Moisture-sensitive handling; chilled utilities; illustrative
A8: LINE_LTE_DKD_ESTER2 | B8: DKD Ester Line 2 | C8: LTE | D8: DKD Block | E8: DKD | F8: Condensation/Isolation | G8: 28 | H8: DR200,DR200_UN,IBC1KL | I8: Flammable (Zone 2) | J8: 44798 | K8: Active | L8: Higher purity campaigns; illustrative
A9: LINE_LTE_ARY_1 | B9: Arylides Intermediate Line 1 | C9: LTE | D9: Arylides Block | E9: ARYLIDE | F9: Batch Condensation/Isolation | G9: 18 | H9: BAG25,DR200_UN | I9: Dust/Combustible | J9: 42867 | K9: Active | L9: Dust collection & ATEX practices; illustrative
A10: LINE_LTE_ARY_2 | B10: Arylides Intermediate Line 2 | C10: LTE | D10: Arylides Block | E10: ARYLIDE | F10: Batch Condensation/Isolation | G10: 24 | H10: BAG25,DR200_UN | I10: Dust/Combustible | J10: 44944 | K10: Active | L10: Wet cake handling; fast turnaround; illustrative
A11: LINE_LTE_FLR_BLOCK200 | B11: Fluoro Block Reactor 200L | C11: LTE | D11: Fluoro Suites | E11: FLUORO | F11: Electrochemical Fluorination | G11: 5 | H11: BAG25,DR200_UN | I11: DG (Fluoro) | J11: 44042 | K11: Active | L11: DG segregation; dedicated ventilation; illustrative
A12: LINE_LTE_FLR_BLOCK500 | B12: Fluoro Block Reactor 500L | C12: LTE | D12: Fluoro Suites | E12: FLUORO | F12: Electrochemical Fluorination | G12: 8 | H12: BAG25,DR200_UN | I12: DG (Fluoro) | J12: 45383 | K12: Active | L12: Scale-up for export blocks; illustrative
A13: LINE_DHJ_SOLV_TRAIN1 | B13: Dahej Solvents Train 1 | C13: DHJ | D13: Bulk Solvents | E13: ACETYL | F13: Continuous Esterification | G13: 300 | H13: ISO20,BULK | I13: Flammable (Zone 2) | J13: 46082 | K13: Planned | L13: Greenfield capacity; port-linked logistics; illustrative
... A17: LINE_LTE_DKD_AMIDE1 | B17: DKD Amidation Line 1 | C17: LTE | D17: DKD Block | E17: DKD | F17: Amidation/Condensation | G17: 15 | H17: DR200,IBC1KL | I17: Flammable (Zone 2) | J17: 44136 | K17: Active | L17: Specialty DKD derivatives line; campaign-based; illustrative

Sheet Production Runs
A1: Mean | B1: 242.58
A2: Std Dev | B2: 0.02
A3: Total per month / No. of entries | B3: 300
A4: Production Run ID (PK) | B4: Production Plan ID (FK) | C4: Line ID (FK) | D4: SKU ID (FK) | E4: Quantity Produced | F4: Scrappage (%) | G4: Quality Defects (%) | H4: Usable Quantity | I4: Start DateTime | J4: End DateTime
A5: RUN202603-0001 | B5: PP202603-0001 | C5: LINE_MHD_EA_TRAIN2 | D5: ESS-ACETYL-ETHACE-LM-98.5-NEAT-BULK-DST | E5: 295.54 | F5: 0.004005008 | G5: 0.015392692 | H5: =E5*(1-F5)*(1-G5) -> 289.82542 | I5: 2026-03-10T10:05:00.000Z | J5: 2026-03-11T01:05:00.000Z
A6: RUN202603-0002 | B6: PP202603-0002 | C6: LINE_MHD_AA_ANHY | D6: SPI-ACETYL-ACEANH-PH-98.6-NEAT-DR200_UN-MHD | E6: 317.86 | F6: 0.021598605 | G6: 0.016378724 | H6: =E6*(1-F6)*(1-G6) -> 305.90097 | I6: 2026-03-31T17:37:00.000Z | J6: 2026-04-01T11:37:00.000Z
A7: RUN202603-0003 | B7: PP202603-0003 | C7: LINE_LTE_DKD_ESTER2 | D7: SPI-DKD-DKDINT-IND-98.4-NEAT-ISO20-DHJ | E7: 207.39 | F7: 0.024164118 | G7: 0.004212081 | H7: =E7*(1-F7)*(1-G7) -> 201.52617 | I7: 2026-03-30T10:04:00.000Z | J7: 2026-03-31T02:04:00.000Z
A8: RUN202603-0004 | B8: PP202603-0004 | C8: LINE_MHD_BA_BATCH1 | D8: ESS-ACETYL-BUTACE-TECH-98.3-NEAT-DR200-DHJ | E8: 255.26 | F8: 0.016632503 | G8: 0.015803835 | H8: =E8*(1-F8)*(1-G8) -> 247.0474 | I8: 2026-03-05T12:25:00.000Z | J8: 2026-03-05T22:25:00.000Z
A9: RUN202603-0005 | B9: PP202603-0005 | C9: LINE_MHD_EA_TRAIN1 | D9: ESS-ACETYL-MAA-LM-98.4-NEAT-IBC1KL-DST | E9: 230.68 | F9: 0.013109801 | G9: 0.012569532 | H9: =E9*(1-F9)*(1-G9) -> 224.7943 | I9: 2026-03-09T08:18:00.000Z | J9: 2026-03-09T15:18:00.000Z
A10: RUN202603-0006 | B10: PP202603-0006 | C10: LINE_MHD_EA_TRAIN1 | D10: SPI-ACETYL-EAA-IND-99.2-NEAT-DR200-MHD | E10: 255.04 | F10: 0.0020940909 | G10: 0.0024837327 | H10: =E10*(1-F10)*(1-G10) -> 253.8738 | I10: 2026-03-31T09:12:00.000Z | J10: 2026-03-31T20:12:00.000Z
A11: RUN202603-0007 | B11: PP202603-0007 | C11: LINE_MHD_AAEM_REACT1 | D11: ESS-ACETYL-AAEM-TECH-98.8-NEAT-BULK-LTE | E11: 231.41 | F11: 0.0094443753 | G11: 0.010555892 | H11: =E11*(1-F11)*(1-G11) -> 226.80481 | I11: 2026-03-19T08:06:00.000Z | J11: 2026-03-20T02:06:00.000Z
A12: RUN202603-0008 | B12: PP202603-0008 | C12: LINE_MHD_EA_TRAIN2 | D12: SPI-ACETYL-ETHACE-TECH-99.9-NEAT-BULK-LTE | E12: 287.06 | F12: 0.023922163 | G12: 0.010161624 | H12: =E12*(1-F12)*(1-G12) -> 277.34569 | I12: 2026-03-03T12:00:00.000Z | J12: 2026-03-04T06:00:00.000Z
A13: RUN202603-0009 | B13: PP202603-0009 | C13: LINE_MHD_AA_ANHY | D13: ESS-ACETYL-ACEANH-TECH-98.1-NEAT-ISO20-DHJ | E13: 319.6 | F13: 0.0015044543 | G13: 0.012535561 | H13: =E13*(1-F13)*(1-G13) -> 315.11884 | I13: 2026-03-31T12:54:00.000Z | J13: 2026-03-31T23:54:00.000Z
A14: RUN202603-0010 | B14: PP202603-0010 | C14: LINE_MHD_EA_TRAIN1 | D14: ESS-ACETYL-ACE-TECH-98.8-NEAT-DR200_UN-DST | E14: 225.04 | F14: 0.026138072 | G14: 0.0070476926 | H14: =E14*(1-F14)*(1-G14) -> 217.61333 | I14: 2026-03-09T07:58:00.000Z | J14: 2026-03-09T19:58:00.000Z
A15: RUN202603-0011 | B15: PP202603-0011 | C15: LINE_MHD_BA_BATCH1 | D15: ESS-ACETYL-BUTACE-IND-98.3-NEAT-ISO20-MHD | E15: 296.31 | F15: 0.012485019 | G15: 0.0022517377 | H15: =E15*(1-F15)*(1-G15) -> 291.95168 | I15: 2026-03-29T05:32:00.000Z | J15: 2026-03-29T22:32:00.000Z
A16: RUN202603-0012 | B16: PP202603-0012 | C16: LINE_MHD_EA_TRAIN1 | D16: SPI-ACETYL-MAA-TECH-98.7-NEAT-DR200-LTE | E16: 279.51 | F16: 0.027561675 | G16: 0.016048706 | H16: =E16*(1-F16)*(1-G16) -> 267.4441 | I16: 2026-03-28T02:44:00.000Z | J16: 2026-03-28T20:44:00.000Z
... A304: RUN202603-0300 | B304: PP202603-0100 | C304: LINE_MHD_AA_ANHY | D304: ESS-ACETYL-ACEANH-IND-98.8-NEAT-BULK-MHD | E304: 277.85 | F304: 0.020307589 | G304: 0.018308216 | H304: =E304*(1-F304)*(1-G304) -> 267.2239 | I304: 2026-03-12T22:01:00.000Z | J304: 2026-03-13T08:01:00.000Z

Sheet Batches
A1: Mean
A2: St Deviation (%)
A3: Total per month / No. of entries | B3: 500
A4: Batch No./Lot No. | B4: Production Run ID (FK) | C4: PR Line Item_ID (FK) | D4: SKU ID (FK) | E4: Quantity | F4: Date of Manufacture/Delivery
A5: BATFG202603-0001 | B5: RUN202603-0001 | D5: ESS-ACETYL-ETHACE-LM-98.5-NEAT-BULK-DST | E5: 48.3 | F5: 46092
A6: BATFG202603-0002 | B6: RUN202603-0001 | D6: ESS-ACETYL-ETHACE-LM-98.5-NEAT-BULK-DST | E6: 48.3 | F6: 46092
A7: BATFG202603-0003 | B7: RUN202603-0001 | D7: ESS-ACETYL-ETHACE-LM-98.5-NEAT-BULK-DST | E7: 48.3 | F7: 46092
A8: BATFG202603-0004 | B8: RUN202603-0001 | D8: ESS-ACETYL-ETHACE-LM-98.5-NEAT-BULK-DST | E8: 48.3 | F8: 46092
A9: BATFG202603-0005 | B9: RUN202603-0001 | D9: ESS-ACETYL-ETHACE-LM-98.5-NEAT-BULK-DST | E9: 48.3 | F9: 46092
A10: BATFG202603-0006 | B10: RUN202603-0001 | D10: ESS-ACETYL-ETHACE-LM-98.5-NEAT-BULK-DST | E10: 48.33 | F10: 46092
A11: BATFG202603-0007 | B11: RUN202603-0002 | D11: SPI-ACETYL-ACEANH-PH-98.6-NEAT-DR200_UN-MHD | E11: 50.98 | F11: 46113
A12: BATFG202603-0008 | B12: RUN202603-0002 | D12: SPI-ACETYL-ACEANH-PH-98.6-NEAT-DR200_UN-MHD | E12: 50.98 | F12: 46113
A13: BATFG202603-0009 | B13: RUN202603-0002 | D13: SPI-ACETYL-ACEANH-PH-98.6-NEAT-DR200_UN-MHD | E13: 50.98 | F13: 46113
A14: BATFG202603-0010 | B14: RUN202603-0002 | D14: SPI-ACETYL-ACEANH-PH-98.6-NEAT-DR200_UN-MHD | E14: 50.98 | F14: 46113
A15: BATFG202603-0011 | B15: RUN202603-0002 | D15: SPI-ACETYL-ACEANH-PH-98.6-NEAT-DR200_UN-MHD | E15: 50.98 | F15: 46113
A16: BATFG202603-0012 | B16: RUN202603-0002 | D16: SPI-ACETYL-ACEANH-PH-98.6-NEAT-DR200_UN-MHD | E16: 51 | F16: 46113
... A404: BATFG202603-0400 | B404: RUN202603-0068 | D404: SPI-ACETYL-MAA-TECH-98.7-NEAT-DR200-LTE | E404: 53.93 | F404: 46105
A405: BATRW202603-0001 | C405: PR202603-0012 | D405: RM-SUL-AC-10477 | E405: 45.96 | F405: 2026-03-18
A406: BATRW202603-0002 | C406: PR202603-0012 | D406: RM-SUL-AC-10477 | E406: 45.96 | F406: 2026-03-18
A407: BATRW202603-0003 | C407: PR202603-0013 | D407: RM-PTC-CAT-27190 | E407: 45.96 | F407: 2026-03-26
A408: BATRW202603-0004 | C408: PR202603-0013 | D408: RM-PTC-CAT-27190 | E408: 45.96 | F408: 2026-03-26
A409: BATRW202603-0005 | C409: PR202603-0014 | D409: INT-AAA-EMM-990812 | E409: 45.95 | F409: 2026-04-03
A410: BATRW202603-0006 | C410: PR202603-0014 | D410: INT-AAA-EMM-990812 | E410: 42.18 | F410: 2026-04-03
A411: BATRW202603-0007 | C411: PR202603-0015 | D411: RM-MTH-AA-40218 | E411: 42.18 | F411: 2026-04-11
A412: BATRW202603-0008 | C412: PR202603-0015 | D412: RM-MTH-AA-40218 | E412: 42.18 | F412: 2026-04-11
A413: BATRW202603-0009 | C413: PR202603-0016 | D413: RM-ACN-SV-33120 | E413: 42.18 | F413: 2026-03-19
A414: BATRW202603-0010 | C414: PR202603-0016 | D414: RM-ACN-SV-33120 | E414: 42.19 | F414: 2026-03-19
A415: BATRW202603-0011 | C415: PR202603-0032 | D415: INT-AAA-EMM-990812 | E415: 46.33 | F415: 2026-03-21
A416: BATRW202603-0012 | C416: PR202603-0032 | D416: INT-AAA-EMM-990812 | E416: 46.33 | F416: 2026-03-21
... A504: BATRW202603-0100 | C504: PR202603-0196 | D504: RM-OAN-AS-55102 | E504: 51.93 | F504: 2026-04-11

Sheet Storage Nodes
A1: node_id (Primary Key) | B1: node_name | C1: node_type | D1: country | E1: city | F1: operator | G1: storage_type | H1: pack_supported | I1: families_supported | J1: dg_classes_supported | K1: licenses | L1: docs_capability | M1: temperature_control | N1: capacity_kl | O1: pallet_positions | P1: throughput_tpm | Q1: latitude | R1: longitude | S1: notes
A2: TNK_EUR_RTM | B2: Rotterdam Tank Terminal | C2: Tank Terminal | D2: Netherlands | E2: Rotterdam | F2: Vopak (illustrative) | G2: Tank | H2: BULK,ISO20 | I2: ACETYL,DKD | J2: 3,8 | K2: ADR,IMDG,Seveso | L2: SDS,COA,REACH,BL | M2: Ambient | N2: 25000 | O2: 0 | P2: 18000 | Q2: 51.955 | R2: 4.142 | S2: EU hub terminal; IMO-ready lanes; illustrative
A3: TNK_EUR_ANT | B3: Antwerp Chemical Tank Farm | C3: Tank Terminal | D3: Belgium | E3: Antwerp | F3: ADPO (illustrative) | G3: Tank | H3: BULK,ISO20 | I3: ACETYL,DKD,ARYLIDE | J3: 3,8 | K3: ADR,IMDG,Seveso | L3: SDS,COA,REACH,CMR | M3: Ambient | N3: 18000 | O3: 0 | P3: 12000 | Q3: 51.26 | R3: 4.4 | S3: Benelux distribution; customs brokerage supported; illustrative
A4: TNK_EUR_GEN | B4: Genoa Port Tank Terminal | C4: Tank Terminal | D4: Italy | E4: Genoa | F4: PSA (illustrative) | G4: Tank | H4: BULK,ISO20 | I4: ACETYL | J4: 3 | K4: ADR,IMDG | L4: SDS,COA,BL | M4: Ambient | N4: 9000 | O4: 0 | P4: 6500 | Q4: 44.405 | R4: 8.944 | S4: Mediterranean hub; coastal feeder connectivity; illustrative
A5: WH_EU_DEU_HAM | B5: Hamburg Chemical Warehouse | C5: Warehouse | D5: Germany | E5: Hamburg | F5: Kuehne+Nagel (illustrative) | G5: Warehouse | H5: DR200_UN,DR200,IBC1KL,BAG25 | I5: ACETYL,ARYLIDE,FLUORO | J5: 3,6.1,8 | K5: ADR,IMDG | L5: SDS,COA,REACH,CMR | M5: Ambient | N5: 1200 | O5: 4200 | P5: 3500 | Q5: 53.546 | R5: 9.966 | S5: EU inland consolidation; DG segregation; illustrative
A6: CFS_IN_NHAV | B6: JNPT / Nhava Sheva CFS | C6: Port/CFS | D6: India | E6: Navi Mumbai | F6: DP World CFS (illustrative) | G6: Yard/Warehouse | H6: ISO20,DR200_UN,DR200,IBC1KL,BAG25,BULK | I6: ACETYL,DKD,ARYLIDE,FLUORO | J6: 3,8 | K6: Customs Bonded,CFS License | L6: SDS,COA,Invoice,Packing List,BL | M6: Ambient | N6: 5000 | O6: 2500 | P6: 9000 | Q6: 18.948 | R6: 72.953 | S6: Export stuffing/de-stuffing; bonded operations; illustrative
A7: WH_IN_WEST_BHI | B7: Bhiwandi Distribution Center | C7: Warehouse | D7: India | E7: Bhiwandi | F7: 3PL West (illustrative) | G7: Warehouse | H7: DR200_UN,DR200,IBC1KL,BAG25 | I7: ACETYL,DKD,ARYLIDE,FLUORO | J7: 3,8 | K7: State Warehouse License,PESO (DG) | L7: COA,Invoice,Ewaybill | M7: Ambient | N7: 900 | O7: 6000 | P7: 6500 | Q7: 19.281 | R7: 73.056 | S7: Mumbai metro servicing; cross-dock to customers; illustrative
A8: WH_IN_GUJ_AHD | B8: Ahmedabad Chemicals Warehouse | C8: Warehouse | D8: India | E8: Ahmedabad | F8: 3PL Gujarat (illustrative) | G8: Warehouse | H8: DR200_UN,DR200,IBC1KL,BAG25 | I8: ACETYL,DKD,ARYLIDE | J8: 3,8 | K8: State Warehouse License | L8: COA,Invoice,Ewaybill | M8: Ambient | N8: 700 | O8: 4200 | P8: 4800 | Q8: 23.022 | R8: 72.571 | S8: Gujarat industrial belt coverage; DG compliant bays; illustrative
A9: WH_IN_SOUTH_HYD | B9: Hyderabad Regional Warehouse | C9: Warehouse | D9: India | E9: Hyderabad | F9: 3PL South (illustrative) | G9: Warehouse | H9: DR200,IBC1KL,BAG25 | I9: ACETYL,ARYLIDE,FLUORO | J9: 3,8 | K9: State Warehouse License | L9: COA,Invoice,Ewaybill | M9: Ambient | N9: 550 | O9: 3800 | P9: 4200 | Q9: 17.385 | R9: 78.487 | S9: South India servicing; powder and liquid zones; illustrative
A10: WH_IN_NORTH_BAW | B10: Bhiwadi/Gurgaon Logistics Hub | C10: Warehouse | D10: India | E10: Bhiwadi | F10: 3PL North (illustrative) | G10: Warehouse | H10: DR200,IBC1KL,BAG25 | I10: ACETYL,ARYLIDE | J10: 3,8 | K10: State Warehouse License | L10: COA,Invoice,Ewaybill | M10: Ambient | N10: 600 | O10: 4500 | P10: 5000 | Q10: 28.21 | R10: 76.865 | S10: NCR coverage; faster deliveries to North customers; illustrative
A11: WH_IN_EAST_KOL | B11: Kolkata Warehouse (East) | C11: Warehouse | D11: India | E11: Kolkata | F11: 3PL East (illustrative) | G11: Warehouse | H11: DR200,IBC1KL,BAG25 | I11: ACETYL,ARYLIDE | J11: 3,8 | K11: State Warehouse License | L11: COA,Invoice,Ewaybill | M11: Ambient | N11: 420 | O11: 2600 | P11: 2800 | Q11: 22.572 | R11: 88.364 | S11: Eastern corridor support; port-adjacent distribution; illustrative
A12: WH_US_EAST_NJ | B12: US East Warehouse (New Jersey) | C12: Warehouse | D12: United States | E12: Newark, NJ | F12: 3PL US East (illustrative) | G12: Warehouse | H12: DR200_UN,DR200,IBC1KL | I12: ACETYL,DKD | J12: 3,8 | K12: DOT HazMat,OSHA | L12: SDS,COA,Commercial Invoice,US customs docs | M12: Ambient | N12: 800 | O12: 3200 | P12: 3800 | Q12: 40.735 | R12: -74.172 | S12: East coast import distribution; HazMat compliant; illustrative
A13: WH_US_MID_CHI | B13: US Midwest Warehouse (Chicago) | C13: Warehouse | D13: United States | E13: Chicago, IL | F13: 3PL US Midwest (illustrative) | G13: Warehouse | H13: DR200,IBC1KL,BAG25 | I13: ACETYL,ARYLIDE,FLUORO | J13: 3,8 | K13: DOT HazMat,OSHA | L13: SDS,COA,US inland POD | M13: Ambient | N13: 650 | O13: 2800 | P13: 3100 | Q13: 41.878 | R13: -87.63 | S13: Midwest coverage; LTL-friendly operations; illustrative
A14: WH_UAE_SHJ | B14: Sharjah Bonded Warehouse | C14: Bonded Warehouse | D14: United Arab Emirates | E14: Sharjah | F14: Freezone Operator (illustrative) | G14: Warehouse | H14: DR200_UN,IBC1KL,BAG25 | I14: ACETYL,DKD,FLUORO | J14: 3,8 | K14: FTZ Bonded,Customs | L14: SDS,COA,Invoice,Packing List | M14: Ambient | N14: 500 | O14: 2200 | P14: 2600 | Q14: 25.346 | R14: 55.42 | S14: GCC re-export node; LC/documentation support; illustrative
A15: WH_CHN_SHA | B15: Shanghai Chemical Warehouse | C15: Warehouse | D15: China | E15: Shanghai | F15: 3PL China (illustrative) | G15: Warehouse | H15: DR200_UN,DR200,IBC1KL,BAG25 | I15: ACETYL,FLUORO | J15: 3,8 | K15: China DG Warehouse License | L15: SDS,COA,CIQ/Customs docs | M15: Ambient | N15: 700 | O15: 3000 | P15: 3400 | Q15: 31.23 | R15: 121.474 | S15: China distribution; local DG compliance; illustrative

Sheet Bins
A1: bin_id (Primary Key) | B1: node_id (FK) | C1: zone | D1: aisle | E1: rack | F1: level | G1: position | H1: bin_type | I1: families_allowed | J1: pack_supported | K1: dg_allowed | L1: temp_control | M1: max_units | N1: max_weight_kg | O1: segregation_class | P1: status | Q1: notes
A2: TNK_EUR_RTM_TB01 | B2: TNK_EUR_RTM | C2: TANK | D2: - | E2: - | F2: - | G2: - | H2: TANK_BAY | I2: ACETYL,DKD | J2: BULK,ISO20 | K2: DG per IMDG (Bulk) | L2: Ambient | M2: 1 | N2: 30000 | O2: DG_Bulk | P2: Active | Q2: Tank bay (bulk liquids); illustrative
A3: TNK_EUR_RTM_TB02 | B3: TNK_EUR_RTM | C3: TANK | D3: - | E3: - | F3: - | G3: - | H3: TANK_BAY | I3: ACETYL,DKD | J3: BULK,ISO20 | K3: DG per IMDG (Bulk) | L3: Ambient | M3: 1 | N3: 30000 | O3: DG_Bulk | P3: Active | Q3: Tank bay (bulk liquids); illustrative
A4: TNK_EUR_RTM_TB03 | B4: TNK_EUR_RTM | C4: TANK | D4: - | E4: - | F4: - | G4: - | H4: TANK_BAY | I4: ACETYL,DKD | J4: BULK,ISO20 | K4: DG per IMDG (Bulk) | L4: Ambient | M4: 1 | N4: 30000 | O4: DG_Bulk | P4: Active | Q4: Tank bay (bulk liquids); illustrative
A5: TNK_EUR_RTM_TB04 | B5: TNK_EUR_RTM | C5: TANK | D5: - | E5: - | F5: - | G5: - | H5: TANK_BAY | I5: ACETYL,DKD | J5: BULK,ISO20 | K5: DG per IMDG (Bulk) | L5: Ambient | M5: 1 | N5: 30000 | O5: DG_Bulk | P5: Active | Q5: Tank bay (bulk liquids); illustrative
A6: TNK_EUR_RTM_TB05 | B6: TNK_EUR_RTM | C6: TANK | D6: - | E6: - | F6: - | G6: - | H6: TANK_BAY | I6: ACETYL,DKD | J6: BULK,ISO20 | K6: DG per IMDG (Bulk) | L6: Ambient | M6: 1 | N6: 30000 | O6: DG_Bulk | P6: Active | Q6: Tank bay (bulk liquids); illustrative
A7: TNK_EUR_RTM_TB06 | B7: TNK_EUR_RTM | C7: TANK | D7: - | E7: - | F7: - | G7: - | H7: TANK_BAY | I7: ACETYL,DKD | J7: BULK,ISO20 | K7: DG per IMDG (Bulk) | L7: Ambient | M7: 1 | N7: 30000 | O7: DG_Bulk | P7: Active | Q7: Tank bay (bulk liquids); illustrative
A8: TNK_EUR_RTM_TB07 | B8: TNK_EUR_RTM | C8: TANK | D8: - | E8: - | F8: - | G8: - | H8: TANK_BAY | I8: ACETYL,DKD | J8: BULK,ISO20 | K8: DG per IMDG (Bulk) | L8: Ambient | M8: 1 | N8: 30000 | O8: DG_Bulk | P8: Active | Q8: Tank bay (bulk liquids); illustrative
A9: TNK_EUR_RTM_TB08 | B9: TNK_EUR_RTM | C9: TANK | D9: - | E9: - | F9: - | G9: - | H9: TANK_BAY | I9: ACETYL,DKD | J9: BULK,ISO20 | K9: DG per IMDG (Bulk) | L9: Ambient | M9: 1 | N9: 30000 | O9: DG_Bulk | P9: Active | Q9: Tank bay (bulk liquids); illustrative
A10: TNK_EUR_RTM_DZ-A-01 | B10: TNK_EUR_RTM | C10: DRUM | D10: A | E10: R01 | F10: 1 | G10: 1 | H10: PALLET_SLOT | I10: ACETYL,DKD | J10: DR200,DR200_UN,IBC1KL | K10: Flammable Liquids; Corrosive; DG per IMDG | L10: Ambient | M10: 4 | N10: 1200 | O10: DG_Pallet | P10: Active | Q10: DG pallet slot (drums/IBCs); illustrative
A11: TNK_EUR_RTM_DZ-A-02 | B11: TNK_EUR_RTM | C11: DRUM | D11: A | E11: R01 | F11: 1 | G11: 2 | H11: PALLET_SLOT | I11: ACETYL,DKD | J11: DR200,DR200_UN,IBC1KL | K11: Flammable Liquids; Corrosive; DG per IMDG | L11: Ambient | M11: 4 | N11: 1200 | O11: DG_Pallet | P11: Active | Q11: DG pallet slot (drums/IBCs); illustrative
A12: TNK_EUR_RTM_DZ-A-03 | B12: TNK_EUR_RTM | C12: DRUM | D12: A | E12: R01 | F12: 2 | G12: 1 | H12: PALLET_SLOT | I12: ACETYL,DKD | J12: DR200,DR200_UN,IBC1KL | K12: Flammable Liquids; Corrosive; DG per IMDG | L12: Ambient | M12: 4 | N12: 1200 | O12: DG_Pallet | P12: Active | Q12: DG pallet slot (drums/IBCs); illustrative
A13: TNK_EUR_RTM_DZ-A-04 | B13: TNK_EUR_RTM | C13: DRUM | D13: A | E13: R01 | F13: 2 | G13: 2 | H13: PALLET_SLOT | I13: ACETYL,DKD | J13: DR200,DR200_UN,IBC1KL | K13: Flammable Liquids; Corrosive; DG per IMDG | L13: Ambient | M13: 4 | N13: 1200 | O13: DG_Pallet | P13: Active | Q13: DG pallet slot (drums/IBCs); illustrative
A14: TNK_EUR_RTM_DZ-A-05 | B14: TNK_EUR_RTM | C14: DRUM | D14: A | E14: R02 | F14: 1 | G14: 1 | H14: PALLET_SLOT | I14: ACETYL,DKD | J14: DR200,DR200_UN,IBC1KL | K14: Flammable Liquids; Corrosive; DG per IMDG | L14: Ambient | M14: 4 | N14: 1200 | O14: DG_Pallet | P14: Active | Q14: DG pallet slot (drums/IBCs); illustrative
A15: TNK_EUR_RTM_DZ-A-06 | B15: TNK_EUR_RTM | C15: DRUM | D15: A | E15: R02 | F15: 1 | G15: 2 | H15: PALLET_SLOT | I15: ACETYL,DKD | J15: DR200,DR200_UN,IBC1KL | K15: Flammable Liquids; Corrosive; DG per IMDG | L15: Ambient | M15: 4 | N15: 1200 | O15: DG_Pallet | P15: Active | Q15: DG pallet slot (drums/IBCs); illustrative
A16: TNK_EUR_RTM_DZ-A-07 | B16: TNK_EUR_RTM | C16: DRUM | D16: A | E16: R02 | F16: 2 | G16: 1 | H16: PALLET_SLOT | I16: ACETYL,DKD | J16: DR200,DR200_UN,IBC1KL | K16: Flammable Liquids; Corrosive; DG per IMDG | L16: Ambient | M16: 4 | N16: 1200 | O16: DG_Pallet | P16: Active | Q16: DG pallet slot (drums/IBCs); illustrative
A17: TNK_EUR_RTM_DZ-A-08 | B17: TNK_EUR_RTM | C17: DRUM | D17: A | E17: R02 | F17: 2 | G17: 2 | H17: PALLET_SLOT | I17: ACETYL,DKD | J17: DR200,DR200_UN,IBC1KL | K17: Flammable Liquids; Corrosive; DG per IMDG | L17: Ambient | M17: 4 | N17: 1200 | O17: DG_Pallet | P17: Active | Q17: DG pallet slot (drums/IBCs); illustrative
A18: TNK_EUR_RTM_DZ-A-09 | B18: TNK_EUR_RTM | C18: DRUM | D18: A | E18: R03 | F18: 1 | G18: 1 | H18: PALLET_SLOT | I18: ACETYL,DKD | J18: DR200,DR200_UN,IBC1KL | K18: Flammable Liquids; Corrosive; DG per IMDG | L18: Ambient | M18: 4 | N18: 1200 | O18: DG_Pallet | P18: Active | Q18: DG pallet slot (drums/IBCs); illustrative
A19: TNK_EUR_RTM_DZ-A-10 | B19: TNK_EUR_RTM | C19: DRUM | D19: A | E19: R03 | F19: 1 | G19: 2 | H19: PALLET_SLOT | I19: ACETYL,DKD | J19: DR200,DR200_UN,IBC1KL | K19: Flammable Liquids; Corrosive; DG per IMDG | L19: Ambient | M19: 4 | N19: 1200 | O19: DG_Pallet | P19: Active | Q19: DG pallet slot (drums/IBCs); illustrative
A20: TNK_EUR_RTM_DZ-B-01 | B20: TNK_EUR_RTM | C20: DRUM | D20: B | E20: R01 | F20: 1 | G20: 1 | H20: PALLET_SLOT | I20: ACETYL,DKD | J20: DR200,DR200_UN,IBC1KL | K20: Flammable Liquids; Corrosive; DG per IMDG | L20: Ambient | M20: 4 | N20: 1200 | O20: DG_Pallet | P20: Active | Q20: DG pallet slot (drums/IBCs); illustrative
A21: TNK_EUR_RTM_DZ-B-02 | B21: TNK_EUR_RTM | C21: DRUM | D21: B | E21: R01 | F21: 1 | G21: 2 | H21: PALLET_SLOT | I21: ACETYL,DKD | J21: DR200,DR200_UN,IBC1KL | K21: Flammable Liquids; Corrosive; DG per IMDG | L21: Ambient | M21: 4 | N21: 1200 | O21: DG_Pallet | P21: Active | Q21: DG pallet slot (drums/IBCs); illustrative
... A69: TNK_EUR_RTM_BZ-B-10 | B69: TNK_EUR_RTM | C69: BAG | D69: B | E69: R02 | F69: 5 | G69: 1 | H69: PALLET_SLOT | I69: ACETYL,DKD | J69: BAG25 | K69: Dust/Combustible; DG per IMDG (as applicable) | L69: Ambient | M69: 50 | N69: 1200 | O69: SOLID_BAG | P69: Active | Q69: Pallet slot for bags/solids; illustrative
A70: TNK_EUR_ANT_TB01 | B70: TNK_EUR_ANT | C70: TANK | D70: - | E70: - | F70: - | G70: - | H70: TANK_BAY | I70: ACETYL,DKD,ARYLIDE | J70: BULK,ISO20 | K70: DG per IMDG (Bulk) | L70: Ambient | M70: 1 | N70: 30000 | O70: DG_Bulk | P70: Active | Q70: Tank bay (bulk liquids); illustrative
A71: TNK_EUR_ANT_TB02 | B71: TNK_EUR_ANT | C71: TANK | D71: - | E71: - | F71: - | G71: - | H71: TANK_BAY | I71: ACETYL,DKD,ARYLIDE | J71: BULK,ISO20 | K71: DG per IMDG (Bulk) | L71: Ambient | M71: 1 | N71: 30000 | O71: DG_Bulk | P71: Active | Q71: Tank bay (bulk liquids); illustrative
A72: TNK_EUR_ANT_TB03 | B72: TNK_EUR_ANT | C72: TANK | D72: - | E72: - | F72: - | G72: - | H72: TANK_BAY | I72: ACETYL,DKD,ARYLIDE | J72: BULK,ISO20 | K72: DG per IMDG (Bulk) | L72: Ambient | M72: 1 | N72: 30000 | O72: DG_Bulk | P72: Active | Q72: Tank bay (bulk liquids); illustrative
A73: TNK_EUR_ANT_TB04 | B73: TNK_EUR_ANT | C73: TANK | D73: - | E73: - | F73: - | G73: - | H73: TANK_BAY | I73: ACETYL,DKD,ARYLIDE | J73: BULK,ISO20 | K73: DG per IMDG (Bulk) | L73: Ambient | M73: 1 | N73: 30000 | O73: DG_Bulk | P73: Active | Q73: Tank bay (bulk liquids); illustrative
A74: TNK_EUR_ANT_TB05 | B74: TNK_EUR_ANT | C74: TANK | D74: - | E74: - | F74: - | G74: - | H74: TANK_BAY | I74: ACETYL,DKD,ARYLIDE | J74: BULK,ISO20 | K74: DG per IMDG (Bulk) | L74: Ambient | M74: 1 | N74: 30000 | O74: DG_Bulk | P74: Active | Q74: Tank bay (bulk liquids); illustrative
A75: TNK_EUR_ANT_TB06 | B75: TNK_EUR_ANT | C75: TANK | D75: - | E75: - | F75: - | G75: - | H75: TANK_BAY | I75: ACETYL,DKD,ARYLIDE | J75: BULK,ISO20 | K75: DG per IMDG (Bulk) | L75: Ambient | M75: 1 | N75: 30000 | O75: DG_Bulk | P75: Active | Q75: Tank bay (bulk liquids); illustrative
A76: TNK_EUR_ANT_TB07 | B76: TNK_EUR_ANT | C76: TANK | D76: - | E76: - | F76: - | G76: - | H76: TANK_BAY | I76: ACETYL,DKD,ARYLIDE | J76: BULK,ISO20 | K76: DG per IMDG (Bulk) | L76: Ambient | M76: 1 | N76: 30000 | O76: DG_Bulk | P76: Active | Q76: Tank bay (bulk liquids); illustrative
A77: TNK_EUR_ANT_TB08 | B77: TNK_EUR_ANT | C77: TANK | D77: - | E77: - | F77: - | G77: - | H77: TANK_BAY | I77: ACETYL,DKD,ARYLIDE | J77: BULK,ISO20 | K77: DG per IMDG (Bulk) | L77: Ambient | M77: 1 | N77: 30000 | O77: DG_Bulk | P77: Active | Q77: Tank bay (bulk liquids); illustrative
A78: TNK_EUR_ANT_DZ-A-01 | B78: TNK_EUR_ANT | C78: DRUM | D78: A | E78: R01 | F78: 1 | G78: 1 | H78: PALLET_SLOT | I78: ACETYL,DKD,ARYLIDE | J78: DR200,DR200_UN,IBC1KL | K78: Flammable Liquids; Corrosive; DG per IMDG | L78: Ambient | M78: 4 | N78: 1200 | O78: DG_Pallet | P78: Active | Q78: DG pallet slot (drums/IBCs); illustrative
A79: TNK_EUR_ANT_DZ-A-02 | B79: TNK_EUR_ANT | C79: DRUM | D79: A | E79: R01 | F79: 1 | G79: 2 | H79: PALLET_SLOT | I79: ACETYL,DKD,ARYLIDE | J79: DR200,DR200_UN,IBC1KL | K79: Flammable Liquids; Corrosive; DG per IMDG | L79: Ambient | M79: 4 | N79: 1200 | O79: DG_Pallet | P79: Active | Q79: DG pallet slot (drums/IBCs); illustrative
A80: TNK_EUR_ANT_DZ-A-03 | B80: TNK_EUR_ANT | C80: DRUM | D80: A | E80: R01 | F80: 2 | G80: 1 | H80: PALLET_SLOT | I80: ACETYL,DKD,ARYLIDE | J80: DR200,DR200_UN,IBC1KL | K80: Flammable Liquids; Corrosive; DG per IMDG | L80: Ambient | M80: 4 | N80: 1200 | O80: DG_Pallet | P80: Active | Q80: DG pallet slot (drums/IBCs); illustrative
A81: TNK_EUR_ANT_DZ-A-04 | B81: TNK_EUR_ANT | C81: DRUM | D81: A | E81: R01 | F81: 2 | G81: 2 | H81: PALLET_SLOT | I81: ACETYL,DKD,ARYLIDE | J81: DR200,DR200_UN,IBC1KL | K81: Flammable Liquids; Corrosive; DG per IMDG | L81: Ambient | M81: 4 | N81: 1200 | O81: DG_Pallet | P81: Active | Q81: DG pallet slot (drums/IBCs); illustrative
A82: TNK_EUR_ANT_DZ-A-05 | B82: TNK_EUR_ANT | C82: DRUM | D82: A | E82: R02 | F82: 1 | G82: 1 | H82: PALLET_SLOT | I82: ACETYL,DKD,ARYLIDE | J82: DR200,DR200_UN,IBC1KL | K82: Flammable Liquids; Corrosive; DG per IMDG | L82: Ambient | M82: 4 | N82: 1200 | O82: DG_Pallet | P82: Active | Q82: DG pallet slot (drums/IBCs); illustrative
A83: TNK_EUR_ANT_DZ-A-06 | B83: TNK_EUR_ANT | C83: DRUM | D83: A | E83: R02 | F83: 1 | G83: 2 | H83: PALLET_SLOT | I83: ACETYL,DKD,ARYLIDE | J83: DR200,DR200_UN,IBC1KL | K83: Flammable Liquids; Corrosive; DG per IMDG | L83: Ambient | M83: 4 | N83: 1200 | O83: DG_Pallet | P83: Active | Q83: DG pallet slot (drums/IBCs); illustrative
A84: TNK_EUR_ANT_DZ-A-07 | B84: TNK_EUR_ANT | C84: DRUM | D84: A | E84: R02 | F84: 2 | G84: 1 | H84: PALLET_SLOT | I84: ACETYL,DKD,ARYLIDE | J84: DR200,DR200_UN,IBC1KL | K84: Flammable Liquids; Corrosive; DG per IMDG | L84: Ambient | M84: 4 | N84: 1200 | O84: DG_Pallet | P84: Active | Q84: DG pallet slot (drums/IBCs); illustrative
A85: TNK_EUR_ANT_DZ-A-08 | B85: TNK_EUR_ANT | C85: DRUM | D85: A | E85: R02 | F85: 2 | G85: 2 | H85: PALLET_SLOT | I85: ACETYL,DKD,ARYLIDE | J85: DR200,DR200_UN,IBC1KL | K85: Flammable Liquids; Corrosive; DG per IMDG | L85: Ambient | M85: 4 | N85: 1200 | O85: DG_Pallet | P85: Active | Q85: DG pallet slot (drums/IBCs); illustrative
A86: TNK_EUR_ANT_DZ-A-09 | B86: TNK_EUR_ANT | C86: DRUM | D86: A | E86: R03 | F86: 1 | G86: 1 | H86: PALLET_SLOT | I86: ACETYL,DKD,ARYLIDE | J86: DR200,DR200_UN,IBC1KL | K86: Flammable Liquids; Corrosive; DG per IMDG | L86: Ambient | M86: 4 | N86: 1200 | O86: DG_Pallet | P86: Active | Q86: DG pallet slot (drums/IBCs); illustrative
A87: TNK_EUR_ANT_DZ-A-10 | B87: TNK_EUR_ANT | C87: DRUM | D87: A | E87: R03 | F87: 1 | G87: 2 | H87: PALLET_SLOT | I87: ACETYL,DKD,ARYLIDE | J87: DR200,DR200_UN,IBC1KL | K87: Flammable Liquids; Corrosive; DG per IMDG | L87: Ambient | M87: 4 | N87: 1200 | O87: DG_Pallet | P87: Active | Q87: DG pallet slot (drums/IBCs); illustrative
A88: TNK_EUR_ANT_DZ-B-01 | B88: TNK_EUR_ANT | C88: DRUM | D88: B | E88: R01 | F88: 1 | G88: 1 | H88: PALLET_SLOT | I88: ACETYL,DKD,ARYLIDE | J88: DR200,DR200_UN,IBC1KL | K88: Flammable Liquids; Corrosive; DG per IMDG | L88: Ambient | M88: 4 | N88: 1200 | O88: DG_Pallet | P88: Active | Q88: DG pallet slot (drums/IBCs); illustrative
A89: TNK_EUR_ANT_DZ-B-02 | B89: TNK_EUR_ANT | C89: DRUM | D89: B | E89: R01 | F89: 1 | G89: 2 | H89: PALLET_SLOT | I89: ACETYL,DKD,ARYLIDE | J89: DR200,DR200_UN,IBC1KL | K89: Flammable Liquids; Corrosive; DG per IMDG | L89: Ambient | M89: 4 | N89: 1200 | O89: DG_Pallet | P89: Active | Q89: DG pallet slot (drums/IBCs); illustrative
... A137: TNK_EUR_ANT_BZ-B-10 | B137: TNK_EUR_ANT | C137: BAG | D137: B | E137: R02 | F137: 5 | G137: 1 | H137: PALLET_SLOT | I137: ACETYL,DKD,ARYLIDE | J137: BAG25 | K137: Dust/Combustible; DG per IMDG (as applicable) | L137: Ambient | M137: 50 | N137: 1200 | O137: SOLID_BAG | P137: Active | Q137: Pallet slot for bags/solids; illustrative
A138: TNK_EUR_GEN_TB01 | B138: TNK_EUR_GEN | C138: TANK | D138: - | E138: - | F138: - | G138: - | H138: TANK_BAY | I138: ACETYL | J138: BULK,ISO20 | K138: DG per IMDG (Bulk) | L138: Ambient | M138: 1 | N138: 30000 | O138: DG_Bulk | P138: Active | Q138: Tank bay (bulk liquids); illustrative
A139: TNK_EUR_GEN_TB02 | B139: TNK_EUR_GEN | C139: TANK | D139: - | E139: - | F139: - | G139: - | H139: TANK_BAY | I139: ACETYL | J139: BULK,ISO20 | K139: DG per IMDG (Bulk) | L139: Ambient | M139: 1 | N139: 30000 | O139: DG_Bulk | P139: Active | Q139: Tank bay (bulk liquids); illustrative
A140: TNK_EUR_GEN_TB03 | B140: TNK_EUR_GEN | C140: TANK | D140: - | E140: - | F140: - | G140: - | H140: TANK_BAY | I140: ACETYL | J140: BULK,ISO20 | K140: DG per IMDG (Bulk) | L140: Ambient | M140: 1 | N140: 30000 | O140: DG_Bulk | P140: Active | Q140: Tank bay (bulk liquids); illustrative
A141: TNK_EUR_GEN_TB04 | B141: TNK_EUR_GEN | C141: TANK | D141: - | E141: - | F141: - | G141: - | H141: TANK_BAY | I141: ACETYL | J141: BULK,ISO20 | K141: DG per IMDG (Bulk) | L141: Ambient | M141: 1 | N141: 30000 | O141: DG_Bulk | P141: Active | Q141: Tank bay (bulk liquids); illustrative
A142: TNK_EUR_GEN_TB05 | B142: TNK_EUR_GEN | C142: TANK | D142: - | E142: - | F142: - | G142: - | H142: TANK_BAY | I142: ACETYL | J142: BULK,ISO20 | K142: DG per IMDG (Bulk) | L142: Ambient | M142: 1 | N142: 30000 | O142: DG_Bulk | P142: Active | Q142: Tank bay (bulk liquids); illustrative
A143: TNK_EUR_GEN_TB06 | B143: TNK_EUR_GEN | C143: TANK | D143: - | E143: - | F143: - | G143: - | H143: TANK_BAY | I143: ACETYL | J143: BULK,ISO20 | K143: DG per IMDG (Bulk) | L143: Ambient | M143: 1 | N143: 30000 | O143: DG_Bulk | P143: Active | Q143: Tank bay (bulk liquids); illustrative
A144: TNK_EUR_GEN_TB07 | B144: TNK_EUR_GEN | C144: TANK | D144: - | E144: - | F144: - | G144: - | H144: TANK_BAY | I144: ACETYL | J144: BULK,ISO20 | K144: DG per IMDG (Bulk) | L144: Ambient | M144: 1 | N144: 30000 | O144: DG_Bulk | P144: Active | Q144: Tank bay (bulk liquids); illustrative
A145: TNK_EUR_GEN_TB08 | B145: TNK_EUR_GEN | C145: TANK | D145: - | E145: - | F145: - | G145: - | H145: TANK_BAY | I145: ACETYL | J145: BULK,ISO20 | K145: DG per IMDG (Bulk) | L145: Ambient | M145: 1 | N145: 30000 | O145: DG_Bulk | P145: Active | Q145: Tank bay (bulk liquids); illustrative
A146: TNK_EUR_GEN_DZ-A-01 | B146: TNK_EUR_GEN | C146: DRUM | D146: A | E146: R01 | F146: 1 | G146: 1 | H146: PALLET_SLOT | I146: ACETYL | J146: DR200,DR200_UN,IBC1KL | K146: Flammable Liquids; Corrosive; DG per IMDG | L146: Ambient | M146: 4 | N146: 1200 | O146: DG_Pallet | P146: Active | Q146: DG pallet slot (drums/IBCs); illustrative
A147: TNK_EUR_GEN_DZ-A-02 | B147: TNK_EUR_GEN | C147: DRUM | D147: A | E147: R01 | F147: 1 | G147: 2 | H147: PALLET_SLOT | I147: ACETYL | J147: DR200,DR200_UN,IBC1KL | K147: Flammable Liquids; Corrosive; DG per IMDG | L147: Ambient | M147: 4 | N147: 1200 | O147: DG_Pallet | P147: Active | Q147: DG pallet slot (drums/IBCs); illustrative
A148: TNK_EUR_GEN_DZ-A-03 | B148: TNK_EUR_GEN | C148: DRUM | D148: A | E148: R01 | F148: 2 | G148: 1 | H148: PALLET_SLOT | I148: ACETYL | J148: DR200,DR200_UN,IBC1KL | K148: Flammable Liquids; Corrosive; DG per IMDG | L148: Ambient | M148: 4 | N148: 1200 | O148: DG_Pallet | P148: Active | Q148: DG pallet slot (drums/IBCs); illustrative
A149: TNK_EUR_GEN_DZ-A-04 | B149: TNK_EUR_GEN | C149: DRUM | D149: A | E149: R01 | F149: 2 | G149: 2 | H149: PALLET_SLOT | I149: ACETYL | J149: DR200,DR200_UN,IBC1KL | K149: Flammable Liquids; Corrosive; DG per IMDG | L149: Ambient | M149: 4 | N149: 1200 | O149: DG_Pallet | P149: Active | Q149: DG pallet slot (drums/IBCs); illustrative
A150: TNK_EUR_GEN_DZ-A-05 | B150: TNK_EUR_GEN | C150: DRUM | D150: A | E150: R02 | F150: 1 | G150: 1 | H150: PALLET_SLOT | I150: ACETYL | J150: DR200,DR200_UN,IBC1KL | K150: Flammable Liquids; Corrosive; DG per IMDG | L150: Ambient | M150: 4 | N150: 1200 | O150: DG_Pallet | P150: Active | Q150: DG pallet slot (drums/IBCs); illustrative
A151: TNK_EUR_GEN_DZ-A-06 | B151: TNK_EUR_GEN | C151: DRUM | D151: A | E151: R02 | F151: 1 | G151: 2 | H151: PALLET_SLOT | I151: ACETYL | J151: DR200,DR200_UN,IBC1KL | K151: Flammable Liquids; Corrosive; DG per IMDG | L151: Ambient | M151: 4 | N151: 1200 | O151: DG_Pallet | P151: Active | Q151: DG pallet slot (drums/IBCs); illustrative
A152: TNK_EUR_GEN_DZ-A-07 | B152: TNK_EUR_GEN | C152: DRUM | D152: A | E152: R02 | F152: 2 | G152: 1 | H152: PALLET_SLOT | I152: ACETYL | J152: DR200,DR200_UN,IBC1KL | K152: Flammable Liquids; Corrosive; DG per IMDG | L152: Ambient | M152: 4 | N152: 1200 | O152: DG_Pallet | P152: Active | Q152: DG pallet slot (drums/IBCs); illustrative
A153: TNK_EUR_GEN_DZ-A-08 | B153: TNK_EUR_GEN | C153: DRUM | D153: A | E153: R02 | F153: 2 | G153: 2 | H153: PALLET_SLOT | I153: ACETYL | J153: DR200,DR200_UN,IBC1KL | K153: Flammable Liquids; Corrosive; DG per IMDG | L153: Ambient | M153: 4 | N153: 1200 | O153: DG_Pallet | P153: Active | Q153: DG pallet slot (drums/IBCs); illustrative
A154: TNK_EUR_GEN_DZ-A-09 | B154: TNK_EUR_GEN | C154: DRUM | D154: A | E154: R03 | F154: 1 | G154: 1 | H154: PALLET_SLOT | I154: ACETYL | J154: DR200,DR200_UN,IBC1KL | K154: Flammable Liquids; Corrosive; DG per IMDG | L154: Ambient | M154: 4 | N154: 1200 | O154: DG_Pallet | P154: Active | Q154: DG pallet slot (drums/IBCs); illustrative
A155: TNK_EUR_GEN_DZ-A-10 | B155: TNK_EUR_GEN | C155: DRUM | D155: A | E155: R03 | F155: 1 | G155: 2 | H155: PALLET_SLOT | I155: ACETYL | J155: DR200,DR200_UN,IBC1KL | K155: Flammable Liquids; Corrosive; DG per IMDG | L155: Ambient | M155: 4 | N155: 1200 | O155: DG_Pallet | P155: Active | Q155: DG pallet slot (drums/IBCs); illustrative
A156: TNK_EUR_GEN_DZ-B-01 | B156: TNK_EUR_GEN | C156: DRUM | D156: B | E156: R01 | F156: 1 | G156: 1 | H156: PALLET_SLOT | I156: ACETYL | J156: DR200,DR200_UN,IBC1KL | K156: Flammable Liquids; Corrosive; DG per IMDG | L156: Ambient | M156: 4 | N156: 1200 | O156: DG_Pallet | P156: Active | Q156: DG pallet slot (drums/IBCs); illustrative
A157: TNK_EUR_GEN_DZ-B-02 | B157: TNK_EUR_GEN | C157: DRUM | D157: B | E157: R01 | F157: 1 | G157: 2 | H157: PALLET_SLOT | I157: ACETYL | J157: DR200,DR200_UN,IBC1KL | K157: Flammable Liquids; Corrosive; DG per IMDG | L157: Ambient | M157: 4 | N157: 1200 | O157: DG_Pallet | P157: Active | Q157: DG pallet slot (drums/IBCs); illustrative
... A268: WH_US_MID_CHI_BZ-B-02 | B268: WH_US_MID_CHI | C268: BAG | D268: B | E268: R01 | F268: 2 | G268: 1 | H268: PALLET_SLOT | I268: ACETYL,ARYLIDE,FLUORO | J268: BAG25 | K268: Dust/Combustible; DG as applicable | L268: Ambient | M268: 50 | N268: 1200 | O268: SOLID_BAG | P268: Active | Q268: Warehouse pallet slot (bags/solids); illustrative

Sheet On Hand inventory
A1: Mean | B1: 194.06
A2: St Deviation (%) | B2: 0.05
A3: Primary Key | B3: Batch ID (FK) | C3: Material Type | D3: Quantity (SOH) | E3: Bin ID (FK) | F3: As on Date | G3: Inventory Age (days) | H3: Inventory Value
A4: INVV202603-0001 | B4: BATFG202603-0001 | C4: FG | D4: 190.88 | E4: TNK_EUR_RTM_TB01 | F4: 46112 | G4: 27 | H4: 278457.65
A5: INVV202603-0002 | B5: BATFG202603-0002 | C5: FG | D5: 192.35 | E5: TNK_EUR_RTM_TB02 | F5: 46112 | G5: 38 | H5: 434120.49
A6: INVV202603-0003 | B6: BATFG202603-0003 | C6: FG | D6: 193.94 | E6: TNK_EUR_RTM_TB03 | F6: 46112 | G6: 24 | H6: 287461.75
A7: INVV202603-0004 | B7: BATFG202603-0004 | C7: FG | D7: 195.29 | E7: TNK_EUR_RTM_TB04 | F7: 46112 | G7: 28 | H7: 240017.27
A8: INVV202603-0005 | B8: BATFG202603-0005 | C8: FG | D8: 194.86 | E8: TNK_EUR_RTM_TB05 | F8: 46112 | G8: 35 | H8: 374766.44
A9: INVV202603-0006 | B9: BATFG202603-0006 | C9: FG | D9: 197.6 | E9: TNK_EUR_RTM_TB06 | F9: 46112 | G9: 33 | H9: 368111.02
A10: INVV202603-0007 | B10: BATFG202603-0013 | C10: FG | D10: 198.82 | E10: TNK_EUR_RTM_TB07 | F10: 46112 | G10: 38 | H10: 404725.94
A11: INVV202603-0008 | B11: BATFG202603-0014 | C11: FG | D11: 190.68 | E11: TNK_EUR_RTM_TB08 | F11: 46112 | G11: 25 | H11: 474156.33
A12: INVV202603-0009 | B12: BATFG202603-0015 | C12: FG | D12: 195.32 | E12: TNK_EUR_ANT_TB01 | F12: 46112 | G12: 41 | H12: 487842.95
A13: INVV202603-0010 | B13: BATFG202603-0016 | C13: FG | D13: 190.03 | E13: TNK_EUR_ANT_TB02 | F13: 46112 | G13: 26 | H13: 404456.05
A14: INVV202603-0011 | B14: BATFG202603-0017 | C14: FG | D14: 189.21 | E14: TNK_EUR_ANT_TB03 | F14: 46112 | G14: 47 | H14: 404328.53
A15: INVV202603-0012 | B15: BATFG202603-0018 | C15: FG | D15: 199.76 | E15: TNK_EUR_ANT_TB04 | F15: 46112 | G15: 29 | H15: 231883.41
... A93: INVV202603-0090 | B93: BATRW202603-0037 | C93: RM | D93: 233.58 | E93: WH_IN_WEST_BHI_BZ-B-04 | F93: 46112 | G93: 27 | H93: 299204.3

Sheet LSP Master List
A1: lsp_id (Primary Key) | B1: lsp_name | C1: provider_type | D1: primary_mode | E1: service_type | F1: service_regions | G1: dg_capable | H1: iso_tank_capable | I1: customs_clearance_capable | J1: incoterms_supported | K1: base_node_id (FK) | L1: preferred_plants | M1: coverage_nodes | N1: primary_sla_profile_id (FK) | O1: otif_target_pct | P1: transit_time_days (min) | Q1: transit_time_days (max) | R1: rate_card_type | S1: contract_status | T1: esg_rating | U1: insurance_coverage | V1: contact_email | W1: contact_phone | X1: created_date | Y1: active
A2: LSP001 | B2: BlueWave Logistics Pvt Ltd | C2: Carrier | D2: Road | E2: Ocean Freight | F2: DOM | G2: No | H2: Yes | I2: No | J2: EXW,FCA | K2: CFS_IN_NHAV | L2: PLT_MHD | M2: TNK_EUR_RTM,TNK_EUR_ANT,TNK_EUR_GEN,WH_EU_DEU_HAM | N2: SLA_STD_DOM_T2 | O2: 93 | P2: 15 | Q2: 30 | R2: Spot + Surcharge | S2: Active | T2: C | U2: INR 5 Cr Liability | V2: ops.lsp001@example.com | W2: +91-22-7001234 | X2: 2024-01-01 | Y2: TRUE
A3: LSP002 | B3: Apex HazMat Carriers Ltd | C3: Carrier | D3: Sea | E3: Container Freight (FCL/LCL) | F3: DOM,EU | G3: No | H3: Yes | I3: No | J3: EXW,FCA,FOB | K3: WH_IN_WEST_BHI | L3: PLT_LTE | M3: TNK_EUR_ANT,TNK_EUR_GEN,WH_EU_DEU_HAM,CFS_IN_NHAV,WH_IN_WEST_BHI | N3: SLA_STD_DOM_T2 | O3: 92 | P3: 18 | Q3: 28 | R3: Annual Rate Card | S3: Active | T3: C | U3: USD 5M Liability | V3: ops.lsp002@example.com | W3: +91-22-7002468 | X3: 2025-06-08 | Y3: TRUE
A4: LSP003 | B4: Navbharat Transport Services LLP | C4: Carrier | D4: Air | E4: DG (HazMat) Logistics | F4: DOM,AMER | G4: Yes | H4: No | I4: No | J4: FCA,FOB,CFR,CIF | K4: TNK_EUR_RTM | L4: PLT_MHD,PLT_DHJ | M4: TNK_EUR_GEN,WH_EU_DEU_HAM,CFS_IN_NHAV,WH_IN_WEST_BHI,WH_IN_GUJ_AHD,WH_IN_SOUTH_HYD | N4: SLA_STD_DOM_T2 | O4: 93 | P4: 2 | Q4: 6 | R4: Contract Tariff | S4: Active | T4: B | U4: USD 5M Liability | V4: ops.lsp003@example.com | W4: +91-22-7003702 | X4: 2026-11-15 | Y4: TRUE
A5: LSP004 | B5: Konkan Coastal Shipping Pvt Ltd | C5: Carrier | D5: Rail | E5: Customs Clearance | F5: DOM,APAC | G5: No | H5: Yes | I5: No | J5: FOB,CFR,CIF | K5: TNK_EUR_ANT | L5: PLT_MHD,PLT_LTE | M5: WH_EU_DEU_HAM,CFS_IN_NHAV,WH_IN_WEST_BHI | N5: SLA_STD_DOM_T2 | O5: 94 | P5: 3 | Q5: 9 | R5: Spot + Surcharge | S5: Active | T5: C | U5: INR 5 Cr Liability | V5: ops.lsp004@example.com | W5: +91-22-7004936 | X5: 2024-04-22 | Y5: TRUE
A6: LSP005 | B6: Western Freightlines India Ltd | C6: Customs Broker | D6: Multimodal | E6: Customs Clearance | F6: EU | G6: No | H6: No | I6: Yes | J6: EXW,FCA,DDP | K6: TNK_EUR_GEN | L6: PLT_MHD | M6: CFS_IN_NHAV,WH_IN_WEST_BHI,WH_IN_GUJ_AHD,WH_IN_SOUTH_HYD | N6: SLA_EXPORT_EU_T1 | O6: 95 | P6: 1 | Q6: 3 | R6: Annual Rate Card | S6: Active | T6: C | U6: USD 5M Liability | V6: ops.lsp005@example.com | W6: +91-22-7006170 | X6: 2025-09-01 | Y6: TRUE
A7: LSP006 | B7: Saffron Customs & Trade Services | C7: Carrier | D7: Road | E7: Last-mile Delivery | F7: AMER | G7: Yes | H7: No | I7: Yes | J7: FCA,FOB,DDP | K7: WH_UAE_SHJ | L7: PLT_LTE | M7: WH_IN_WEST_BHI,WH_IN_GUJ_AHD,WH_IN_SOUTH_HYD,WH_IN_NORTH_BAW,WH_IN_EAST_KOL | N7: SLA_EXPORT_US_T1_D | O7: 90 | P7: 1 | Q7: 3 | R7: Contract Tariff | S7: Active | T7: B | U7: USD 5M Liability | V7: ops.lsp006@example.com | W7: +91-22-7007404 | X7: 2026-02-08 | Y7: TRUE
A8: LSP007 | B8: OceanLink Forwarders Pvt Ltd | C8: CFS Operator | D8: Multimodal | E8: Air Freight | F8: MEA | G8: No | H8: No | I8: Yes | J8: EXW,FCA | K8: WH_US_EAST_NJ | L8: PLT_MHD,PLT_DHJ | M8: WH_IN_GUJ_AHD,WH_IN_SOUTH_HYD,WH_IN_NORTH_BAW,WH_IN_EAST_KOL,WH_US_EAST_NJ,WH_US_MID_CHI | N8: SLA_EXPORT_ROW_T2_P | O8: 91 | P8: 1 | Q8: 3 | R8: Spot + Surcharge | S8: Active | T8: A | U8: INR 5 Cr Liability | V8: ops.lsp007@example.com | W8: +91-22-7008638 | X8: 2024-07-15 | Y8: TRUE
A9: LSP008 | B9: Gateway CFS Operations Pvt Ltd | C9: Carrier | D9: Air | E9: Ocean Freight | F9: APAC | G9: No | H9: Yes | I9: No | J9: EXW,FCA,FOB | K9: CFS_IN_NHAV | L9: PLT_MHD,PLT_LTE | M9: WH_IN_SOUTH_HYD,WH_IN_NORTH_BAW,WH_IN_EAST_KOL | N9: SLA_EXPORT_ROW_T2_D | O9: 92 | P9: 10 | Q9: 18 | R9: Annual Rate Card | S9: Active | T9: C | U9: INR 5 Cr Liability | V9: ops.lsp008@example.com | W9: +91-22-7009872 | X9: 2025-12-22 | Y9: TRUE
A10: LSP009 | B10: EuroTank Terminal Services NV | C10: Tank Terminal Operator | D10: Sea | E10: Warehousing & Distribution | F10: EU,AMER | G10: Yes | H10: Yes | I10: No | J10: FCA,FOB,CFR,CIF | K10: WH_IN_WEST_BHI | L10: PLT_MHD | M10: WH_IN_NORTH_BAW,WH_IN_EAST_KOL,WH_US_EAST_NJ,WH_US_MID_CHI | N10: SLA_EXPORT_EU_T1 | O10: 93 | P10: 18 | Q10: 28 | R10: Contract Tariff | S10: Active | T10: B | U10: USD 5M Liability | V10: ops.lsp009@example.com | W10: +91-22-7011106 | X10: 2026-05-01 | Y10: TRUE
A11: LSP010 | B11: RheinPort Tank Logistics GmbH | C11: Customs Broker | D11: Multimodal | E11: Customs Clearance | F11: EU,MEA,ROW | G11: No | H11: No | I11: Yes | J11: FOB,CFR,CIF | K11: TNK_EUR_RTM | L11: PLT_LTE | M11: WH_IN_EAST_KOL,WH_US_EAST_NJ,WH_US_MID_CHI,WH_UAE_SHJ,WH_CHN_SHA | N11: SLA_EXPORT_EU_T1 | O11: 94 | P11: 1 | Q11: 3 | R11: Spot + Surcharge | S11: Planned | T11: C | U11: USD 5M Liability | V11: ops.lsp010@example.com | W11: +91-22-7012340 | X11: 2024-10-08 | Y11: TRUE
A12: LSP011 | B12: Antwerp Chemical Logistics NV | C12: Carrier | D12: Road | E12: Customs Clearance | F12: AMER,APAC | G12: No | H12: No | I12: No | J12: EXW,FCA,DDP | K12: TNK_EUR_ANT | L12: PLT_MHD,PLT_DHJ | M12: WH_US_EAST_NJ,WH_US_MID_CHI,WH_UAE_SHJ,WH_CHN_SHA,TNK_EUR_RTM,TNK_EUR_ANT | N12: SLA_EXPORT_US_T1_P | O12: 95 | P12: 1 | Q12: 3 | R12: Annual Rate Card | S12: Active | T12: C | U12: USD 5M Liability | V12: ops.lsp011@example.com | W12: +91-22-7013574 | X12: 2025-03-15 | Y12: TRUE
A13: LSP012 | B13: Liguria Tank Storage S.p.A. | C13: Carrier | D13: Sea | E13: Warehousing & Distribution | F13: DOM,EU,AMER,APAC,MEA | G13: Yes | H13: Yes | I13: Yes | J13: FCA,FOB,DDP | K13: TNK_EUR_GEN | L13: PLT_MHD,PLT_LTE | M13: WH_US_MID_CHI,WH_UAE_SHJ,WH_CHN_SHA | N13: SLA_EXPORT_ROW_T2_D | O13: 90 | P13: 18 | Q13: 28 | R13: Contract Tariff | S13: Active | T13: B | U13: USD 5M Liability | V13: ops.lsp012@example.com | W13: +91-22-7014808 | X13: 2026-08-22 | Y13: TRUE
... A41: LSP040 | B41: Astra Global Supply Chain LLP | C41: Customs Broker | D41: Multimodal | E41: Customs Clearance | F41: DOM,APAC | G41: No | H41: Yes | I41: Yes | J41: FOB,CFR,CIF | K41: TNK_EUR_GEN | L41: PLT_MHD,PLT_LTE | M41: WH_US_MID_CHI,WH_UAE_SHJ,WH_CHN_SHA | N41: SLA_STD_DOM_T2 | O41: 94 | P41: 1 | Q41: 3 | R41: Spot + Surcharge | S41: Planned | T41: C | U41: INR 5 Cr Liability | V41: ops.lsp040@example.com | W41: +91-22-7049360 | X41: 2024-04-22 | Y41: TRUE

Sheet Shipments
A1: Avg no. of shipments per month | B1: 220
A2: St Deviation (%) | B2: 0.1
A3: Shipment ID (PK) | B3: Shipment Type | C3: Planned Start Date | D3: Planned End Date | E3: Shipment Status | F3: Actual Start Date | G3: Actual End Date | H3: From Location_Supplier | I3: From Storage Location (FK) | J3: From Plant Location (FK) | K3: To Location_Customer | L3: To Storage Location (FK) | M3: To Plant Location (FK) | N3: Mode | O3: Incoterms | P3: Constraints | Q3: International/Domestic | R3: Documents Required | S3: Freight Forwarder/Carrier ID (FK) | T3: Logistics PO No. | U3: Cost of Shipment (USD) | V3: Proof of Delivery_Doc | X3: Mode | Y3: Type | Z3: Rate per kg (USD) | AA3: Base Fee (USD)
A4: SHP202603-0001 | B4: Outbound | C4: 46093 | D4: 46097 | E4: In Progress | F4: 46094 | I4: WH_IN_NORTH_BAW | J4: MHD | K4: CUS0071 | N4: Rail | O4: EXW | P4: Temp-Control | Q4: Domestic | R4: Invoice;Ewaybill;COA | S4: LSP016 | T4: LPO202603-0001 | U4: {=ROUND(SUMIF(Movements!$B$5:$B$329,$A4,Movements!$F$5:$F$329)*INDEX($Z$4:$Z$13,MATCH($N4&$Q4,$X$4:$X$13&$Y$4:$Y$13,0))+INDEX($AA$4:$AA$13,MATCH($N4&$Q4,$X$4:$X$13&$Y$4:$Y$13,0)),2)} -> 49.72 | X4: Road | Y4: Domestic | Z4: 0.08 | AA4: 50
A5: SHP202603-0002 | B5: Outbound | C5: 46110 | D5: 46128 | E5: In Progress | F5: 46112 | I5: CFS_IN_NHAV | J5: MHD | K5: CUS0002 | L5: TNK_EUR_ANT | N5: Sea | O5: CFR | P5: Temp-Control,Customs | Q5: International | R5: Invoice;Packing List;COA;SDS;BL | S5: LSP030 | T5: LPO202603-0002 | U5: {=ROUND(SUMIF(Movements!$B$5:$B$329,$A5,Movements!$F$5:$F$329)*INDEX($Z$4:$Z$13,MATCH($N5&$Q5,$X$4:$X$13&$Y$4:$Y$13,0))+INDEX($AA$4:$AA$13,MATCH($N5&$Q5,$X$4:$X$13&$Y$4:$Y$13,0)),2)} -> 288 | X5: Road | Y5: International | Z5: 0.15 | AA5: 150
A6: SHP202603-0003 | B6: Inbound | C6: 46091 | D6: 46097 | E6: Delivered | F6: 46092 | G6: 46099 | H6: Supplier - Domestic | L6: WH_IN_GUJ_AHD | M6: MHD | N6: Road | O6: FCA | P6: DG | Q6: Domestic | R6: Invoice;Ewaybill;COA;IMDG Declaration;DG Packing Cert | S6: LSP032 | T6: LPO202603-0003 | U6: {=ROUND(SUMIF(Movements!$B$5:$B$329,$A6,Movements!$F$5:$F$329)*INDEX($Z$4:$Z$13,MATCH($N6&$Q6,$X$4:$X$13&$Y$4:$Y$13,0))+INDEX($AA$4:$AA$13,MATCH($N6&$Q6,$X$4:$X$13&$Y$4:$Y$13,0)),2)} -> 67.52 | X6: Rail | Y6: Domestic | Z6: 0.05 | AA6: 40
A7: SHP202603-0004 | B7: Outbound | C7: 46094 | D7: 46100 | E7: Delivered | F7: 46093 | G7: 46101 | I7: WH_IN_NORTH_BAW | J7: MHD | K7: CUS0071 | N7: Road | O7: FCA | P7: Temp-Control | Q7: Domestic | R7: Invoice;Ewaybill;COA | S7: LSP017 | T7: LPO202603-0004 | U7: {=ROUND(SUMIF(Movements!$B$5:$B$329,$A7,Movements!$F$5:$F$329)*INDEX($Z$4:$Z$13,MATCH($N7&$Q7,$X$4:$X$13&$Y$4:$Y$13,0))+INDEX($AA$4:$AA$13,MATCH($N7&$Q7,$X$4:$X$13&$Y$4:$Y$13,0)),2)} -> 55.08 | V7: https://pod.example.com/SHP202603-0004.pdf | X7: Rail | Y7: International | Z7: 0.1 | AA7: 120
A8: SHP202603-0005 | B8: Outbound | C8: 46105 | D8: 46110 | E8: In Progress | F8: 46104 | I8: CFS_IN_NHAV | J8: MHD | K8: CUS0091 | L8: WH_US_MID_CHI | N8: Air | O8: CIF | P8: Temp-Control,Customs | Q8: International | R8: Invoice;Packing List;COA;SDS;BL | S8: LSP033 | T8: LPO202603-0005 | U8: {=ROUND(SUMIF(Movements!$B$5:$B$329,$A8,Movements!$F$5:$F$329)*INDEX($Z$4:$Z$13,MATCH($N8&$Q8,$X$4:$X$13&$Y$4:$Y$13,0))+INDEX($AA$4:$AA$13,MATCH($N8&$Q8,$X$4:$X$13&$Y$4:$Y$13,0)),2)} -> 986.39 | X8: Sea | Y8: Domestic | Z8: 0.03 | AA8: 75
A9: SHP202603-0006 | B9: Inbound | C9: 46106 | D9: 46110 | E9: Planned | H9: Supplier - APAC | L9: WH_IN_WEST_BHI | M9: DST | N9: Air | O9: CFR | P9: DG | Q9: International | R9: Invoice;Packing List;COA;SDS;BL;IMDG Declaration;DG Packing Cert | S9: LSP036 | T9: LPO202603-0006 | U9: {=ROUND(SUMIF(Movements!$B$5:$B$329,$A9,Movements!$F$5:$F$329)*INDEX($Z$4:$Z$13,MATCH($N9&$Q9,$X$4:$X$13&$Y$4:$Y$13,0))+INDEX($AA$4:$AA$13,MATCH($N9&$Q9,$X$4:$X$13&$Y$4:$Y$13,0)),2)} -> 964.66 | X9: Sea | Y9: International | Z9: 0.12 | AA9: 250
A10: SHP202603-0007 | B10: Outbound | C10: 46095 | D10: 46107 | E10: In Progress | F10: 46096 | I10: CFS_IN_NHAV | J10: MHD | K10: CUS0078 | N10: Road | O10: FCA | P10: DG | Q10: Domestic | R10: Invoice;Ewaybill;COA;IMDG Declaration;DG Packing Cert | S10: LSP022 | T10: LPO202603-0007 | U10: {=ROUND(SUMIF(Movements!$B$5:$B$329,$A10,Movements!$F$5:$F$329)*INDEX($Z$4:$Z$13,MATCH($N10&$Q10,$X$4:$X$13&$Y$4:$Y$13,0))+INDEX($AA$4:$AA$13,MATCH($N10&$Q10,$X$4:$X$13&$Y$4:$Y$13,0)),2)} -> 54.78 | X10: Air | Y10: Domestic | Z10: 0.75 | AA10: 100
A11: SHP202603-0008 | B11: Transfer | C11: 46102 | D11: 46104 | E11: In Progress | F11: 46103 | I11: WH_IN_SOUTH_HYD | L11: WH_US_EAST_NJ | N11: Sea | O11: CIF | P11: Standard | Q11: International | R11: Invoice;Packing List;COA;SDS;BL | S11: LSP020 | T11: LPO202603-0008 | U11: {=ROUND(SUMIF(Movements!$B$5:$B$329,$A11,Movements!$F$5:$F$329)*INDEX($Z$4:$Z$13,MATCH($N11&$Q11,$X$4:$X$13&$Y$4:$Y$13,0))+INDEX($AA$4:$AA$13,MATCH($N11&$Q11,$X$4:$X$13&$Y$4:$Y$13,0)),2)} -> 258.89 | X11: Air | Y11: International | Z11: 4.5 | AA11: 350
A12: SHP202603-0009 | B12: Outbound | C12: 46085 | D12: 46101 | E12: Delivered | F12: 46084 | G12: 46102 | I12: CFS_IN_NHAV | J12: LTE | K12: CUS0007 | N12: Road | O12: FCA | P12: DG | Q12: Domestic | R12: Invoice;Ewaybill;COA;IMDG Declaration;DG Packing Cert | S12: LSP033 | T12: LPO202603-0009 | U12: {=ROUND(SUMIF(Movements!$B$5:$B$329,$A12,Movements!$F$5:$F$329)*INDEX($Z$4:$Z$13,MATCH($N12&$Q12,$X$4:$X$13&$Y$4:$Y$13,0))+INDEX($AA$4:$AA$13,MATCH($N12&$Q12,$X$4:$X$13&$Y$4:$Y$13,0)),2)} -> 60.58 | X12: Multimodal | Y12: Domestic | Z12: 0.1 | AA12: 80
A13: SHP202603-0010 | B13: Outbound | C13: 46099 | D13: 46106 | E13: Planned | I13: WH_IN_GUJ_AHD | J13: LTE | K13: CUS0025 | N13: Road | O13: FCA | P13: DG | Q13: Domestic | R13: Invoice;Ewaybill;COA;IMDG Declaration;DG Packing Cert | S13: LSP007 | T13: LPO202603-0010 | U13: {=ROUND(SUMIF(Movements!$B$5:$B$329,$A13,Movements!$F$5:$F$329)*INDEX($Z$4:$Z$13,MATCH($N13&$Q13,$X$4:$X$13&$Y$4:$Y$13,0))+INDEX($AA$4:$AA$13,MATCH($N13&$Q13,$X$4:$X$13&$Y$4:$Y$13,0)),2)} -> 65.11 | X13: Multimodal | Y13: International | Z13: 0.3 | AA13: 200
A14: SHP202603-0011 | B14: Outbound | C14: 46111 | D14: 46112 | E14: Planned | I14: CFS_IN_NHAV | J14: LTE | K14: CUS0079 | N14: Multimodal | O14: EXW | P14: Standard | Q14: Domestic | R14: Invoice;Ewaybill;COA | S14: LSP034 | T14: LPO202603-0011 | U14: {=ROUND(SUMIF(Movements!$B$5:$B$329,$A14,Movements!$F$5:$F$329)*INDEX($Z$4:$Z$13,MATCH($N14&$Q14,$X$4:$X$13&$Y$4:$Y$13,0))+INDEX($AA$4:$AA$13,MATCH($N14&$Q14,$X$4:$X$13&$Y$4:$Y$13,0)),2)} -> 99.44
A15: SHP202603-0012 | B15: Inbound | C15: 46098 | D15: 46105 | E15: In Progress | F15: 46100 | H15: Supplier - MEA | L15: WH_IN_SOUTH_HYD | M15: LTE | N15: Sea | O15: CFR | P15: DG | Q15: International | R15: Invoice;Packing List;COA;SDS;BL;IMDG Declaration;DG Packing Cert | S15: LSP023 | T15: LPO202603-0012 | U15: {=ROUND(SUMIF(Movements!$B$5:$B$329,$A15,Movements!$F$5:$F$329)*INDEX($Z$4:$Z$13,MATCH($N15&$Q15,$X$4:$X$13&$Y$4:$Y$13,0))+INDEX($AA$4:$AA$13,MATCH($N15&$Q15,$X$4:$X$13&$Y$4:$Y$13,0)),2)} -> 281.82
A16: SHP202603-0013 | B16: Outbound | C16: 46105 | D16: 46110 | E16: Planned | I16: WH_IN_SOUTH_HYD | J16: LTE | K16: CUS0009 | N16: Road | O16: EXW | P16: Standard | Q16: Domestic | R16: Invoice;Ewaybill;COA | S16: LSP002 | T16: LPO202603-0013 | U16: {=ROUND(SUMIF(Movements!$B$5:$B$329,$A16,Movements!$F$5:$F$329)*INDEX($Z$4:$Z$13,MATCH($N16&$Q16,$X$4:$X$13&$Y$4:$Y$13,0))+INDEX($AA$4:$AA$13,MATCH($N16&$Q16,$X$4:$X$13&$Y$4:$Y$13,0)),2)} -> 61.81
A17: SHP202603-0014 | B17: Outbound | C17: 46109 | D17: 46114 | E17: Planned | I17: WH_IN_WEST_BHI | J17: MHD | K17: CUS0085 | N17: Road | O17: EXW | P17: Standard | Q17: Domestic | R17: Invoice;Ewaybill;COA | S17: LSP006 | T17: LPO202603-0014 | U17: {=ROUND(SUMIF(Movements!$B$5:$B$329,$A17,Movements!$F$5:$F$329)*INDEX($Z$4:$Z$13,MATCH($N17&$Q17,$X$4:$X$13&$Y$4:$Y$13,0))+INDEX($AA$4:$AA$13,MATCH($N17&$Q17,$X$4:$X$13&$Y$4:$Y$13,0)),2)} -> 50
A18: SHP202603-0015 | B18: Transfer | C18: 46110 | D18: 46122 | E18: Planned | I18: WH_IN_NORTH_BAW | J18: LTE | L18: TNK_EUR_GEN | N18: Sea | O18: CFR | P18: Standard | Q18: International | R18: Invoice;Packing List;COA;SDS;BL | S18: LSP032 | T18: LPO202603-0015 | U18: {=ROUND(SUMIF(Movements!$B$5:$B$329,$A18,Movements!$F$5:$F$329)*INDEX($Z$4:$Z$13,MATCH($N18&$Q18,$X$4:$X$13&$Y$4:$Y$13,0))+INDEX($AA$4:$AA$13,MATCH($N18&$Q18,$X$4:$X$13&$Y$4:$Y$13,0)),2)} -> 265.55
A19: SHP202603-0016 | B19: Transfer | C19: 46109 | D19: 46120 | E19: In Progress | F19: 46109 | I19: WH_IN_SOUTH_HYD | L19: TNK_EUR_ANT | N19: Air | O19: FOB | P19: DG | Q19: International | R19: Invoice;Packing List;COA;SDS;BL;IMDG Declaration;DG Packing Cert | S19: LSP004 | T19: LPO202603-0016 | U19: {=ROUND(SUMIF(Movements!$B$5:$B$329,$A19,Movements!$F$5:$F$329)*INDEX($Z$4:$Z$13,MATCH($N19&$Q19,$X$4:$X$13&$Y$4:$Y$13,0))+INDEX($AA$4:$AA$13,MATCH($N19&$Q19,$X$4:$X$13&$Y$4:$Y$13,0)),2)} -> 644.3
A20: SHP202603-0017 | B20: Inbound | C20: 46092 | D20: 46093 | E20: Delivered | F20: 46091 | G20: 46093 | H20: Supplier - EU | L20: WH_IN_SOUTH_HYD | M20: LTE | N20: Sea | O20: CFR | P20: Standard | Q20: International | R20: Invoice;Packing List;COA;SDS;BL | S20: LSP009 | T20: LPO202603-0017 | U20: {=ROUND(SUMIF(Movements!$B$5:$B$329,$A20,Movements!$F$5:$F$329)*INDEX($Z$4:$Z$13,MATCH($N20&$Q20,$X$4:$X$13&$Y$4:$Y$13,0))+INDEX($AA$4:$AA$13,MATCH($N20&$Q20,$X$4:$X$13&$Y$4:$Y$13,0)),2)} -> 281.71
A21: SHP202603-0018 | B21: Outbound | C21: 46095 | D21: 46096 | E21: In Progress | F21: 46097 | I21: WH_IN_WEST_BHI | J21: MHD | K21: CUS0083 | N21: Rail | O21: FCA | P21: Standard | Q21: Domestic | R21: Invoice;Ewaybill;COA | S21: LSP030 | T21: LPO202603-0018 | U21: {=ROUND(SUMIF(Movements!$B$5:$B$329,$A21,Movements!$F$5:$F$329)*INDEX($Z$4:$Z$13,MATCH($N21&$Q21,$X$4:$X$13&$Y$4:$Y$13,0))+INDEX($AA$4:$AA$13,MATCH($N21&$Q21,$X$4:$X$13&$Y$4:$Y$13,0)),2)} -> 40
A22: SHP202603-0019 | B22: Outbound | C22: 46091 | D22: 46096 | E22: Delivered | F22: 46091 | G22: 46095 | I22: WH_IN_GUJ_AHD | J22: MHD | K22: CUS0021 | L22: TNK_EUR_ANT | N22: Sea | O22: FOB | P22: Temp-Control | Q22: International | R22: Invoice;Packing List;COA;SDS;BL | S22: LSP018 | T22: LPO202603-0019 | U22: {=ROUND(SUMIF(Movements!$B$5:$B$329,$A22,Movements!$F$5:$F$329)*INDEX($Z$4:$Z$13,MATCH($N22&$Q22,$X$4:$X$13&$Y$4:$Y$13,0))+INDEX($AA$4:$AA$13,MATCH($N22&$Q22,$X$4:$X$13&$Y$4:$Y$13,0)),2)} -> 266.64 | V22: https://pod.example.com/SHP202603-0019.pdf
A23: SHP202603-0020 | B23: Outbound | C23: 46091 | D23: 46094 | E23: Delivered | F23: 46093 | G23: 46095 | I23: CFS_IN_NHAV | J23: MHD | K23: CUS0067 | N23: Multimodal | O23: FCA | P23: Standard | Q23: Domestic | R23: Invoice;Ewaybill;COA | S23: LSP029 | T23: LPO202603-0020 | U23: {=ROUND(SUMIF(Movements!$B$5:$B$329,$A23,Movements!$F$5:$F$329)*INDEX($Z$4:$Z$13,MATCH($N23&$Q23,$X$4:$X$13&$Y$4:$Y$13,0))+INDEX($AA$4:$AA$13,MATCH($N23&$Q23,$X$4:$X$13&$Y$4:$Y$13,0)),2)} -> 80 | V23: https://pod.example.com/SHP202603-0020.pdf
A24: SHP202603-0021 | B24: Outbound | C24: 46101 | D24: 46106 | E24: In Progress | F24: 46101 | I24: CFS_IN_NHAV | J24: MHD | K24: CUS0025 | L24: WH_US_MID_CHI | N24: Sea | O24: FOB | P24: DG | Q24: International | R24: Invoice;Packing List;COA;SDS;BL;IMDG Declaration;DG Packing Cert | S24: LSP001 | T24: LPO202603-0021 | U24: {=ROUND(SUMIF(Movements!$B$5:$B$329,$A24,Movements!$F$5:$F$329)*INDEX($Z$4:$Z$13,MATCH($N24&$Q24,$X$4:$X$13&$Y$4:$Y$13,0))+INDEX($AA$4:$AA$13,MATCH($N24&$Q24,$X$4:$X$13&$Y$4:$Y$13,0)),2)} -> 250
A25: SHP202603-0022 | B25: Outbound | C25: 46098 | D25: 46112 | E25: In Progress | F25: 46098 | I25: CFS_IN_NHAV | J25: LTE | K25: CUS0029 | N25: Road | O25: FCA | P25: Standard | Q25: Domestic | R25: Invoice;Ewaybill;COA | S25: LSP036 | T25: LPO202603-0022 | U25: {=ROUND(SUMIF(Movements!$B$5:$B$329,$A25,Movements!$F$5:$F$329)*INDEX($Z$4:$Z$13,MATCH($N25&$Q25,$X$4:$X$13&$Y$4:$Y$13,0))+INDEX($AA$4:$AA$13,MATCH($N25&$Q25,$X$4:$X$13&$Y$4:$Y$13,0)),2)} -> 58.85
A26: SHP202603-0023 | B26: Outbound | C26: 46086 | D26: 46100 | E26: In Progress | F26: 46085 | I26: WH_IN_NORTH_BAW | J26: MHD | K26: CUS0096 | N26: Rail | O26: FCA | P26: Standard | Q26: Domestic | R26: Invoice;Ewaybill;COA | S26: LSP022 | T26: LPO202603-0023 | U26: {=ROUND(SUMIF(Movements!$B$5:$B$329,$A26,Movements!$F$5:$F$329)*INDEX($Z$4:$Z$13,MATCH($N26&$Q26,$X$4:$X$13&$Y$4:$Y$13,0))+INDEX($AA$4:$AA$13,MATCH($N26&$Q26,$X$4:$X$13&$Y$4:$Y$13,0)),2)} -> 40
A27: SHP202603-0024 | B27: Transfer | C27: 46084 | D27: 46096 | E27: In Progress | F27: 46084 | I27: WH_IN_GUJ_AHD | L27: WH_US_EAST_NJ | N27: Multimodal | O27: CIF | P27: Standard | Q27: International | R27: Invoice;Packing List;COA;SDS;BL | S27: LSP018 | T27: LPO202603-0024 | U27: {=ROUND(SUMIF(Movements!$B$5:$B$329,$A27,Movements!$F$5:$F$329)*INDEX($Z$4:$Z$13,MATCH($N27&$Q27,$X$4:$X$13&$Y$4:$Y$13,0))+INDEX($AA$4:$AA$13,MATCH($N27&$Q27,$X$4:$X$13&$Y$4:$Y$13,0)),2)} -> 220.65
A28: SHP202603-0025 | B28: Inbound | C28: 46107 | D28: 46113 | E28: In Progress | F28: 46109 | H28: Supplier - APAC | L28: WH_IN_GUJ_AHD | M28: MHD | N28: Sea | O28: CFR | P28: DG | Q28: International | R28: Invoice;Packing List;COA;SDS;BL;IMDG Declaration;DG Packing Cert | S28: LSP026 | T28: LPO202603-0025 | U28: {=ROUND(SUMIF(Movements!$B$5:$B$329,$A28,Movements!$F$5:$F$329)*INDEX($Z$4:$Z$13,MATCH($N28&$Q28,$X$4:$X$13&$Y$4:$Y$13,0))+INDEX($AA$4:$AA$13,MATCH($N28&$Q28,$X$4:$X$13&$Y$4:$Y$13,0)),2)} -> 264.03
A29: SHP202603-0026 | B29: Outbound | C29: 46092 | D29: 46110 | E29: Delivered | F29: 46091 | G29: 46112 | I29: CFS_IN_NHAV | J29: MHD | K29: CUS0017 | N29: Road | O29: FCA | P29: DG | Q29: Domestic | R29: Invoice;Ewaybill;COA;IMDG Declaration;DG Packing Cert | S29: LSP033 | T29: LPO202603-0026 | U29: {=ROUND(SUMIF(Movements!$B$5:$B$329,$A29,Movements!$F$5:$F$329)*INDEX($Z$4:$Z$13,MATCH($N29&$Q29,$X$4:$X$13&$Y$4:$Y$13,0))+INDEX($AA$4:$AA$13,MATCH($N29&$Q29,$X$4:$X$13&$Y$4:$Y$13,0)),2)} -> 59.95
A30: SHP202603-0027 | B30: Transfer | C30: 46111 | D30: 46121 | E30: Planned | I30: WH_IN_WEST_BHI | L30: WH_IN_SOUTH_HYD | N30: Road | O30: FCA | P30: Standard | Q30: Domestic | R30: Invoice;Ewaybill;COA | S30: LSP002 | T30: LPO202603-0027 | U30: {=ROUND(SUMIF(Movements!$B$5:$B$329,$A30,Movements!$F$5:$F$329)*INDEX($Z$4:$Z$13,MATCH($N30&$Q30,$X$4:$X$13&$Y$4:$Y$13,0))+INDEX($AA$4:$AA$13,MATCH($N30&$Q30,$X$4:$X$13&$Y$4:$Y$13,0)),2)} -> 55.12
A31: SHP202603-0028 | B31: Outbound | C31: 46104 | D31: 46108 | E31: Planned | I31: CFS_IN_NHAV | J31: MHD | K31: CUS0050 | N31: Road | O31: FCA | P31: DG | Q31: Domestic | R31: Invoice;Ewaybill;COA;IMDG Declaration;DG Packing Cert | S31: LSP002 | T31: LPO202603-0028 | U31: {=ROUND(SUMIF(Movements!$B$5:$B$329,$A31,Movements!$F$5:$F$329)*INDEX($Z$4:$Z$13,MATCH($N31&$Q31,$X$4:$X$13&$Y$4:$Y$13,0))+INDEX($AA$4:$AA$13,MATCH($N31&$Q31,$X$4:$X$13&$Y$4:$Y$13,0)),2)} -> 54.74
A32: SHP202603-0029 | B32: Outbound | C32: 46111 | D32: 46121 | E32: In Progress | F32: 46111 | I32: WH_IN_GUJ_AHD | J32: MHD | K32: CUS0026 | N32: Road | O32: FCA | P32: Standard | Q32: Domestic | R32: Invoice;Ewaybill;COA | S32: LSP005 | T32: LPO202603-0029 | U32: {=ROUND(SUMIF(Movements!$B$5:$B$329,$A32,Movements!$F$5:$F$329)*INDEX($Z$4:$Z$13,MATCH($N32&$Q32,$X$4:$X$13&$Y$4:$Y$13,0))+INDEX($AA$4:$AA$13,MATCH($N32&$Q32,$X$4:$X$13&$Y$4:$Y$13,0)),2)} -> 71.16
A33: SHP202603-0030 | B33: Outbound | C33: 46107 | D33: 46116 | E33: Planned | I33: CFS_IN_NHAV | J33: LTE | K33: CUS0025 | N33: Road | O33: FCA | P33: Standard | Q33: Domestic | R33: Invoice;Ewaybill;COA | S33: LSP021 | T33: LPO202603-0030 | U33: {=ROUND(SUMIF(Movements!$B$5:$B$329,$A33,Movements!$F$5:$F$329)*INDEX($Z$4:$Z$13,MATCH($N33&$Q33,$X$4:$X$13&$Y$4:$Y$13,0))+INDEX($AA$4:$AA$13,MATCH($N33&$Q33,$X$4:$X$13&$Y$4:$Y$13,0)),2)} -> 55.19
A34: SHP202603-0031 | B34: Inbound | C34: 46107 | D34: 46115 | E34: Planned | H34: Supplier - Domestic | L34: WH_IN_GUJ_AHD | M34: MHD | N34: Rail | O34: FCA | P34: Standard | Q34: Domestic | R34: Invoice;Ewaybill;COA | S34: LSP017 | T34: LPO202603-0031 | U34: {=ROUND(SUMIF(Movements!$B$5:$B$329,$A34,Movements!$F$5:$F$329)*INDEX($Z$4:$Z$13,MATCH($N34&$Q34,$X$4:$X$13&$Y$4:$Y$13,0))+INDEX($AA$4:$AA$13,MATCH($N34&$Q34,$X$4:$X$13&$Y$4:$Y$13,0)),2)} -> 43.1
A35: SHP202603-0032 | B35: Outbound | C35: 46084 | D35: 46085 | E35: Delivered | F35: 46085 | G35: 46084 | I35: CFS_IN_NHAV | J35: LTE | K35: CUS0041 | N35: Road | O35: FCA | P35: DG | Q35: Domestic | R35: Invoice;Ewaybill;COA;IMDG Declaration;DG Packing Cert | S35: LSP003 | T35: LPO202603-0032 | U35: {=ROUND(SUMIF(Movements!$B$5:$B$329,$A35,Movements!$F$5:$F$329)*INDEX($Z$4:$Z$13,MATCH($N35&$Q35,$X$4:$X$13&$Y$4:$Y$13,0))+INDEX($AA$4:$AA$13,MATCH($N35&$Q35,$X$4:$X$13&$Y$4:$Y$13,0)),2)} -> 67.8
A36: SHP202603-0033 | B36: Inbound | C36: 46093 | D36: 46101 | E36: In Progress | F36: 46093 | H36: Supplier - Domestic | L36: WH_IN_WEST_BHI | M36: MHD | N36: Road | O36: FCA | P36: Standard | Q36: Domestic | R36: Invoice;Ewaybill;COA | S36: LSP034 | T36: LPO202603-0033 | U36: {=ROUND(SUMIF(Movements!$B$5:$B$329,$A36,Movements!$F$5:$F$329)*INDEX($Z$4:$Z$13,MATCH($N36&$Q36,$X$4:$X$13&$Y$4:$Y$13,0))+INDEX($AA$4:$AA$13,MATCH($N36&$Q36,$X$4:$X$13&$Y$4:$Y$13,0)),2)} -> 65.17
A37: SHP202603-0034 | B37: Outbound | C37: 46111 | D37: 46125 | E37: In Progress | F37: 46110 | I37: CFS_IN_NHAV | J37: MHD | K37: CUS0018 | N37: Road | O37: FCA | P37: Standard | Q37: Domestic | R37: Invoice;Ewaybill;COA | S37: LSP025 | T37: LPO202603-0034 | U37: {=ROUND(SUMIF(Movements!$B$5:$B$329,$A37,Movements!$F$5:$F$329)*INDEX($Z$4:$Z$13,MATCH($N37&$Q37,$X$4:$X$13&$Y$4:$Y$13,0))+INDEX($AA$4:$AA$13,MATCH($N37&$Q37,$X$4:$X$13&$Y$4:$Y$13,0)),2)} -> 77.52
A38: SHP202603-0035 | B38: Outbound | C38: 46107 | D38: 46125 | E38: Planned | I38: CFS_IN_NHAV | J38: LTE | K38: CUS0079 | N38: Road | O38: EXW | P38: Standard | Q38: Domestic | R38: Invoice;Ewaybill;COA | S38: LSP006 | T38: LPO202603-0035 | U38: {=ROUND(SUMIF(Movements!$B$5:$B$329,$A38,Movements!$F$5:$F$329)*INDEX($Z$4:$Z$13,MATCH($N38&$Q38,$X$4:$X$13&$Y$4:$Y$13,0))+INDEX($AA$4:$AA$13,MATCH($N38&$Q38,$X$4:$X$13&$Y$4:$Y$13,0)),2)} -> 61.19
A39: SHP202603-0036 | B39: Inbound | C39: 46106 | D39: 46108 | E39: Planned | H39: Supplier - Domestic | L39: WH_IN_GUJ_AHD | M39: DST | N39: Road | O39: FCA | P39: Standard | Q39: Domestic | R39: Invoice;Ewaybill;COA | S39: LSP010 | T39: LPO202603-0036 | U39: {=ROUND(SUMIF(Movements!$B$5:$B$329,$A39,Movements!$F$5:$F$329)*INDEX($Z$4:$Z$13,MATCH($N39&$Q39,$X$4:$X$13&$Y$4:$Y$13,0))+INDEX($AA$4:$AA$13,MATCH($N39&$Q39,$X$4:$X$13&$Y$4:$Y$13,0)),2)} -> 70.89
A40: SHP202603-0037 | B40: Outbound | C40: 46111 | D40: 46118 | E40: Planned | I40: CFS_IN_NHAV | J40: MHD | K40: CUS0010 | N40: Rail | O40: EXW | P40: Standard | Q40: Domestic | R40: Invoice;Ewaybill;COA | S40: LSP033 | T40: LPO202603-0037 | U40: {=ROUND(SUMIF(Movements!$B$5:$B$329,$A40,Movements!$F$5:$F$329)*INDEX($Z$4:$Z$13,MATCH($N40&$Q40,$X$4:$X$13&$Y$4:$Y$13,0))+INDEX($AA$4:$AA$13,MATCH($N40&$Q40,$X$4:$X$13&$Y$4:$Y$13,0)),2)} -> 50.23
A41: SHP202603-0038 | B41: Outbound | C41: 46097 | D41: 46101 | E41: Planned | I41: WH_IN_NORTH_BAW | J41: LTE | K41: CUS0058 | N41: Road | O41: FCA | P41: DG | Q41: Domestic | R41: Invoice;Ewaybill;COA;IMDG Declaration;DG Packing Cert | S41: LSP006 | T41: LPO202603-0038 | U41: {=ROUND(SUMIF(Movements!$B$5:$B$329,$A41,Movements!$F$5:$F$329)*INDEX($Z$4:$Z$13,MATCH($N41&$Q41,$X$4:$X$13&$Y$4:$Y$13,0))+INDEX($AA$4:$AA$13,MATCH($N41&$Q41,$X$4:$X$13&$Y$4:$Y$13,0)),2)} -> 55.88
A42: SHP202603-0039 | B42: Outbound | C42: 46107 | D42: 46114 | E42: In Progress | F42: 46107 | I42: CFS_IN_NHAV | J42: LTE | K42: CUS0011 | L42: WH_UAE_SHJ | N42: Sea | O42: CFR | P42: Standard | Q42: International | R42: Invoice;Packing List;COA;SDS;BL | S42: LSP001 | T42: LPO202603-0039 | U42: {=ROUND(SUMIF(Movements!$B$5:$B$329,$A42,Movements!$F$5:$F$329)*INDEX($Z$4:$Z$13,MATCH($N42&$Q42,$X$4:$X$13&$Y$4:$Y$13,0))+INDEX($AA$4:$AA$13,MATCH($N42&$Q42,$X$4:$X$13&$Y$4:$Y$13,0)),2)} -> 258.89
A43: SHP202603-0040 | B43: Outbound | C43: 46089 | D43: 46103 | E43: Delivered | F43: 46089 | G43: 46104 | I43: WH_IN_NORTH_BAW | J43: LTE | K43: CUS0015 | N43: Road | O43: FCA | P43: Temp-Control | Q43: Domestic | R43: Invoice;Ewaybill;COA | S43: LSP027 | T43: LPO202603-0040 | U43: {=ROUND(SUMIF(Movements!$B$5:$B$329,$A43,Movements!$F$5:$F$329)*INDEX($Z$4:$Z$13,MATCH($N43&$Q43,$X$4:$X$13&$Y$4:$Y$13,0))+INDEX($AA$4:$AA$13,MATCH($N43&$Q43,$X$4:$X$13&$Y$4:$Y$13,0)),2)} -> 55.63
A44: SHP202603-0041 | B44: Outbound | C44: 46112 | D44: 46115 | E44: In Progress | F44: 46114 | I44: WH_IN_WEST_BHI | J44: MHD | K44: CUS0076 | N44: Road | O44: EXW | P44: Standard | Q44: Domestic | R44: Invoice;Ewaybill;COA | S44: LSP018 | T44: LPO202603-0041 | U44: {=ROUND(SUMIF(Movements!$B$5:$B$329,$A44,Movements!$F$5:$F$329)*INDEX($Z$4:$Z$13,MATCH($N44&$Q44,$X$4:$X$13&$Y$4:$Y$13,0))+INDEX($AA$4:$AA$13,MATCH($N44&$Q44,$X$4:$X$13&$Y$4:$Y$13,0)),2)} -> 55.02
A45: SHP202603-0042 | B45: Inbound | C45: 46108 | D45: 46110 | E45: Planned | H45: Supplier - EU | L45: WH_IN_WEST_BHI | M45: LTE | N45: Air | O45: CFR | P45: DG,Temp-Control | Q45: International | R45: Invoice;Packing List;COA;SDS;BL;IMDG Declaration;DG Packing Cert | S45: LSP022 | T45: LPO202603-0042 | U45: {=ROUND(SUMIF(Movements!$B$5:$B$329,$A45,Movements!$F$5:$F$329)*INDEX($Z$4:$Z$13,MATCH($N45&$Q45,$X$4:$X$13&$Y$4:$Y$13,0))+INDEX($AA$4:$AA$13,MATCH($N45&$Q45,$X$4:$X$13&$Y$4:$Y$13,0)),2)} -> 685.21
A46: SHP202603-0043 | B46: Outbound | C46: 46112 | D46: 46116 | E46: In Progress | F46: 46111 | I46: WH_IN_WEST_BHI | J46: MHD | K46: CUS0092 | L46: TNK_EUR_ANT | N46: Air | O46: FOB | P46: Standard | Q46: International | R46: Invoice;Packing List;COA;SDS;BL | S46: LSP009 | T46: LPO202603-0043 | U46: {=ROUND(SUMIF(Movements!$B$5:$B$329,$A46,Movements!$F$5:$F$329)*INDEX($Z$4:$Z$13,MATCH($N46&$Q46,$X$4:$X$13&$Y$4:$Y$13,0))+INDEX($AA$4:$AA$13,MATCH($N46&$Q46,$X$4:$X$13&$Y$4:$Y$13,0)),2)} -> 350
A47: SHP202603-0044 | B47: Inbound | C47: 46108 | D47: 46111 | E47: In Progress | F47: 46108 | H47: Supplier - Domestic | L47: WH_IN_NORTH_BAW | M47: DST | N47: Road | O47: FCA | P47: Standard | Q47: Domestic | R47: Invoice;Ewaybill;COA | S47: LSP005 | T47: LPO202603-0044 | U47: {=ROUND(SUMIF(Movements!$B$5:$B$329,$A47,Movements!$F$5:$F$329)*INDEX($Z$4:$Z$13,MATCH($N47&$Q47,$X$4:$X$13&$Y$4:$Y$13,0))+INDEX($AA$4:$AA$13,MATCH($N47&$Q47,$X$4:$X$13&$Y$4:$Y$13,0)),2)} -> 55.16
A48: SHP202603-0045 | B48: Inbound | C48: 46088 | D48: 46091 | E48: Delivered | F48: 46090 | G48: 46093 | H48: Supplier - Domestic | L48: WH_IN_WEST_BHI | M48: MHD | N48: Road | O48: FCA | P48: Standard | Q48: Domestic | R48: Invoice;Ewaybill;COA | S48: LSP033 | T48: LPO202603-0045 | U48: {=ROUND(SUMIF(Movements!$B$5:$B$329,$A48,Movements!$F$5:$F$329)*INDEX($Z$4:$Z$13,MATCH($N48&$Q48,$X$4:$X$13&$Y$4:$Y$13,0))+INDEX($AA$4:$AA$13,MATCH($N48&$Q48,$X$4:$X$13&$Y$4:$Y$13,0)),2)} -> 60.62 | V48: https://pod.example.com/SHP202603-0045.pdf
A49: SHP202603-0046 | B49: Outbound | C49: 46092 | D49: 46110 | E49: Delivered | F49: 46091 | G49: 46108 | I49: WH_IN_WEST_BHI | J49: LTE | K49: CUS0080 | L49: TNK_EUR_GEN | N49: Sea | O49: CIF | P49: DG | Q49: International | R49: Invoice;Packing List;COA;SDS;BL;IMDG Declaration;DG Packing Cert | S49: LSP034 | T49: LPO202603-0046 | U49: {=ROUND(SUMIF(Movements!$B$5:$B$329,$A49,Movements!$F$5:$F$329)*INDEX($Z$4:$Z$13,MATCH($N49&$Q49,$X$4:$X$13&$Y$4:$Y$13,0))+INDEX($AA$4:$AA$13,MATCH($N49&$Q49,$X$4:$X$13&$Y$4:$Y$13,0)),2)} -> 273.78
A50: SHP202603-0047 | B50: Inbound | C50: 46108 | D50: 46114 | E50: Planned | H50: Supplier - Domestic | L50: WH_IN_WEST_BHI | M50: LTE | N50: Road | O50: FCA | P50: Standard | Q50: Domestic | R50: Invoice;Ewaybill;COA | S50: LSP025 | T50: LPO202603-0047 | U50: {=ROUND(SUMIF(Movements!$B$5:$B$329,$A50,Movements!$F$5:$F$329)*INDEX($Z$4:$Z$13,MATCH($N50&$Q50,$X$4:$X$13&$Y$4:$Y$13,0))+INDEX($AA$4:$AA$13,MATCH($N50&$Q50,$X$4:$X$13&$Y$4:$Y$13,0)),2)} -> 60.29
A51: SHP202603-0048 | B51: Inbound | C51: 46097 | D51: 46099 | E51: In Progress | F51: 46097 | H51: Supplier - Domestic | L51: CFS_IN_NHAV | M51: LTE | N51: Road | O51: FCA | P51: Standard | Q51: Domestic | R51: Invoice;Ewaybill;COA | S51: LSP027 | T51: LPO202603-0048 | U51: {=ROUND(SUMIF(Movements!$B$5:$B$329,$A51,Movements!$F$5:$F$329)*INDEX($Z$4:$Z$13,MATCH($N51&$Q51,$X$4:$X$13&$Y$4:$Y$13,0))+INDEX($AA$4:$AA$13,MATCH($N51&$Q51,$X$4:$X$13&$Y$4:$Y$13,0)),2)} -> 50
A52: SHP202603-0049 | B52: Outbound | C52: 46083 | D52: 46090 | E52: Delivered | F52: 46085 | G52: 46089 | I52: CFS_IN_NHAV | J52: LTE | K52: CUS0054 | N52: Rail | O52: FCA | P52: Standard | Q52: Domestic | R52: Invoice;Ewaybill;COA | S52: LSP002 | T52: LPO202603-0049 | U52: {=ROUND(SUMIF(Movements!$B$5:$B$329,$A52,Movements!$F$5:$F$329)*INDEX($Z$4:$Z$13,MATCH($N52&$Q52,$X$4:$X$13&$Y$4:$Y$13,0))+INDEX($AA$4:$AA$13,MATCH($N52&$Q52,$X$4:$X$13&$Y$4:$Y$13,0)),2)} -> 40 | V52: https://pod.example.com/SHP202603-0049.pdf
A53: SHP202603-0050 | B53: Outbound | C53: 46085 | D53: 46096 | E53: In Progress | F53: 46087 | I53: CFS_IN_NHAV | J53: MHD | K53: CUS0024 | N53: Rail | O53: FCA | P53: Standard | Q53: Domestic | R53: Invoice;Ewaybill;COA | S53: LSP025 | T53: LPO202603-0050 | U53: {=ROUND(SUMIF(Movements!$B$5:$B$329,$A53,Movements!$F$5:$F$329)*INDEX($Z$4:$Z$13,MATCH($N53&$Q53,$X$4:$X$13&$Y$4:$Y$13,0))+INDEX($AA$4:$AA$13,MATCH($N53&$Q53,$X$4:$X$13&$Y$4:$Y$13,0)),2)} -> 46.76
A54: SHP202603-0051 | B54: Inbound | C54: 46102 | D54: 46104 | E54: In Progress | F54: 46101 | H54: Supplier - Domestic | L54: WH_IN_NORTH_BAW | M54: DST | N54: Road | O54: FCA | P54: Standard | Q54: Domestic | R54: Invoice;Ewaybill;COA | S54: LSP022 | T54: LPO202603-0051 | U54: {=ROUND(SUMIF(Movements!$B$5:$B$329,$A54,Movements!$F$5:$F$329)*INDEX($Z$4:$Z$13,MATCH($N54&$Q54,$X$4:$X$13&$Y$4:$Y$13,0))+INDEX($AA$4:$AA$13,MATCH($N54&$Q54,$X$4:$X$13&$Y$4:$Y$13,0)),2)} -> 70.75
A55: SHP202603-0052 | B55: Outbound | C55: 46092 | D55: 46093 | E55: Planned | I55: WH_IN_WEST_BHI | J55: LTE | K55: CUS0011 | N55: Rail | O55: FCA | P55: Standard | Q55: Domestic | R55: Invoice;Ewaybill;COA | S55: LSP018 | T55: LPO202603-0052 | U55: {=ROUND(SUMIF(Movements!$B$5:$B$329,$A55,Movements!$F$5:$F$329)*INDEX($Z$4:$Z$13,MATCH($N55&$Q55,$X$4:$X$13&$Y$4:$Y$13,0))+INDEX($AA$4:$AA$13,MATCH($N55&$Q55,$X$4:$X$13&$Y$4:$Y$13,0)),2)} -> 43.55
A56: SHP202603-0053 | B56: Outbound | C56: 46100 | D56: 46107 | E56: In Progress | F56: 46100 | I56: WH_IN_WEST_BHI | J56: LTE | K56: CUS0064 | N56: Road | O56: FCA | P56: DG | Q56: Domestic | R56: Invoice;Ewaybill;COA;IMDG Declaration;DG Packing Cert | S56: LSP031 | T56: LPO202603-0053 | U56: {=ROUND(SUMIF(Movements!$B$5:$B$329,$A56,Movements!$F$5:$F$329)*INDEX($Z$4:$Z$13,MATCH($N56&$Q56,$X$4:$X$13&$Y$4:$Y$13,0))+INDEX($AA$4:$AA$13,MATCH($N56&$Q56,$X$4:$X$13&$Y$4:$Y$13,0)),2)} -> 54.75
A57: SHP202603-0054 | B57: Outbound | C57: 46103 | D57: 46109 | E57: In Progress | F57: 46105 | I57: CFS_IN_NHAV | J57: LTE | K57: CUS0067 | L57: WH_US_EAST_NJ | N57: Sea | O57: CFR | P57: Standard | Q57: International | R57: Invoice;Packing List;COA;SDS;BL | S57: LSP011 | T57: LPO202603-0054 | U57: {=ROUND(SUMIF(Movements!$B$5:$B$329,$A57,Movements!$F$5:$F$329)*INDEX($Z$4:$Z$13,MATCH($N57&$Q57,$X$4:$X$13&$Y$4:$Y$13,0))+INDEX($AA$4:$AA$13,MATCH($N57&$Q57,$X$4:$X$13&$Y$4:$Y$13,0)),2)} -> 266.36
A58: SHP202603-0055 | B58: Outbound | C58: 46095 | D58: 46108 | E58: Delivered | F58: 46094 | G58: 46107 | I58: WH_IN_SOUTH_HYD | J58: MHD | K58: CUS0070 | N58: Multimodal | O58: EXW | P58: Standard | Q58: Domestic | R58: Invoice;Ewaybill;COA | S58: LSP008 | T58: LPO202603-0055 | U58: {=ROUND(SUMIF(Movements!$B$5:$B$329,$A58,Movements!$F$5:$F$329)*INDEX($Z$4:$Z$13,MATCH($N58&$Q58,$X$4:$X$13&$Y$4:$Y$13,0))+INDEX($AA$4:$AA$13,MATCH($N58&$Q58,$X$4:$X$13&$Y$4:$Y$13,0)),2)} -> 86.56 | V58: https://pod.example.com/SHP202603-0055.pdf
A59: SHP202603-0056 | B59: Outbound | C59: 46101 | D59: 46102 | E59: Planned | I59: WH_IN_WEST_BHI | J59: MHD | K59: CUS0005 | L59: TNK_EUR_GEN | N59: Air | O59: CIF | P59: DG,Customs | Q59: International | R59: Invoice;Packing List;COA;SDS;BL;IMDG Declaration;DG Packing Cert | S59: LSP014 | T59: LPO202603-0056 | U59: {=ROUND(SUMIF(Movements!$B$5:$B$329,$A59,Movements!$F$5:$F$329)*INDEX($Z$4:$Z$13,MATCH($N59&$Q59,$X$4:$X$13&$Y$4:$Y$13,0))+INDEX($AA$4:$AA$13,MATCH($N59&$Q59,$X$4:$X$13&$Y$4:$Y$13,0)),2)} -> 1505.29
A60: SHP202603-0057 | B60: Outbound | C60: 46083 | D60: 46101 | E60: In Progress | F60: 46083 | I60: WH_IN_NORTH_BAW | J60: LTE | K60: CUS0075 | N60: Road | O60: FCA | P60: Standard | Q60: Domestic | R60: Invoice;Ewaybill;COA | S60: LSP011 | T60: LPO202603-0057 | U60: {=ROUND(SUMIF(Movements!$B$5:$B$329,$A60,Movements!$F$5:$F$329)*INDEX($Z$4:$Z$13,MATCH($N60&$Q60,$X$4:$X$13&$Y$4:$Y$13,0))+INDEX($AA$4:$AA$13,MATCH($N60&$Q60,$X$4:$X$13&$Y$4:$Y$13,0)),2)} -> 54.59
A61: SHP202603-0058 | B61: Outbound | C61: 46083 | D61: 46098 | E61: Delivered | F61: 46083 | G61: 46098 | I61: WH_IN_SOUTH_HYD | J61: LTE | K61: CUS0079 | L61: WH_US_MID_CHI | N61: Sea | O61: FOB | P61: Standard | Q61: International | R61: Invoice;Packing List;COA;SDS;BL | S61: LSP021 | T61: LPO202603-0058 | U61: {=ROUND(SUMIF(Movements!$B$5:$B$329,$A61,Movements!$F$5:$F$329)*INDEX($Z$4:$Z$13,MATCH($N61&$Q61,$X$4:$X$13&$Y$4:$Y$13,0))+INDEX($AA$4:$AA$13,MATCH($N61&$Q61,$X$4:$X$13&$Y$4:$Y$13,0)),2)} -> 259.74
A62: SHP202603-0059 | B62: Inbound | C62: 46092 | D62: 46100 | E62: Delivered | F62: 46091 | G62: 46102 | H62: Supplier - Domestic | L62: WH_IN_WEST_BHI | M62: LTE | N62: Road | O62: FCA | P62: DG | Q62: Domestic | R62: Invoice;Ewaybill;COA;IMDG Declaration;DG Packing Cert | S62: LSP033 | T62: LPO202603-0059 | U62: {=ROUND(SUMIF(Movements!$B$5:$B$329,$A62,Movements!$F$5:$F$329)*INDEX($Z$4:$Z$13,MATCH($N62&$Q62,$X$4:$X$13&$Y$4:$Y$13,0))+INDEX($AA$4:$AA$13,MATCH($N62&$Q62,$X$4:$X$13&$Y$4:$Y$13,0)),2)} -> 59.77
A63: SHP202603-0060 | B63: Outbound | C63: 46106 | D63: 46110 | E63: Planned | I63: CFS_IN_NHAV | J63: LTE | K63: CUS0074 | N63: Road | O63: EXW | P63: Standard | Q63: Domestic | R63: Invoice;Ewaybill;COA | S63: LSP011 | T63: LPO202603-0060 | U63: {=ROUND(SUMIF(Movements!$B$5:$B$329,$A63,Movements!$F$5:$F$329)*INDEX($Z$4:$Z$13,MATCH($N63&$Q63,$X$4:$X$13&$Y$4:$Y$13,0))+INDEX($AA$4:$AA$13,MATCH($N63&$Q63,$X$4:$X$13&$Y$4:$Y$13,0)),2)} -> 60.11
A64: SHP202603-0061 | B64: Outbound | C64: 46092 | D64: 46104 | E64: In Progress | F64: 46093 | I64: WH_IN_WEST_BHI | J64: LTE | K64: CUS0055 | L64: TNK_EUR_GEN | N64: Sea | O64: FOB | P64: DG | Q64: International | R64: Invoice;Packing List;COA;SDS;BL;IMDG Declaration;DG Packing Cert | S64: LSP023 | T64: LPO202603-0061 | U64: {=ROUND(SUMIF(Movements!$B$5:$B$329,$A64,Movements!$F$5:$F$329)*INDEX($Z$4:$Z$13,MATCH($N64&$Q64,$X$4:$X$13&$Y$4:$Y$13,0))+INDEX($AA$4:$AA$13,MATCH($N64&$Q64,$X$4:$X$13&$Y$4:$Y$13,0)),2)} -> 258.66
A65: SHP202603-0062 | B65: Inbound | C65: 46111 | D65: 46119 | E65: Planned | H65: Supplier - Domestic | L65: CFS_IN_NHAV | M65: LTE | N65: Rail | O65: FCA | P65: Standard | Q65: Domestic | R65: Invoice;Ewaybill;COA | S65: LSP027 | T65: LPO202603-0062 | U65: {=ROUND(SUMIF(Movements!$B$5:$B$329,$A65,Movements!$F$5:$F$329)*INDEX($Z$4:$Z$13,MATCH($N65&$Q65,$X$4:$X$13&$Y$4:$Y$13,0))+INDEX($AA$4:$AA$13,MATCH($N65&$Q65,$X$4:$X$13&$Y$4:$Y$13,0)),2)} -> 40
A66: SHP202603-0063 | B66: Inbound | C66: 46098 | D66: 46102 | E66: In Progress | F66: 46100 | H66: Supplier - Domestic | L66: WH_IN_WEST_BHI | M66: LTE | N66: Road | O66: FCA | P66: Standard | Q66: Domestic | R66: Invoice;Ewaybill;COA | S66: LSP028 | T66: LPO202603-0063 | U66: {=ROUND(SUMIF(Movements!$B$5:$B$329,$A66,Movements!$F$5:$F$329)*INDEX($Z$4:$Z$13,MATCH($N66&$Q66,$X$4:$X$13&$Y$4:$Y$13,0))+INDEX($AA$4:$AA$13,MATCH($N66&$Q66,$X$4:$X$13&$Y$4:$Y$13,0)),2)} -> 50
A67: SHP202603-0064 | B67: Outbound | C67: 46091 | D67: 46098 | E67: In Progress | F67: 46092 | I67: WH_IN_NORTH_BAW | J67: LTE | K67: CUS0099 | N67: Road | O67: FCA | P67: Standard | Q67: Domestic | R67: Invoice;Ewaybill;COA | S67: LSP021 | T67: LPO202603-0064 | U67: {=ROUND(SUMIF(Movements!$B$5:$B$329,$A67,Movements!$F$5:$F$329)*INDEX($Z$4:$Z$13,MATCH($N67&$Q67,$X$4:$X$13&$Y$4:$Y$13,0))+INDEX($AA$4:$AA$13,MATCH($N67&$Q67,$X$4:$X$13&$Y$4:$Y$13,0)),2)} -> 77.16
A68: SHP202603-0065 | B68: Transfer | C68: 46110 | D68: 46116 | E68: Planned | I68: WH_IN_SOUTH_HYD | L68: WH_UAE_SHJ | N68: Multimodal | O68: CIF | P68: DG | Q68: International | R68: Invoice;Packing List;COA;SDS;BL;IMDG Declaration;DG Packing Cert | S68: LSP029 | T68: LPO202603-0065 | U68: {=ROUND(SUMIF(Movements!$B$5:$B$329,$A68,Movements!$F$5:$F$329)*INDEX($Z$4:$Z$13,MATCH($N68&$Q68,$X$4:$X$13&$Y$4:$Y$13,0))+INDEX($AA$4:$AA$13,MATCH($N68&$Q68,$X$4:$X$13&$Y$4:$Y$13,0)),2)} -> 221.77
A69: SHP202603-0066 | B69: Inbound | C69: 46093 | D69: 46099 | E69: In Progress | F69: 46092 | H69: Supplier - Domestic | L69: CFS_IN_NHAV | M69: LTE | N69: Multimodal | O69: FCA | P69: Standard | Q69: Domestic | R69: Invoice;Ewaybill;COA | S69: LSP018 | T69: LPO202603-0066 | U69: {=ROUND(SUMIF(Movements!$B$5:$B$329,$A69,Movements!$F$5:$F$329)*INDEX($Z$4:$Z$13,MATCH($N69&$Q69,$X$4:$X$13&$Y$4:$Y$13,0))+INDEX($AA$4:$AA$13,MATCH($N69&$Q69,$X$4:$X$13&$Y$4:$Y$13,0)),2)} -> 80
A70: SHP202603-0067 | B70: Outbound | C70: 46092 | D70: 46093 | E70: Planned | I70: WH_IN_SOUTH_HYD | J70: LTE | K70: CUS0057 | L70: TNK_EUR_RTM | N70: Multimodal | O70: DDP | P70: Standard | Q70: International | R70: Invoice;Packing List;COA;SDS;BL;Import Clearance | S70: LSP006 | T70: LPO202603-0067 | U70: {=ROUND(SUMIF(Movements!$B$5:$B$329,$A70,Movements!$F$5:$F$329)*INDEX($Z$4:$Z$13,MATCH($N70&$Q70,$X$4:$X$13&$Y$4:$Y$13,0))+INDEX($AA$4:$AA$13,MATCH($N70&$Q70,$X$4:$X$13&$Y$4:$Y$13,0)),2)} -> 222.89
A71: SHP202603-0068 | B71: Outbound | C71: 46098 | D71: 46112 | E71: Delivered | F71: 46100 | G71: 46111 | I71: WH_IN_SOUTH_HYD | J71: LTE | K71: CUS0038 | N71: Road | O71: FCA | P71: Standard | Q71: Domestic | R71: Invoice;Ewaybill;COA | S71: LSP003 | T71: LPO202603-0068 | U71: {=ROUND(SUMIF(Movements!$B$5:$B$329,$A71,Movements!$F$5:$F$329)*INDEX($Z$4:$Z$13,MATCH($N71&$Q71,$X$4:$X$13&$Y$4:$Y$13,0))+INDEX($AA$4:$AA$13,MATCH($N71&$Q71,$X$4:$X$13&$Y$4:$Y$13,0)),2)} -> 50 | V71: https://pod.example.com/SHP202603-0068.pdf
A72: SHP202603-0069 | B72: Outbound | C72: 46096 | D72: 46103 | E72: In Progress | F72: 46096 | I72: WH_IN_SOUTH_HYD | J72: LTE | K72: CUS0015 | N72: Road | O72: FCA | P72: Standard | Q72: Domestic | R72: Invoice;Ewaybill;COA | S72: LSP010 | T72: LPO202603-0069 | U72: {=ROUND(SUMIF(Movements!$B$5:$B$329,$A72,Movements!$F$5:$F$329)*INDEX($Z$4:$Z$13,MATCH($N72&$Q72,$X$4:$X$13&$Y$4:$Y$13,0))+INDEX($AA$4:$AA$13,MATCH($N72&$Q72,$X$4:$X$13&$Y$4:$Y$13,0)),2)} -> 61.49
A73: SHP202603-0070 | B73: Outbound | C73: 46085 | D73: 46090 | E73: Delivered | F73: 46085 | G73: 46091 | I73: CFS_IN_NHAV | J73: LTE | K73: CUS0064 | L73: TNK_EUR_GEN | N73: Sea | O73: FOB | P73: DG | Q73: International | R73: Invoice;Packing List;COA;SDS;BL;IMDG Declaration;DG Packing Cert | S73: LSP020 | T73: LPO202603-0070 | U73: {=ROUND(SUMIF(Movements!$B$5:$B$329,$A73,Movements!$F$5:$F$329)*INDEX($Z$4:$Z$13,MATCH($N73&$Q73,$X$4:$X$13&$Y$4:$Y$13,0))+INDEX($AA$4:$AA$13,MATCH($N73&$Q73,$X$4:$X$13&$Y$4:$Y$13,0)),2)} -> 250 | V73: https://pod.example.com/SHP202603-0070.pdf
A74: SHP202603-0071 | B74: Outbound | C74: 46102 | D74: 46117 | E74: In Progress | F74: 46101 | I74: CFS_IN_NHAV | J74: LTE | K74: CUS0082 | N74: Road | O74: FCA | P74: DG | Q74: Domestic | R74: Invoice;Ewaybill;COA;IMDG Declaration;DG Packing Cert | S74: LSP005 | T74: LPO202603-0071 | U74: {=ROUND(SUMIF(Movements!$B$5:$B$329,$A74,Movements!$F$5:$F$329)*INDEX($Z$4:$Z$13,MATCH($N74&$Q74,$X$4:$X$13&$Y$4:$Y$13,0))+INDEX($AA$4:$AA$13,MATCH($N74&$Q74,$X$4:$X$13&$Y$4:$Y$13,0)),2)} -> 60.87
A75: SHP202603-0072 | B75: Outbound | C75: 46104 | D75: 46109 | E75: Planned | I75: WH_IN_SOUTH_HYD | J75: MHD | K75: CUS0016 | L75: WH_UAE_SHJ | N75: Sea | O75: CFR | P75: DG,Customs | Q75: International | R75: Invoice;Packing List;COA;SDS;BL;IMDG Declaration;DG Packing Cert | S75: LSP002 | T75: LPO202603-0072 | U75: {=ROUND(SUMIF(Movements!$B$5:$B$329,$A75,Movements!$F$5:$F$329)*INDEX($Z$4:$Z$13,MATCH($N75&$Q75,$X$4:$X$13&$Y$4:$Y$13,0))+INDEX($AA$4:$AA$13,MATCH($N75&$Q75,$X$4:$X$13&$Y$4:$Y$13,0)),2)} -> 281.95
A76: SHP202603-0073 | B76: Outbound | C76: 46102 | D76: 46105 | E76: Planned | I76: CFS_IN_NHAV | J76: LTE | K76: CUS0061 | L76: TNK_EUR_ANT | N76: Sea | O76: CIF | P76: Standard | Q76: International | R76: Invoice;Packing List;COA;SDS;BL | S76: LSP016 | T76: LPO202603-0073 | U76: {=ROUND(SUMIF(Movements!$B$5:$B$329,$A76,Movements!$F$5:$F$329)*INDEX($Z$4:$Z$13,MATCH($N76&$Q76,$X$4:$X$13&$Y$4:$Y$13,0))+INDEX($AA$4:$AA$13,MATCH($N76&$Q76,$X$4:$X$13&$Y$4:$Y$13,0)),2)} -> 259.33
A77: SHP202603-0074 | B77: Outbound | C77: 46097 | D77: 46103 | E77: Planned | I77: WH_IN_WEST_BHI | J77: MHD | K77: CUS0089 | L77: WH_US_EAST_NJ | N77: Sea | O77: DDP | P77: DG,Customs | Q77: International | R77: Invoice;Packing List;COA;SDS;BL;IMDG Declaration;DG Packing Cert;Import Clearance | S77: LSP022 | T77: LPO202603-0074 | U77: {=ROUND(SUMIF(Movements!$B$5:$B$329,$A77,Movements!$F$5:$F$329)*INDEX($Z$4:$Z$13,MATCH($N77&$Q77,$X$4:$X$13&$Y$4:$Y$13,0))+INDEX($AA$4:$AA$13,MATCH($N77&$Q77,$X$4:$X$13&$Y$4:$Y$13,0)),2)} -> 267.3
A78: SHP202603-0075 | B78: Inbound | C78: 46105 | D78: 46109 | E78: Planned | H78: Supplier - Domestic | L78: WH_IN_NORTH_BAW | M78: MHD | N78: Road | O78: FCA | P78: Standard | Q78: Domestic | R78: Invoice;Ewaybill;COA | S78: LSP034 | T78: LPO202603-0075 | U78: {=ROUND(SUMIF(Movements!$B$5:$B$329,$A78,Movements!$F$5:$F$329)*INDEX($Z$4:$Z$13,MATCH($N78&$Q78,$X$4:$X$13&$Y$4:$Y$13,0))+INDEX($AA$4:$AA$13,MATCH($N78&$Q78,$X$4:$X$13&$Y$4:$Y$13,0)),2)} -> 54.58
A79: SHP202603-0076 | B79: Outbound | C79: 46100 | D79: 46102 | E79: In Progress | F79: 46102 | I79: WH_IN_SOUTH_HYD | J79: MHD | K79: CUS0100 | N79: Road | O79: EXW | P79: Standard | Q79: Domestic | R79: Invoice;Ewaybill;COA | S79: LSP023 | T79: LPO202603-0076 | U79: {=ROUND(SUMIF(Movements!$B$5:$B$329,$A79,Movements!$F$5:$F$329)*INDEX($Z$4:$Z$13,MATCH($N79&$Q79,$X$4:$X$13&$Y$4:$Y$13,0))+INDEX($AA$4:$AA$13,MATCH($N79&$Q79,$X$4:$X$13&$Y$4:$Y$13,0)),2)} -> 60.92
A80: SHP202603-0077 | B80: Outbound | C80: 46107 | D80: 46112 | E80: Planned | I80: CFS_IN_NHAV | J80: MHD | K80: CUS0002 | L80: WH_US_MID_CHI | N80: Sea | O80: CIF | P80: Standard | Q80: International | R80: Invoice;Packing List;COA;SDS;BL | S80: LSP009 | T80: LPO202603-0077 | U80: {=ROUND(SUMIF(Movements!$B$5:$B$329,$A80,Movements!$F$5:$F$329)*INDEX($Z$4:$Z$13,MATCH($N80&$Q80,$X$4:$X$13&$Y$4:$Y$13,0))+INDEX($AA$4:$AA$13,MATCH($N80&$Q80,$X$4:$X$13&$Y$4:$Y$13,0)),2)} -> 250
A81: SHP202603-0078 | B81: Inbound | C81: 46098 | D81: 46101 | E81: In Progress | F81: 46097 | H81: Supplier - Domestic | L81: CFS_IN_NHAV | M81: LTE | N81: Road | O81: FCA | P81: Standard | Q81: Domestic | R81: Invoice;Ewaybill;COA | S81: LSP017 | T81: LPO202603-0078 | U81: {=ROUND(SUMIF(Movements!$B$5:$B$329,$A81,Movements!$F$5:$F$329)*INDEX($Z$4:$Z$13,MATCH($N81&$Q81,$X$4:$X$13&$Y$4:$Y$13,0))+INDEX($AA$4:$AA$13,MATCH($N81&$Q81,$X$4:$X$13&$Y$4:$Y$13,0)),2)} -> 61.04
A82: SHP202603-0079 | B82: Outbound | C82: 46101 | D82: 46108 | E82: Planned | I82: CFS_IN_NHAV | J82: MHD | K82: CUS0075 | N82: Multimodal | O82: FCA | P82: Standard | Q82: Domestic | R82: Invoice;Ewaybill;COA | S82: LSP017 | T82: LPO202603-0079 | U82: {=ROUND(SUMIF(Movements!$B$5:$B$329,$A82,Movements!$F$5:$F$329)*INDEX($Z$4:$Z$13,MATCH($N82&$Q82,$X$4:$X$13&$Y$4:$Y$13,0))+INDEX($AA$4:$AA$13,MATCH($N82&$Q82,$X$4:$X$13&$Y$4:$Y$13,0)),2)} -> 92.6
A83: SHP202603-0080 | B83: Transfer | C83: 46083 | D83: 46095 | E83: In Progress | F83: 46085 | I83: WH_IN_NORTH_BAW | L83: WH_IN_WEST_BHI | N83: Road | O83: FCA | P83: Standard | Q83: Domestic | R83: Invoice;Ewaybill;COA | S83: LSP009 | T83: LPO202603-0080 | U83: {=ROUND(SUMIF(Movements!$B$5:$B$329,$A83,Movements!$F$5:$F$329)*INDEX($Z$4:$Z$13,MATCH($N83&$Q83,$X$4:$X$13&$Y$4:$Y$13,0))+INDEX($AA$4:$AA$13,MATCH($N83&$Q83,$X$4:$X$13&$Y$4:$Y$13,0)),2)} -> 55.08
A84: SHP202603-0081 | B84: Outbound | C84: 46100 | D84: 46101 | E84: In Progress | F84: 46100 | I84: CFS_IN_NHAV | J84: MHD | K84: CUS0002 | L84: WH_US_EAST_NJ | N84: Sea | O84: FOB | P84: Customs | Q84: International | R84: Invoice;Packing List;COA;SDS;BL | S84: LSP031 | T84: LPO202603-0081 | U84: {=ROUND(SUMIF(Movements!$B$5:$B$329,$A84,Movements!$F$5:$F$329)*INDEX($Z$4:$Z$13,MATCH($N84&$Q84,$X$4:$X$13&$Y$4:$Y$13,0))+INDEX($AA$4:$AA$13,MATCH($N84&$Q84,$X$4:$X$13&$Y$4:$Y$13,0)),2)} -> 267.58
A85: SHP202603-0082 | B85: Inbound | C85: 46097 | D85: 46099 | E85: Planned | H85: Supplier - Domestic | L85: CFS_IN_NHAV | M85: LTE | N85: Rail | O85: FCA | P85: Standard | Q85: Domestic | R85: Invoice;Ewaybill;COA | S85: LSP027 | T85: LPO202603-0082 | U85: {=ROUND(SUMIF(Movements!$B$5:$B$329,$A85,Movements!$F$5:$F$329)*INDEX($Z$4:$Z$13,MATCH($N85&$Q85,$X$4:$X$13&$Y$4:$Y$13,0))+INDEX($AA$4:$AA$13,MATCH($N85&$Q85,$X$4:$X$13&$Y$4:$Y$13,0)),2)} -> 40
A86: SHP202603-0083 | B86: Transfer | C86: 46105 | D86: 46112 | E86: Planned | I86: WH_IN_SOUTH_HYD | J86: LTE | L86: WH_US_EAST_NJ | N86: Air | O86: CIF | P86: Customs | Q86: International | R86: Invoice;Packing List;COA;SDS;BL | S86: LSP004 | T86: LPO202603-0083 | U86: {=ROUND(SUMIF(Movements!$B$5:$B$329,$A86,Movements!$F$5:$F$329)*INDEX($Z$4:$Z$13,MATCH($N86&$Q86,$X$4:$X$13&$Y$4:$Y$13,0))+INDEX($AA$4:$AA$13,MATCH($N86&$Q86,$X$4:$X$13&$Y$4:$Y$13,0)),2)} -> 1250.86
A87: SHP202603-0084 | B87: Inbound | C87: 46111 | D87: 46119 | E87: Planned | H87: Supplier - Domestic | L87: WH_IN_WEST_BHI | M87: DST | N87: Road | O87: FCA | P87: DG | Q87: Domestic | R87: Invoice;Ewaybill;COA;IMDG Declaration;DG Packing Cert | S87: LSP034 | T87: LPO202603-0084 | U87: {=ROUND(SUMIF(Movements!$B$5:$B$329,$A87,Movements!$F$5:$F$329)*INDEX($Z$4:$Z$13,MATCH($N87&$Q87,$X$4:$X$13&$Y$4:$Y$13,0))+INDEX($AA$4:$AA$13,MATCH($N87&$Q87,$X$4:$X$13&$Y$4:$Y$13,0)),2)} -> 55.65
A88: SHP202603-0085 | B88: Outbound | C88: 46109 | D88: 46113 | E88: Planned | I88: CFS_IN_NHAV | J88: MHD | K88: CUS0095 | N88: Road | O88: EXW | P88: DG | Q88: Domestic | R88: Invoice;Ewaybill;COA;IMDG Declaration;DG Packing Cert | S88: LSP035 | T88: LPO202603-0085 | U88: {=ROUND(SUMIF(Movements!$B$5:$B$329,$A88,Movements!$F$5:$F$329)*INDEX($Z$4:$Z$13,MATCH($N88&$Q88,$X$4:$X$13&$Y$4:$Y$13,0))+INDEX($AA$4:$AA$13,MATCH($N88&$Q88,$X$4:$X$13&$Y$4:$Y$13,0)),2)} -> 60.38
A89: SHP202603-0086 | B89: Outbound | C89: 46086 | D89: 46089 | E89: Delivered | F89: 46086 | G89: 46091 | I89: WH_IN_NORTH_BAW | J89: LTE | K89: CUS0083 | N89: Road | O89: FCA | P89: Standard | Q89: Domestic | R89: Invoice;Ewaybill;COA | S89: LSP034 | T89: LPO202603-0086 | U89: {=ROUND(SUMIF(Movements!$B$5:$B$329,$A89,Movements!$F$5:$F$329)*INDEX($Z$4:$Z$13,MATCH($N89&$Q89,$X$4:$X$13&$Y$4:$Y$13,0))+INDEX($AA$4:$AA$13,MATCH($N89&$Q89,$X$4:$X$13&$Y$4:$Y$13,0)),2)} -> 50 | V89: https://pod.example.com/SHP202603-0086.pdf
A90: SHP202603-0087 | B90: Transfer | C90: 46094 | D90: 46098 | E90: In Progress | F90: 46093 | I90: CFS_IN_NHAV | L90: TNK_EUR_ANT | N90: Sea | O90: CIF | P90: Standard | Q90: International | R90: Invoice;Packing List;COA;SDS;BL | S90: LSP010 | T90: LPO202603-0087 | U90: {=ROUND(SUMIF(Movements!$B$5:$B$329,$A90,Movements!$F$5:$F$329)*INDEX($Z$4:$Z$13,MATCH($N90&$Q90,$X$4:$X$13&$Y$4:$Y$13,0))+INDEX($AA$4:$AA$13,MATCH($N90&$Q90,$X$4:$X$13&$Y$4:$Y$13,0)),2)} -> 250
A91: SHP202603-0088 | B91: Transfer | C91: 46095 | D91: 46102 | E91: In Progress | F91: 46096 | I91: WH_IN_NORTH_BAW | J91: MHD | L91: WH_UAE_SHJ | N91: Air | O91: FOB | P91: Standard | Q91: International | R91: Invoice;Packing List;COA;SDS;BL | S91: LSP017 | T91: LPO202603-0088 | U91: {=ROUND(SUMIF(Movements!$B$5:$B$329,$A91,Movements!$F$5:$F$329)*INDEX($Z$4:$Z$13,MATCH($N91&$Q91,$X$4:$X$13&$Y$4:$Y$13,0))+INDEX($AA$4:$AA$13,MATCH($N91&$Q91,$X$4:$X$13&$Y$4:$Y$13,0)),2)} -> 350
A92: SHP202603-0089 | B92: Outbound | C92: 46112 | D92: 46114 | E92: Planned | I92: CFS_IN_NHAV | J92: MHD | K92: CUS0067 | L92: TNK_EUR_RTM | N92: Sea | O92: CFR | P92: Standard | Q92: International | R92: Invoice;Packing List;COA;SDS;BL | S92: LSP009 | T92: LPO202603-0089 | U92: {=ROUND(SUMIF(Movements!$B$5:$B$329,$A92,Movements!$F$5:$F$329)*INDEX($Z$4:$Z$13,MATCH($N92&$Q92,$X$4:$X$13&$Y$4:$Y$13,0))+INDEX($AA$4:$AA$13,MATCH($N92&$Q92,$X$4:$X$13&$Y$4:$Y$13,0)),2)} -> 265.31
A93: SHP202603-0090 | B93: Outbound | C93: 46086 | D93: 46092 | E93: Delivered | F93: 46087 | G93: 46092 | I93: CFS_IN_NHAV | J93: LTE | K93: CUS0018 | L93: WH_US_MID_CHI | N93: Sea | O93: DDP | P93: DG,Customs | Q93: International | R93: Invoice;Packing List;COA;SDS;BL;IMDG Declaration;DG Packing Cert;Import Clearance | S93: LSP025 | T93: LPO202603-0090 | U93: {=ROUND(SUMIF(Movements!$B$5:$B$329,$A93,Movements!$F$5:$F$329)*INDEX($Z$4:$Z$13,MATCH($N93&$Q93,$X$4:$X$13&$Y$4:$Y$13,0))+INDEX($AA$4:$AA$13,MATCH($N93&$Q93,$X$4:$X$13&$Y$4:$Y$13,0)),2)} -> 258.39 | V93: https://pod.example.com/SHP202603-0090.pdf
A94: SHP202603-0091 | B94: Outbound | C94: 46082 | D94: 46090 | E94: Delivered | F94: 46081 | G94: 46088 | I94: CFS_IN_NHAV | J94: MHD | K94: CUS0028 | N94: Road | O94: FCA | P94: DG | Q94: Domestic | R94: Invoice;Ewaybill;COA;IMDG Declaration;DG Packing Cert | S94: LSP020 | T94: LPO202603-0091 | U94: {=ROUND(SUMIF(Movements!$B$5:$B$329,$A94,Movements!$F$5:$F$329)*INDEX($Z$4:$Z$13,MATCH($N94&$Q94,$X$4:$X$13&$Y$4:$Y$13,0))+INDEX($AA$4:$AA$13,MATCH($N94&$Q94,$X$4:$X$13&$Y$4:$Y$13,0)),2)} -> 50
A95: SHP202603-0092 | B95: Outbound | C95: 46094 | D95: 46107 | E95: Planned | I95: WH_IN_WEST_BHI | J95: LTE | K95: CUS0097 | L95: TNK_EUR_RTM | N95: Sea | O95: FOB | P95: DG,Customs | Q95: International | R95: Invoice;Packing List;COA;SDS;BL;IMDG Declaration;DG Packing Cert | S95: LSP004 | T95: LPO202603-0092 | U95: {=ROUND(SUMIF(Movements!$B$5:$B$329,$A95,Movements!$F$5:$F$329)*INDEX($Z$4:$Z$13,MATCH($N95&$Q95,$X$4:$X$13&$Y$4:$Y$13,0))+INDEX($AA$4:$AA$13,MATCH($N95&$Q95,$X$4:$X$13&$Y$4:$Y$13,0)),2)} -> 266.36
A96: SHP202603-0093 | B96: Outbound | C96: 46100 | D96: 46105 | E96: Delivered | F96: 46101 | G96: 46107 | I96: WH_IN_NORTH_BAW | J96: MHD | K96: CUS0082 | L96: TNK_EUR_ANT | N96: Sea | O96: DDP | P96: Temp-Control | Q96: International | R96: Invoice;Packing List;COA;SDS;BL;Import Clearance | S96: LSP016 | T96: LPO202603-0093 | U96: {=ROUND(SUMIF(Movements!$B$5:$B$329,$A96,Movements!$F$5:$F$329)*INDEX($Z$4:$Z$13,MATCH($N96&$Q96,$X$4:$X$13&$Y$4:$Y$13,0))+INDEX($AA$4:$AA$13,MATCH($N96&$Q96,$X$4:$X$13&$Y$4:$Y$13,0)),2)} -> 266.28
A97: SHP202603-0094 | B97: Inbound | C97: 46101 | D97: 46109 | E97: Delivered | F97: 46103 | G97: 46108 | H97: Supplier - Domestic | L97: WH_IN_GUJ_AHD | M97: LTE | N97: Rail | O97: FCA | P97: DG | Q97: Domestic | R97: Invoice;Ewaybill;COA;IMDG Declaration;DG Packing Cert | S97: LSP024 | T97: LPO202603-0094 | U97: {=ROUND(SUMIF(Movements!$B$5:$B$329,$A97,Movements!$F$5:$F$329)*INDEX($Z$4:$Z$13,MATCH($N97&$Q97,$X$4:$X$13&$Y$4:$Y$13,0))+INDEX($AA$4:$AA$13,MATCH($N97&$Q97,$X$4:$X$13&$Y$4:$Y$13,0)),2)} -> 40 | V97: https://pod.example.com/SHP202603-0094.pdf
A98: SHP202603-0095 | B98: Outbound | C98: 46108 | D98: 46116 | E98: Planned | I98: CFS_IN_NHAV | J98: MHD | K98: CUS0091 | N98: Road | O98: EXW | P98: Standard | Q98: Domestic | R98: Invoice;Ewaybill;COA | S98: LSP032 | T98: LPO202603-0095 | U98: {=ROUND(SUMIF(Movements!$B$5:$B$329,$A98,Movements!$F$5:$F$329)*INDEX($Z$4:$Z$13,MATCH($N98&$Q98,$X$4:$X$13&$Y$4:$Y$13,0))+INDEX($AA$4:$AA$13,MATCH($N98&$Q98,$X$4:$X$13&$Y$4:$Y$13,0)),2)} -> 55.18
A99: SHP202603-0096 | B99: Outbound | C99: 46111 | D99: 46117 | E99: In Progress | F99: 46111 | I99: WH_IN_SOUTH_HYD | J99: MHD | K99: CUS0028 | L99: TNK_EUR_ANT | N99: Multimodal | O99: DDP | P99: Standard | Q99: International | R99: Invoice;Packing List;COA;SDS;BL;Import Clearance | S99: LSP018 | T99: LPO202603-0096 | U99: {=ROUND(SUMIF(Movements!$B$5:$B$329,$A99,Movements!$F$5:$F$329)*INDEX($Z$4:$Z$13,MATCH($N99&$Q99,$X$4:$X$13&$Y$4:$Y$13,0))+INDEX($AA$4:$AA$13,MATCH($N99&$Q99,$X$4:$X$13&$Y$4:$Y$13,0)),2)} -> 200
A100: SHP202603-0097 | B100: Transfer | C100: 46102 | D100: 46113 | E100: In Progress | F100: 46104 | I100: CFS_IN_NHAV | L100: WH_UAE_SHJ | N100: Sea | O100: CFR | P100: Customs | Q100: International | R100: Invoice;Packing List;COA;SDS;BL | S100: LSP018 | T100: LPO202603-0097 | U100: {=ROUND(SUMIF(Movements!$B$5:$B$329,$A100,Movements!$F$5:$F$329)*INDEX($Z$4:$Z$13,MATCH($N100&$Q100,$X$4:$X$13&$Y$4:$Y$13,0))+INDEX($AA$4:$AA$13,MATCH($N100&$Q100,$X$4:$X$13&$Y$4:$Y$13,0)),2)} -> 273.71
...

Sheet Movements
A1: Mean | B1: 66.67
A2: Std Dev | B2: 0.1
A3: Total per month / No. of entries | B3: 325
A4: Movement ID (PK) | B4: Shipment ID (FK) | C4: Batch No. (FK) | D4: Order ID (FK) | E4: PR Line ID (FK) | F4: Quantity
A5: MOV202603-0001 | B5: SHP202603-0009 | C5: BATFG202603-0255 | D5: ORD202602-0136 | F5: 68.68
A6: MOV202603-0002 | B6: SHP202603-0194 | C6: BATFG202603-0251 | D6: ORD202602-0132 | F6: 73.42
A7: MOV202603-0003 | B7: SHP202603-0001 | C7: BATFG202603-0112 | D7: ORD202602-0162 | F7: 57.96
A8: MOV202603-0004 | B8: SHP202603-0056 | C8: BATFG202603-0359 | D8: ORD202602-0045 | F8: 59.52
A9: MOV202603-0005 | B9: SHP202603-0004 | C9: BATFG202603-0379 | D9: ORD202602-0116 | F9: 63.5
A10: MOV202603-0006 | B10: SHP202603-0035 | C10: BATFG202603-0189 | D10: ORD202602-0022 | F10: 69.61
A11: MOV202603-0007 | B11: SHP202603-0060 | C11: BATFG202603-0070 | D11: ORD202602-0128 | F11: 72.78
A12: MOV202603-0008 | B12: SHP202603-0038 | C12: BATFG202603-0182 | D12: ORD202602-0122 | F12: 73.45
A13: MOV202603-0009 | B13: SHP202603-0089 | C13: BATFG202603-0329 | D13: ORD202602-0037 | F13: 64.42
A14: MOV202603-0010 | B14: SHP202603-0002 | C14: BATFG202603-0385 | D14: ORD202602-0048 | F14: 67.2
A15: MOV202603-0011 | B15: SHP202603-0205 | C15: BATFG202603-0007 | D15: ORD202602-0033 | F15: 62.38
A16: MOV202603-0012 | B16: SHP202603-0166 | C16: BATFG202603-0286 | D16: ORD202602-0039 | F16: 77.27
... A204: MOV202603-0200 | B204: SHP202603-0207 | C204: BATFG202603-0051 | D204: ORD202602-0110 | F204: 74.27
A205: MOV202603-0201 | B205: SHP202603-0142 | C205: BATRW202603-0053 | E205: PR202603-0113 | F205: 69.01
A206: MOV202603-0202 | B206: SHP202603-0033 | C206: BATRW202603-0050 | E206: PR202603-0096 | F206: 69.98
A207: MOV202603-0203 | B207: SHP202603-0164 | C207: BATRW202603-0064 | E207: PR202603-0133 | F207: 64.07
A208: MOV202603-0204 | B208: SHP202603-0218 | C208: BATRW202603-0006 | E208: PR202603-0014 | F208: 56.65
A209: MOV202603-0205 | B209: SHP202603-0149 | C209: BATRW202603-0003 | E209: PR202603-0013 | F209: 60.96
A210: MOV202603-0206 | B210: SHP202603-0152 | C210: BATRW202603-0020 | E210: PR202603-0036 | F210: 68.94
A211: MOV202603-0207 | B211: SHP202603-0156 | C211: BATRW202603-0064 | E211: PR202603-0133 | F211: 71.64
A212: MOV202603-0208 | B212: SHP202603-0218 | C212: BATRW202603-0054 | E212: PR202603-0113 | F212: 50.28
A213: MOV202603-0209 | B213: SHP202603-0036 | C213: BATRW202603-0071 | E213: PR202603-0152 | F213: 62.75
A214: MOV202603-0210 | B214: SHP202603-0202 | C214: BATRW202603-0043 | E214: PR202603-0093 | F214: 64.3
A215: MOV202603-0211 | B215: SHP202603-0084 | C215: BATRW202603-0077 | E215: PR202603-0155 | F215: 70.58
A216: MOV202603-0212 | B216: SHP202603-0017 | C216: BATRW202603-0050 | E216: PR202603-0096 | F216: 70.55
... A299: MOV202603-0295 | B299: SHP202603-0012 | C299: BATRW202603-0019 | E299: PR202603-0036 | F299: 64.97
A300: MOV202603-0296 | B300: SHP202603-0215 | C300: BATFG202603-0215 | F300: 54.14
A301: MOV202603-0297 | B301: SHP202603-0141 | C301: BATFG202603-0133 | F301: 73.1
A302: MOV202603-0298 | B302: SHP202603-0106 | C302: BATFG202603-0137 | F302: 71.32
A303: MOV202603-0299 | B303: SHP202603-0083 | C303: BATFG202603-0144 | F303: 67.97
A304: MOV202603-0300 | B304: SHP202603-0170 | C304: BATFG202603-0105 | F304: 73.08
A305: MOV202603-0301 | B305: SHP202603-0015 | C305: BATFG202603-0072 | F305: 70.26
A306: MOV202603-0302 | B306: SHP202603-0184 | C306: BATFG202603-0252 | F306: 62.53
A307: MOV202603-0303 | B307: SHP202603-0080 | C307: BATFG202603-0161 | F307: 63.56
A308: MOV202603-0304 | B308: SHP202603-0107 | C308: BATFG202603-0006 | F308: 67.54
A309: MOV202603-0305 | B309: SHP202603-0126 | C309: BATFG202603-0064 | F309: 62.47
A310: MOV202603-0306 | B310: SHP202603-0154 | C310: BATFG202603-0381 | F310: 71.85
A311: MOV202603-0307 | B311: SHP202603-0016 | C311: BATFG202603-0298 | F311: 65.4
... A329: MOV202603-0325 | B329: SHP202603-0083 | C329: BATFG202603-0130 | F329: 66.3

Sheet Exceptions
A1: No restriction on number of exceptions
A2: Exception ID (Primary Key) | B2: Exception Type | C2: Severity Level | D2: Probability | E2: Confidence | F2: Impacted Entities | G2: Impacted KPIs | H2: Magnitude | I2: Time Horizon | J2: Root Cause Hypotheses | K2: Alerted Stakeholders | L2: Current Status | M2: Resolution Summary | N2: AttachmentsURL | O2: Lessons ID (FK)
A3: EXC202602-0001 | B3: Logistics delay | C3: Medium | D3: 0.62 | E3: 0.86 | F3: Shipments,Orders,Movements | G3: OTIF,Transit Time | H3: 8-15% impact | I3: 3-10 days | J3: JNPT gate-in congestion; DG yard slot constraints | K3: Team-Intl,Team-Strategic,Logistics | L3: Mitigating | M3: Advanced documentation cut-off; shifted some cargo to earlier sailings | N3: https://docs.example.com/exc/EXC202602-0001.pdf | O3: LES202602-0001
A4: EXC202602-0002 | B4: Demand spike | C4: Low | D4: 0.48 | E4: 0.71 | F4: Orders,Order_Line Items,Forecasts | G4: Fill Rate,Backorder Days | H4: 1-3% impact | I4: 3-10 days | J4: Distributor pulled forward volumes due to seasonal demand | K4: Team-West,Sales Ops | L4: Investigating | M4: Validated customer forecast; allocated available stock; monitor repeat pattern | N4: https://docs.example.com/exc/EXC202602-0002.pdf | O4: LES202602-0008
A5: EXC202602-0003 | B5: Supply disruption | C5: Medium | D5: 0.55 | E5: 0.8 | F5: ProductionRuns,Production Plan,PurchaseRequisitions | G5: Schedule Adherence,Throughput | H5: 1-3% impact | I5: 3-10 days | J5: DG packing bay capacity constrained at LTE; shift sequencing required | K5: Plant Ops,EHS,Supply Planning | L5: Mitigating | M5: Staggered campaigns; added weekend packing slot; prioritized export SKUs | N5: https://docs.example.com/exc/EXC202602-0003.pdf | O5: LES202602-0003
A6: EXC202602-0004 | B6: Logistics delay | C6: Medium | D6: 0.58 | E6: 0.82 | F6: Shipments,Storage Nodes,Bins | G6: Dock-to-Stock Time,Transit Time | H6: 1-3% impact | I6: 3-10 days | J6: Rotterdam terminal slot reduction for ISO tanks | K6: Team-Intl,Logistics | L6: Open | M6: Pre-booked ISO slots; moved one lot to TNK_EUR_ANT where feasible | N6: https://docs.example.com/exc/EXC202602-0004.pdf | O6: LES202602-0004
A7: EXC202602-0005 | B7: Logistics delay | C7: Low | D7: 0.44 | E7: 0.73 | F7: Shipments,Orders | G7: OTIF,Delivery Variance | H7: 1-3% impact | I7: 3-10 days | J7: US rail congestion impacting Midwest last-mile | K7: Team-Intl,Customer Service | L7: Mitigating | M7: Pre-positioned inventory to WH_US_MID_CHI; increased delivery buffers | N7: https://docs.example.com/exc/EXC202602-0005.pdf | O7: LES202602-0005
A8: EXC202602-0006 | B8: Regulatory | C8: High | D8: 0.36 | E8: 0.79 | F8: Orders,Shipments,Customers | G8: Documentation Accuracy,Clearance Time | H8: 8-15% impact | I8: 2-3 weeks | J8: Customer credit downgrade + compliance review for EU distributor | K8: Finance,Team-Intl,Legal | L8: Investigating | M8: Moved impacted orders to Net 15/Advance; initiated KYC refresh | N8: https://docs.example.com/exc/EXC202602-0006.pdf | O8: LES202602-0002
A9: EXC202602-0007 | B9: Logistics delay | C9: Low | D9: 0.41 | E9: 0.81 | F9: Shipments,Storage Nodes | G9: Dwell Time,OTIF | H9: 1-3% impact | I9: 3-10 days | J9: Sharjah bonded warehouse added DG segregation inspections | K9: Team-Intl,Logistics | L9: Mitigating | M9: Added 2-day buffer; prioritized non-DG loads; pre-cleared documentation | N9: https://docs.example.com/exc/EXC202602-0007.pdf | O9: LES202602-0007
A10: EXC202602-0008 | B10: Demand spike | C10: Low | D10: 0.52 | E10: 0.66 | F10: Orders,Order_Line Items | G10: OTIF,Fill Rate | H10: 1-3% impact | I10: 3-10 days | J10: Expedited request from domestic pharma customer for acetic anhydride | K10: Team-West,Customer Service,Plant Ops | L10: Resolved | M10: Pulled inventory from WH_IN_GUJ_AHD; dispatched under SLA_STD_DOM_T2 | N10: https://docs.example.com/exc/EXC202602-0008.pdf | O10: LES202602-0008
A11: EXC202602-0009 | B11: Regulatory | C11: Medium | D11: 0.47 | E11: 0.75 | F11: Shipments,Orders,SLA Profiles | G11: Documentation Accuracy,OTIF | H11: 1-3% impact | I11: 2-3 weeks | J11: EU REACH/CLP enforcement focus; SDS language and completeness checks | K11: Quality,Regulatory,Team-Intl | L11: Mitigating | M11: Completed SDS audit; updated templates; re-trained documentation team | N11: https://docs.example.com/exc/EXC202602-0009.pdf | O11: LES202602-0006
A12: EXC202602-0010 | B12: Logistics delay | C12: Low | D12: 0.43 | E12: 0.77 | F12: Shipments,Storage Nodes | G12: Cut-off Compliance,OTIF | H12: 1-3% impact | I12: 3-10 days | J12: Antwerp terminal weekend cut-off change for DG paperwork | K12: Team-Intl,Logistics | L12: Resolved | M12: Shifted document prep to T-48 hours; aligned booking windows | N12: https://docs.example.com/exc/EXC202602-0010.pdf | O12: LES202602-0010
A13: EXC202602-0011 | B13: Supply disruption | C13: Medium | D13: 0.5 | E13: 0.73 | F13: Orders,Accounts Receivable | G13: DSO,Credit Exposure | H13: 1-3% impact | I13: 3-10 days | J13: North India distributor payment delays affecting credit availability | K13: Finance,Team-North,Sales Ops | L13: Mitigating | M13: Moved new orders to Advance; set credit hold thresholds | N13: https://docs.example.com/exc/EXC202602-0011.pdf | O13: LES202602-0002
A14: EXC202602-0012 | B14: Quality hold | C14: Medium | D14: 0.39 | E14: 0.62 | F14: Orders,Shipments,Batches | G14: OTIF,Claims Rate | H14: 1-3% impact | I14: 3-10 days | J14: Customer requests 24h COA; lab turnaround constraint | K14: QA,Customer Service,Team-Intl | L14: Investigating | M14: Prioritized lab queue for export lots; implemented digital COA release | N14: https://docs.example.com/exc/EXC202602-0012.pdf | O14: LES202602-0009
... A19: EXC202602-0017 | B19: Regulatory | C19: Low | D19: 0.35 | E19: 0.6 | F19: Shipments,Orders | G19: Clearance Time,Documentation Accuracy | H19: 1-3% impact | I19: 3-10 days | J19: EU customer requested REACH dossier reference in shipping documents | K19: Regulatory,Documentation,Team-Intl | L19: Resolved | M19: Added REACH reference field to doc pack; verified TNK_EUR_ANT packets | N19: https://docs.example.com/exc/EXC202602-0017.pdf | O19: LES202602-0006

Sheet Lessons
A1: No restriction on number of lessons
A2: Lessons ID (Primary Key) | B2: Title | C2: Context | D2: Forecast ID (FK) | E2: What Happened | F2: Why it Happened | G2: Considered Alternatives | H2: Chosen Action | I2: Outcome Metrics | J2: Repeatability | K2: Preventive Guidelines | L2: Applicability | M2: Review ID (FK) | N2: Review By | O2: Attachments
A3: LES202602-0001 | B3: JNPT DG gate-in congestion playbook | C3: Linked to EXC202602-0001 (Logistics delay) impacting Shipments, Orders, Movements and OTIF/Transit Time. | D3: FC202602-DOM-ACETYL | E3: DG export containers missed preferred gate-in slots at CFS_IN_NHAV during peak congestion. | F3: Terminal congestion and DG yard slot constraints reduced throughput. | G3: Shift to alternate sailing; route via different port; split loads to non-DG where possible. | H3: Moved documentation cut-off to T-48 and pre-booked DG slots; staggered dispatches. | I3: OTIF +1.5pp vs prior week; dwell time -1.2 days; 0 document rejections. | J3: High (repeatable for peak weeks) | K3: Maintain DG pre-gate checklist; freeze docs 48h; confirm slot booking 72h prior. | L3: CFS_IN_NHAV, export shipments, DG loads | M3: REV202602-0005 | N3: Logistics Lead - Export | O3: https://docs.example.com/lessons/LES202602-0001.pdf
A4: LES202602-0002 | B4: Credit tightening rule for C-rated distributors | C4: Linked to EXC202602-0011 (Credit pressure) impacting Orders and DSO/Credit Exposure. | D4: FC202602-DOM-ACETYL | E4: Several North India distributor orders requested extended credit beyond approved limits. | F4: Collections lag and higher risk exposure for C-rated accounts. | G4: Continue Net 30; partial shipment; require bank guarantee. | H4: Moved C-rated new orders to Advance; Net 15 for B-rated until review. | I4: DSO -6 days for impacted accounts; bad debt risk reduced (qualitative). | J4: Medium | K4: Embed risk-based payment term rule in order entry; auto-flag overrides. | L4: Domestic distributors, credit policy | M4: REV202602-0006 | N4: Finance Controller | O4: https://docs.example.com/lessons/LES202602-0002.pdf
A5: LES202602-0003 | B5: DG packing slot reservation at LTE | C5: Linked to EXC202602-0003 (Supply disruption) impacting ProductionRuns/Production Plan and Schedule Adherence. | D5: FC202602-APAC-DKD | E5: DG packing capacity at LTE became a bottleneck for FLUORO/DKD export lots. | F5: Limited DG bay availability and uneven campaign sequencing. | G5: Outsource packing; defer lower margin lots; add overtime shifts. | H5: Reserved fixed DG packing windows and sequenced campaigns to match packing capacity. | I5: Schedule adherence +4pp; export backlog cleared in 5 days. | J5: High | K5: Create DG packing calendar; lock windows during weekly ops review; maintain safety stock of DG labels. | L5: LTE, FLUORO/DKD exports | M5: REV202602-0001 | N5: Plant Ops Head - LTE | O5: https://docs.example.com/lessons/LES202602-0003.pdf
A6: LES202602-0004 | B6: Rotterdam ISO slot pre-booking for bulk solvents | C6: Linked to EXC202602-0004 (Logistics delay) impacting Storage Nodes/Bins and dock-to-stock time. | D6: FC202602-EU-ACETYL | E6: ISO tank arrivals faced slot unavailability at TNK_EUR_RTM, extending dwell. | F6: Terminal slot reductions and clustering of arrivals. | G6: Divert to TNK_EUR_ANT; break bulk into drums; delay shipments. | H6: Pre-booked ISO slots 2 weeks ahead and spread arrivals across terminals. | I6: Dwell time -0.8 days; demurrage cost avoided on 2 loads. | J6: Medium | K6: Maintain forward slot bookings; align sailing schedules; set arrival caps per week. | L6: EU bulk lanes, TNK_EUR_* | M6: REV202602-0002 | N6: Intl Logistics Manager | O6: https://docs.example.com/lessons/LES202602-0004.pdf
A7: LES202602-0005 | B7: US Midwest buffer inventory strategy | C7: Linked to EXC202602-0005 (Logistics delay) impacting Shipments and OTIF/Delivery Variance. | D7: FC202602-AMER-ACETYL | E7: Inland delays increased risk of late deliveries to Midwest customers. | F7: Rail congestion and appointment constraints at WH_US_EAST_NJ. | G7: Air expedite; customer reschedule; ship direct to customer port. | H7: Pre-positioned inventory at WH_US_MID_CHI and increased lead time buffers. | I7: OTIF maintained at 93% for Midwest; expedite cost -18%. | J7: High | K7: Use dual-node inventory for AMER; monitor rail bulletins weekly; trigger buffer when risk rises. | L7: AMER distribution network | M7: REV202602-0002 | N7: Supply Planning Lead - AMER | O7: https://docs.example.com/lessons/LES202602-0005.pdf
A8: LES202602-0006 | B8: EU documentation pack quality for REACH focus | C8: Linked to EXC202602-0009 (Regulatory) impacting Documentation Accuracy and clearance time. | D8: FC202602-EU-ACETYL | E8: EU customers requested additional REACH/CLP references; increased document scrutiny. | F8: Regulatory enforcement focus and inconsistent document templates. | G8: Manual checks only; outsource documentation; delay shipments. | H8: Standardized templates and added pre-dispatch validation checklist. | I8: Doc accuracy 99.7% sustained; 0 clearance holds in Feb. | J8: High | K8: Maintain master SDS library; enforce version control; audit 5% of doc packs monthly. | L8: EU exports via TNK_EUR_* | M8: REV202602-0003 | N8: Regulatory Affairs Lead | O8: https://docs.example.com/lessons/LES202602-0006.pdf
A9: LES202602-0007 | B9: Sharjah DG inspection buffer rule | C9: Linked to EXC202602-0007 (Logistics delay) impacting dwell time and OTIF for MEA. | D9: FC202602-APAC-DKD | E9: Additional DG segregation inspections at WH_UAE_SHJ increased dwell. | F9: Operator introduced new inspection step without prior notice. | G9: Reroute via direct customer delivery; change LSP; send non-DG only. | H9: Added 2-day buffer for DG shipments and prioritized non-DG where feasible. | I9: No missed customer delivery windows; dwell stabilized at +0.5 days. | J9: Medium | K9: Maintain bonded node change log; confirm SOP changes with operators monthly. | L9: MEA/GCC lanes via WH_UAE_SHJ | M9: REV202602-0002 | N9: Logistics Coordinator - MEA | O9: https://docs.example.com/lessons/LES202602-0007.pdf
A10: LES202602-0008 | B10: Expedite protocol for domestic pharma acetic anhydride | C10: Linked to EXC202602-0008 (Demand spike) impacting Orders/Line items and OTIF. | D10: FC202602-DOM-ACETYL | E10: Customer required expedited delivery for acetic anhydride within SLA_STD_DOM_T2 window. | F10: Unplanned demand and limited ready stock at nearest node. | G10: Reject request; partial shipment; air move (not suitable). | H10: Reallocated stock to WH_IN_GUJ_AHD and prioritized dispatch with DG-compliant packing. | I10: Delivery met; OTIF retained; no quality deviations. | J10: High | K10: Keep safety stock for critical SKUs at regional warehouses; define expedite approval matrix. | L10: DOM pharma customers | M10: REV202602-0004 | N10: Customer Service Manager | O10: https://docs.example.com/lessons/LES202602-0008.pdf
A11: LES202602-0009 | B11: COA release within 24h for export pharma/high purity | C11: Linked to EXC202602-0012 (Quality hold risk) impacting OTIF and claims rate. | D11: FC202602-AMER-ACETYL | E11: COA turnaround expectations tightened for export customers; risk of shipment hold. | F11: Lab queue prioritization not aligned to shipment cut-offs. | G11: Hire temp analysts; delay dispatch; issue preliminary COA. | H11: Implemented lab priority queue for export lots and digital COA release workflow. | I11: COA TAT median 18h; holds reduced to 0 for Feb export lots. | J11: Medium | K11: Align lab schedule with shipping calendar; auto-alert if COA pending at T-12. | L11: Export shipments via CFS_IN_NHAV | M11: REV202602-0004 | N11: QA Lead | O11: https://docs.example.com/lessons/LES202602-0009.pdf
A12: LES202602-0010 | B12: Antwerp weekend DG cut-off compliance | C12: Linked to EXC202602-0010 (Logistics delay) impacting cut-off compliance and OTIF. | D12: FC202602-EU-ACETYL | E12: Weekend cut-off change caused risk of missing DG documentation deadline at TNK_EUR_ANT. | F12: Late document finalization and unclear ownership of DG declarations. | G12: Switch terminal; hold cargo; pay premium handling. | H12: Moved documentation completion to T-48 and assigned single owner for DG docs. | I12: 0 missed cut-offs after change; reduced rework incidents. | J12: High | K12: Maintain cut-off calendar; RACI for DG docs; pre-validate IMO declarations. | L12: EU terminals and DG shipments | M12: REV202602-0002 | N12: Documentation Lead | O12: https://docs.example.com/lessons/LES202602-0010.pdf
A13: LES202602-0011 | B13: Powder bagging maintenance mitigation | C13: Linked to EXC202602-0014 (Capacity/quality risk) impacting powder pack-out and fill rate. | D13: FC202602-DOM-ARYLIDE | E13: Dust collection maintenance reduced BAG25 pack-out capacity for powders. | F13: Maintenance scheduled during peak dispatch window. | G13: Delay commitments; outsource packing; run overtime after maintenance. | H13: Pre-packed prior week and shifted liquids forward; scheduled maintenance off-peak. | I13: No customer backorders; pack-out recovered within 3 days. | J13: Medium | K13: Maintenance planning must consider dispatch calendar; maintain pre-pack buffer for BAG25. | L13: Powder SKUs (ARYLIDE/FLUORO) | M13: REV202602-0001 | N13: Maintenance Planner | O13: https://docs.example.com/lessons/LES202602-0011.pdf
... A17: LES202602-0015 | B17: Dahej capacity assumption guardrail in planning | C17: Context from project risk note impacting capacity planning and forecast confidence. | D17: FC202602-DOM-ACETYL | E17: Dahej commissioning risks required removing DHJ capacity from near-term assumptions. | F17: Utility commissioning risk and dependency on external approvals. | G17: Assume partial DHJ start; add overtime at MHD/LTE; outsource production. | H17: Kept DHJ as planned only; built buffers at MHD/LTE and adjusted reservations. | I17: No capacity shortfall in Feb; clearer scenario planning for March. | J17: High | K17: Use scenario planning for greenfield projects; avoid committing capacity until gate criteria met. | L17: All planning cycles; capacity reservations | M17: REV202602-0003 | N17: Head - S&OP | O17: https://docs.example.com/lessons/LES202602-0015.pdf

Sheet Review Events
A1: Review Event ID (Primary Key) | B1: Review Type | C1: Frequency | D1: ScheduledDate | E1: Actual Held On Date | F1: Participants | G1: Agenda | H1: Minutes of the Meeting_Doc | I1: Decision Outcomes | J1: Follow Up Action | K1: Next Review Date
A2: REV202602-0001 | B2: Weekly Ops Review | C2: Weekly | D2: 46083 | E2: 46083 | F2: Plant Ops Lead; Supply Planning; QA; EHS | G2: Week-5 run adherence, DG packing slots, dispatch constraints | H2: https://minutes.example.com/rev/REV202602-0001.pdf | I2: Re-sequenced DKD/FLUORO campaigns; locked DG bay windows | J2: Issue updated daily production schedule by EOD; confirm DG labels | K2: 46297
A3: REV202602-0002 | B3: Weekly Ops Review | C3: Weekly | D3: 46297 | E3: 46297 | F3: Plant Ops Lead; Maintenance; Supply Planning; Logistics | G3: CFS gate-in risk, maintenance readiness, inventory balancing | H3: https://minutes.example.com/rev/REV202602-0002.pdf | I3: Pulled forward export stuffing by 48h; approved overtime for packing | J3: Advance documentation cut-off; allocate buffer stock to CFS_IN_NHAV | K3: 2026-02-17T00:00:00.000Z
A4: REV202602-0003 | B4: Monthly S&OP Review | C4: Monthly | D4: 2026-02-14T00:00:00.000Z | E4: 2026-02-14T00:00:00.000Z | F4: Sales Head; Supply Chain Head; Finance; Plant Heads; Logistics | G4: Feb demand vs plan, capacity, inventory, key exceptions | H4: https://minutes.example.com/rev/REV202602-0003.pdf | I4: Approved Feb supply plan; prioritized AMER acetyl exports; capped low-margin MEA | J4: Confirm allocation by region; update Forecasts assumptions for Mar | K4: 2026-03-14T00:00:00.000Z
A5: REV202602-0004 | B5: Weekly Ops Review | C5: Weekly | D5: 2026-02-17T00:00:00.000Z | E5: 2026-02-17T00:00:00.000Z | F5: Plant Ops Lead; QA; Warehouse Leads (WH_IN_WEST_BHI/WH_IN_GUJ_AHD) | G5: Quality release TAT, warehouse space, drum availability | H5: https://minutes.example.com/rev/REV202602-0004.pdf | I5: Increased COA release prioritization; reserved DR200_UN lot for export | J5: Set COA SLA to 24h for export lots; validate packaging supplier ETA | K5: 2026-02-24T00:00:00.000Z
A6: REV202602-0005 | B6: Post-mortem | C6: Ad-hoc | D6: 2026-02-20T00:00:00.000Z | E6: 2026-02-20T00:00:00.000Z | F6: Customer Service; Logistics; Documentation; Finance | G6: Review EXC202602-0001 JNPT delays and OTIF misses | H6: https://minutes.example.com/rev/REV202602-0005.pdf | I6: Added T-48 document freeze; implemented pre-gate-in checklist | J6: Create SOP for DG container handover; train team and audit weekly | K6: 46176
A7: REV202602-0006 | B7: Weekly Ops Review | C7: Weekly | D7: 2026-02-24T00:00:00.000Z | E7: 2026-02-24T00:00:00.000Z | F7: Supply Planning; Procurement; Plant Ops; LSP Manager | G7: Raw material receipts, PR aging, inbound lead-time deviations | H7: https://minutes.example.com/rev/REV202602-0006.pdf | I7: Expedite critical RM for DKD; approved alternate vendor for solvents | J7: Release priority POs; update Material Requirements Plan lead-times | K7: 46084
A8: REV202602-0007 | B8: Post-mortem | C8: Ad-hoc | D8: 2026-02-26T00:00:00.000Z | E8: 2026-02-26T00:00:00.000Z | F8: QA; Plant Ops; EHS; Customer Service | G8: Review ACE handling advisory and packaging integrity checks | H8: https://minutes.example.com/rev/REV202602-0007.pdf | I8: Implemented enhanced drum inspection; refreshed SOP and training | J8: Audit DR200_UN stock; document corrective actions in CAPA log | K8: 46359
A9: REV202602-0008 | B9: Monthly S&OP Review | C9: Monthly | D9: 2026-02-28T00:00:00.000Z | E9: 2026-02-28T00:00:00.000Z | F9: Sales Head; Supply Chain Head; Finance; Plant Heads; Intl Sales | G9: Month-end reconciliation, KPI review, March freeze and risks | H9: https://minutes.example.com/rev/REV202602-0008.pdf | I9: Frozen Mar capacity reservations; approved safety stock targets EU tanks | J9: Publish March master production schedule; align LSP bookings | K9: 2026-03-28T00:00:00.000Z

Sheet List of Roles
A1: S.No. | B1: Roles | C1: Level | D1: Description
A2: 1 | B2: Supply Chain Head / VP | C2: Central | D2: Central head of supply chain management; overlooking sales regions and plant locations
A3: 2 | B3: Head - Central Planning | C3: Central and functional | D3: Overlooks central planning - demand, supply & inventory planning
A4: 3 | B4: Plant Supply Chain Manager | C4: Plant | D4: Mini supply chain head of plant responsible for RM planning, scheduling, storage, FG dispatch
A5: 4 | B5: Regional Fulfilment Manager | C5: Sales region | D5: Responsible for region-wise customer service, order management, storage & distribution

Sheet Components Descriiption

Sheet Components and Features
A1: Features

Sheet KPI Structure
